Workbook
Name asd: #REF!
Name beta: #REF!
Name Book_Equity: [1]ABV!$B$28
Name CIQWBInfo: "{ ""CIQVersion"":""9.45.614.5792"" }"
Name Forecast: #REF!
Name Gross_Profit: '[2]Advanced Financial Analysis'!$9:$9
Name IQ_NAMES_REVISION_DATE_: "10/01/2018 15:52:08"
Name Sensitivity: '[2]Advanced Financial Analysis'!$D$49
Name SG_A: '[2]Advanced Financial Analysis'!$11:$11
Name Shares_Out: #REF!
Name Step_1: #REF!
Name Step_2: #REF!
Name Step_3: #REF!
Name Step_4: #REF!
Name Step_5: #REF!
Name Step_6: #REF!
Name Step1: #REF!
Name Step2: #REF!
Name Step3: #REF!
Name Step4: #REF!
Name Step5: #REF!
Name Step6: #REF!
Name Tax_Rate: [1]ABV!$B$29
Name Tax_Rate: [1]ABV!$B$29
Name Tax_Rate: [1]ABV!$B$29
Name Tax_Rate: [1]ABV!$B$29
Name Tax_Rate: #REF!

Sheet Cover
B2: Petrobras Valuation
B9: Prepared by Group 19 : Salma Regaieg - Mustapha Aziz Laroussi
B11: Model Guide | G11: Model Checks
C13: I. Outputs
H14: Valuation Date Check Issue | L14: =-Inputs!F98 -> 0
C15: II. Inputs & Assumptions
H16: Cash Flow Date Check Issue | L16: =Inputs!F99 -> 0
C17: III. DCF Valuation Model
H18: Terminal growth rate > WACC Check Issue | L18: =Inputs!F110 -> 0
C19: IV. Relative Comparables Valuation
H20: Balance Sheet Mismatch | L20: ='3-Statement Analysis'!R60 -> 0
C21: V. Ratios
C23: VI. Assumptions Source
C25: VII. Football Field Chart

Sheet Football Field Chart
B3: Football Field Chart
E36: Low | F36: Middle | G36: High
D37: DCF - Multiple Method | E37: =Outputs!H16 -> 18.049091 | F37: =Outputs!H15 -> 27.352756 | G37: =Outputs!H14 -> 39.983756
D38: DCF - Perpetuity Method | E38: =Outputs!I62 -> 20.178266 | F38: =Outputs!I61 -> 40.431239 | G38: =Outputs!I60 -> 68.740942
D39: Comparable Companies | E39: =Comparables!L27 -> 5.8859726 | F39: =G39-E39 -> 6.8815494 | G39: =Comparables!L29 -> 12.767522
D40: ="Average Valuation: "&TEXT(E40,"$0,00") -> Average Valuation: $037 | E40: =AVERAGE(E37:E38,G37:G38) -> 36.738014

Sheet Outputs
B3: Dashboard: Multiple Method
D6: Model Drivers Set To | L6: All figures in USD thousands unless stated
D9: Main Outputs 1 | L9: Selected Inputs
F11: Enterprise | G11: Equity | H11: Equity
F12: Value | G12: Value | H12: Per Share | L12: Terminal Multiple | O12: =+Inputs!$F$108 -> 6.9249444
F13: =Model!$J$395 -> 3.5778236e+08 | L13: WACC | O13: =Inputs!$L$84 -> 0.043493934
D14: =E60 -> Best Case | E14: 1 | F14: 5.2057994e+08 | G14: =F14-$O$14 -> 5.1533994e+08 | H14: =+G14/$O$15 -> 39.983756 | L14: Net Debt | N14: =O60 -> (End of 2024) | O14: =Inputs!$L$94 -> 5240000
D15: =E61 -> Base Case | E15: 2 | F15: 3.5778236e+08 | G15: =F15-$O$14 -> 3.5254236e+08 | H15: =+G15/$O$15 -> 27.352756 | L15: Shares Outstanding | N15: (FD 000) | O15: =Inputs!$F$105 -> 12888733
D16: =E62 -> Worst Case | E16: 3 | F16: 2.3786991e+08 | G16: =F16-$O$14 -> 2.3262991e+08 | H16: =+G16/$O$15 -> 18.049091 | L16: Current Stock Price | N16: (US$/sh) | O16: =Inputs!$F$106 -> 11.6
D20: Enterprise Value 1 | L20: Equity Value per Share
D22: Terminal Multiple | L22: Terminal Multiple
C23: =Model!$J$395 -> 3.5778236e+08 | D23: =E23-0.5 -> 5.9249444 | E23: =F23-0.5 -> 6.4249444 | F23: =+Inputs!$F$108 -> 6.9249444 | G23: =+F23+0.5 -> 7.4249444 | H23: =+G23+0.5 -> 7.9249444 | L23: =D23 -> 5.9249444 | M23: =E23 -> 6.4249444 | N23: =F23 -> 6.9249444 | O23: =G23 -> 7.4249444 | P23: =H23 -> 7.9249444
B24: WACC | C24: =C25-0.01 -> 0.023493934 | D24: 4.1232863e+08 | E24: 4.1232863e+08 | F24: 4.1232863e+08 | G24: 4.1232863e+08 | H24: 4.1232863e+08 | J24: WACC | K24: =C24 -> 0.023493934 | L24: =D37/$O$15 -> 31.584845 | M24: =E37/$O$15 -> 31.584845 | N24: =F37/$O$15 -> 31.584845 | O24: =G37/$O$15 -> 31.584845 | P24: =H37/$O$15 -> 31.584845
C25: =C26-0.01 -> 0.033493934 | D25: 3.8389421e+08 | E25: 3.8389421e+08 | F25: 3.8389421e+08 | G25: 3.8389421e+08 | H25: 3.8389421e+08 | K25: =C25 -> 0.033493934 | L25: =D38/$O$15 -> 29.3787 | M25: =E38/$O$15 -> 29.3787 | N25: =F38/$O$15 -> 29.3787 | O25: =G38/$O$15 -> 29.3787 | P25: =H38/$O$15 -> 29.3787
C26: =Inputs!$L$84 -> 0.043493934 | D26: 3.5778236e+08 | E26: 3.5778236e+08 | F26: 3.5778236e+08 | G26: 3.5778236e+08 | H26: 3.5778236e+08 | K26: =C26 -> 0.043493934 | L26: =D39/$O$15 -> 27.352756 | M26: =E39/$O$15 -> 27.352756 | N26: =F39/$O$15 -> 27.352756 | O26: =G39/$O$15 -> 27.352756 | P26: =H39/$O$15 -> 27.352756
C27: =C26+0.01 -> 0.053493934 | D27: 3.3378036e+08 | E27: 3.3378036e+08 | F27: 3.3378036e+08 | G27: 3.3378036e+08 | H27: 3.3378036e+08 | K27: =C27 -> 0.053493934 | L27: =D40/$O$15 -> 25.490509 | M27: =E40/$O$15 -> 25.490509 | N27: =F40/$O$15 -> 25.490509 | O27: =G40/$O$15 -> 25.490509 | P27: =H40/$O$15 -> 25.490509
C28: =C27+0.01 -> 0.063493934 | D28: 3.1169693e+08 | E28: 3.1169693e+08 | F28: 3.1169693e+08 | G28: 3.1169693e+08 | H28: 3.1169693e+08 | K28: =C28 -> 0.063493934 | L28: =D41/$O$15 -> 23.777119 | M28: =E41/$O$15 -> 23.777119 | N28: =F41/$O$15 -> 23.777119 | O28: =G41/$O$15 -> 23.777119 | P28: =H41/$O$15 -> 23.777119
D33: Equity Value | L33: Premium (Discount) to Stock Price
D35: Terminal Multiple | L35: Terminal Multiple
D36: =D23 -> 5.9249444 | E36: =E23 -> 6.4249444 | F36: =F23 -> 6.9249444 | G36: =G23 -> 7.4249444 | H36: =H23 -> 7.9249444 | L36: =D36 -> 5.9249444 | M36: =E36 -> 6.4249444 | N36: =F36 -> 6.9249444 | O36: =G36 -> 7.4249444 | P36: =H36 -> 7.9249444
B37: WACC | C37: =C24 -> 0.023493934 | D37: =D24-$O$14 -> 4.0708863e+08 | E37: =E24-$O$14 -> 4.0708863e+08 | F37: =F24-$O$14 -> 4.0708863e+08 | G37: =G24-$O$14 -> 4.0708863e+08 | H37: =H24-$O$14 -> 4.0708863e+08 | J37: WACC | K37: =C37 -> 0.023493934 | L37: =L24/$O$16-1 -> 1.7228315 | M37: =M24/$O$16-1 -> 1.7228315 | N37: =N24/$O$16-1 -> 1.7228315 | O37: =O24/$O$16-1 -> 1.7228315 | P37: =P24/$O$16-1 -> 1.7228315
C38: =C25 -> 0.033493934 | D38: =D25-$O$14 -> 3.7865421e+08 | E38: =E25-$O$14 -> 3.7865421e+08 | F38: =F25-$O$14 -> 3.7865421e+08 | G38: =G25-$O$14 -> 3.7865421e+08 | H38: =H25-$O$14 -> 3.7865421e+08 | K38: =C38 -> 0.033493934 | L38: =L25/$O$16-1 -> 1.5326466 | M38: =M25/$O$16-1 -> 1.5326466 | N38: =N25/$O$16-1 -> 1.5326466 | O38: =O25/$O$16-1 -> 1.5326466 | P38: =P25/$O$16-1 -> 1.5326466
C39: =C26 -> 0.043493934 | D39: =D26-$O$14 -> 3.5254236e+08 | E39: =E26-$O$14 -> 3.5254236e+08 | F39: =F26-$O$14 -> 3.5254236e+08 | G39: =G26-$O$14 -> 3.5254236e+08 | H39: =H26-$O$14 -> 3.5254236e+08 | K39: =C39 -> 0.043493934 | L39: =L26/$O$16-1 -> 1.3579962 | M39: =M26/$O$16-1 -> 1.3579962 | N39: =N26/$O$16-1 -> 1.3579962 | O39: =O26/$O$16-1 -> 1.3579962 | P39: =P26/$O$16-1 -> 1.3579962
C40: =C27 -> 0.053493934 | D40: =D27-$O$14 -> 3.2854036e+08 | E40: =E27-$O$14 -> 3.2854036e+08 | F40: =F27-$O$14 -> 3.2854036e+08 | G40: =G27-$O$14 -> 3.2854036e+08 | H40: =H27-$O$14 -> 3.2854036e+08 | K40: =C40 -> 0.053493934 | L40: =L27/$O$16-1 -> 1.1974577 | M40: =M27/$O$16-1 -> 1.1974577 | N40: =N27/$O$16-1 -> 1.1974577 | O40: =O27/$O$16-1 -> 1.1974577 | P40: =P27/$O$16-1 -> 1.1974577
C41: =C28 -> 0.063493934 | D41: =D28-$O$14 -> 3.0645693e+08 | E41: =E28-$O$14 -> 3.0645693e+08 | F41: =F28-$O$14 -> 3.0645693e+08 | G41: =G28-$O$14 -> 3.0645693e+08 | H41: =H28-$O$14 -> 3.0645693e+08 | K41: =C41 -> 0.063493934 | L41: =L28/$O$16-1 -> 1.0497516 | M41: =M28/$O$16-1 -> 1.0497516 | N41: =N28/$O$16-1 -> 1.0497516 | O41: =O28/$O$16-1 -> 1.0497516 | P41: =P28/$O$16-1 -> 1.0497516
P43: These tables require the workbook calculation to be set to automatic to update.
C49: Dashboard: Perpetuity Method
E52: Model Drivers Set To | G52: 2 | M52: All figures in USD thousands unless stated
E55: Main Outputs 1 | M55: Selected Inputs
G57: Enterprise | H57: Equity | I57: Equity
G58: Value | H58: Value | I58: Per Share | M58: Terminal Growth Rate | P58: =Inputs!F107 -> 0.01
G59: =Model!$J$348 -> 5.2634743e+08 | M59: WACC | P59: =Inputs!$L$84 -> 0.043493934
E60: Best Case | F60: 1 | G60: 8.9122363e+08 | H60: =G60-$P$60 -> 8.8598363e+08 | I60: =H60/$P$61 -> 68.740942 | M60: Net Debt | O60: =CONCATENATE("(End of ",Model!$J$5,")") -> (End of 2024) | P60: =Inputs!$L$94 -> 5240000
E61: Base Case | F61: 2 | G61: 5.2634743e+08 | H61: =G61-$P$60 -> 5.2110743e+08 | I61: =H61/$P$61 -> 40.431239 | M61: Shares Outstanding | O61: (FD 000) | P61: =Inputs!F105 -> 12888733
E62: Worst Case | F62: 3 | G62: 2.6531228e+08 | H62: =G62-$P$60 -> 2.6007228e+08 | I62: =H62/$P$61 -> 20.178266 | M62: Current Stock Price | O62: (US$/sh) | P62: =Inputs!$F$106 -> 11.6
E66: Enterprise Value 1 | M66: Equity Value per Share
E68: Terminal Growth Rate | M68: Terminal Growth Rate
D69: =Model!$J$348 -> 5.2634743e+08 | E69: =F69-0.005 -> 0 | F69: =G69-0.005 -> 0.005 | G69: =Inputs!$F$107 -> 0.01 | H69: =G69+0.005 -> 0.015 | I69: =H69+0.005 -> 0.02 | M69: =E69 -> 0 | N69: =F69 -> 0.005 | O69: =G69 -> 0.01 | P69: =H69 -> 0.015 | Q69: =I69 -> 0.02
C70: WACC | D70: =D71-0.01 -> 0.023493934 | E70: 8.1896624e+08 | F70: 1.0095452e+09 | G70: 1.3413573e+09 | H70: 2.0638154e+09 | I70: 4.8540232e+09 | K70: WACC | L70: =D70 -> 0.023493934 | M70: =E83/$P$61 -> 63.134697 | N70: =F83/$P$61 -> 77.921177 | O70: =G83/$P$61 -> 103.66553 | P70: =H83/$P$61 -> 159.71899 | Q70: =I83/$P$61 -> 376.20325
D71: =D72-0.01 -> 0.033493934 | E71: 5.656767e+08 | F71: 6.4587745e+08 | G71: 7.60215e+08 | H71: 9.363769e+08 | I71: 1.2430878e+09 | L71: =D71 -> 0.033493934 | M71: =E84/$P$61 -> 43.482685 | N71: =F84/$P$61 -> 49.705232 | O71: =G84/$P$61 -> 58.576356 | P71: =H84/$P$61 -> 72.244255 | Q71: =I84/$P$61 -> 96.041075
D72: =Inputs!$L$84 -> 0.043493934 | E72: 4.2914031e+08 | F72: 4.7143072e+08 | G72: 5.2634743e+08 | H72: 6.0053726e+08 | I72: 7.0630538e+08 | L72: =D72 -> 0.043493934 | M72: =E85/$P$61 -> 32.889215 | N72: =F85/$P$61 -> 36.170408 | O72: =G85/$P$61 -> 40.431239 | P72: =H85/$P$61 -> 46.187416 | Q72: =I85/$P$61 -> 54.393663
D73: =D72+0.01 -> 0.053493934 | E73: 3.4386763e+08 | F73: 3.6913497e+08 | G73: 4.0021171e+08 | H73: 4.393616e+08 | I73: 4.9020015e+08 | L73: =D73 -> 0.053493934 | M73: =E86/$P$61 -> 26.273151 | N73: =F86/$P$61 -> 28.233572 | O73: =G86/$P$61 -> 30.644728 | P73: =H86/$P$61 -> 33.682257 | Q73: =I86/$P$61 -> 37.626674
D74: =D73+0.01 -> 0.063493934 | E74: 2.8562711e+08 | F74: 3.0197696e+08 | G74: 3.213832e+08 | H74: 3.4479123e+08 | I74: 3.7358116e+08 | L74: =D74 -> 0.063493934 | M74: =E87/$P$61 -> 21.754436 | N74: =F87/$P$61 -> 23.022974 | O74: =G87/$P$61 -> 24.528649 | P74: =H87/$P$61 -> 26.344811 | Q74: =I87/$P$61 -> 28.57854
E79: Equity Value | M79: Premium (Discount) to Stock Price
E81: Terminal Growth Rate | M81: Terminal Growth Rate
E82: =E69 -> 0 | F82: =F69 -> 0.005 | G82: =G69 -> 0.01 | H82: =H69 -> 0.015 | I82: =I69 -> 0.02 | M82: =E82 -> 0 | N82: =F82 -> 0.005 | O82: =G82 -> 0.01 | P82: =H82 -> 0.015 | Q82: =I82 -> 0.02
C83: WACC | D83: =D70 -> 0.023493934 | E83: =E70-$P$60 -> 8.1372624e+08 | F83: =F70-$P$60 -> 1.0043052e+09 | G83: =G70-$P$60 -> 1.3361173e+09 | H83: =H70-$P$60 -> 2.0585754e+09 | I83: =I70-$P$60 -> 4.8487832e+09 | K83: WACC | L83: =D83 -> 0.023493934 | M83: =M70/$P$62-1 -> 4.4426463 | N83: =N70/$P$62-1 -> 5.7173429 | O83: =O70/$P$62-1 -> 7.9366836 | P83: =P70/$P$62-1 -> 12.768878 | Q83: =Q70/$P$62-1 -> 31.431315
D84: =D71 -> 0.033493934 | E84: =E71-$P$60 -> 5.604367e+08 | F84: =F71-$P$60 -> 6.4063745e+08 | G84: =G71-$P$60 -> 7.54975e+08 | H84: =H71-$P$60 -> 9.311369e+08 | I84: =I71-$P$60 -> 1.2378478e+09 | L84: =D84 -> 0.033493934 | M84: =M71/$P$62-1 -> 2.7485073 | N84: =N71/$P$62-1 -> 3.2849338 | O84: =O71/$P$62-1 -> 4.0496859 | P84: =P71/$P$62-1 -> 5.227953 | Q84: =Q71/$P$62-1 -> 7.279403
D85: =D72 -> 0.043493934 | E85: =E72-$P$60 -> 4.2390031e+08 | F85: =F72-$P$60 -> 4.6619072e+08 | G85: =G72-$P$60 -> 5.2110743e+08 | H85: =H72-$P$60 -> 5.9529726e+08 | I85: =I72-$P$60 -> 7.0106538e+08 | L85: =D85 -> 0.043493934 | M85: =M72/$P$62-1 -> 1.8352772 | N85: =N72/$P$62-1 -> 2.1181386 | O85: =O72/$P$62-1 -> 2.4854516 | P85: =P72/$P$62-1 -> 2.9816738 | Q85: =Q72/$P$62-1 -> 3.6891088
D86: =D73 -> 0.053493934 | E86: =E73-$P$60 -> 3.3862763e+08 | F86: =F73-$P$60 -> 3.6389497e+08 | G86: =G73-$P$60 -> 3.9497171e+08 | H86: =H73-$P$60 -> 4.341216e+08 | I86: =I73-$P$60 -> 4.8496015e+08 | L86: =D86 -> 0.053493934 | M86: =M73/$P$62-1 -> 1.2649268 | N86: =N73/$P$62-1 -> 1.4339287 | O86: =O73/$P$62-1 -> 1.6417869 | P86: =P73/$P$62-1 -> 1.9036428 | Q86: =Q73/$P$62-1 -> 2.2436788
D87: =D74 -> 0.063493934 | E87: =E74-$P$60 -> 2.8038711e+08 | F87: =F74-$P$60 -> 2.9673696e+08 | G87: =G74-$P$60 -> 3.161432e+08 | H87: =H74-$P$60 -> 3.3955123e+08 | I87: =I74-$P$60 -> 3.6834116e+08 | L87: =D87 -> 0.063493934 | M87: =M74/$P$62-1 -> 0.87538241 | N87: =N74/$P$62-1 -> 0.98473914 | O87: =O74/$P$62-1 -> 1.1145387 | P87: =P74/$P$62-1 -> 1.2711044 | Q87: =Q74/$P$62-1 -> 1.4636672
Q89: These tables require the workbook calculation to be set to automatic to update.

Sheet Inputs
B3: Drivers
B5: All figures in USD thousands unless stated | G5: =$F$97 -> 2025 | H5: =G5+1 -> 2026 | I5: =H5+1 -> 2027 | J5: =I5+1 -> 2028 | K5: =J5+1 -> 2029 | L5: =K5+1 -> 2030 | M5: =L5+1 -> 2031 | N5: =M5+1 -> 2032 | O5: Term
B7: Driver Switch | D7: =Outputs!G52 -> 2
B10: Revenue | G10: {=INDEX(G12:G14,$D$7)} -> 0.12 | H10: {=INDEX(H12:H14,$D$7)} -> 0.112 | I10: {=INDEX(I12:I14,$D$7)} -> 0.104 | J10: {=INDEX(J12:J14,$D$7)} -> 0.048 | K10: {=INDEX(K12:K14,$D$7)} -> 0.04 | L10: {=INDEX(L12:L14,$D$7)} -> 0.032 | M10: {=INDEX(M12:M14,$D$7)} -> 0.028 | N10: {=INDEX(N12:N14,$D$7)} -> 0.028 | O10: {=INDEX(O12:O14,$D$7)} -> 0.028
B12: =Outputs!E60 -> Best Case | G12: 0.15 | H12: 0.14 | I12: 0.13 | J12: 0.06 | K12: 0.05 | L12: 0.04 | M12: 0.035 | N12: 0.035 | O12: 0.035
B13: =Outputs!E61 -> Base Case | G13: =G12*0.8 -> 0.12 | H13: =H12*0.8 -> 0.112 | I13: =I12*0.8 -> 0.104 | J13: =J12*0.8 -> 0.048 | K13: =K12*0.8 -> 0.04 | L13: =L12*0.8 -> 0.032 | M13: =M12*0.8 -> 0.028 | N13: =N12*0.8 -> 0.028 | O13: =O12*0.8 -> 0.028
B14: =Outputs!E62 -> Worst Case | G14: =G13*0.7 -> 0.084 | H14: =H13*0.7 -> 0.0784 | I14: =I13*0.7 -> 0.0728 | J14: =J13*0.7 -> 0.0336 | K14: =K13*0.7 -> 0.028 | L14: =L13*0.7 -> 0.0224 | M14: =M13*0.7 -> 0.0196 | N14: =N13*0.7 -> 0.0196 | O14: =O13*0.7 -> 0.0196
B17: COGS% | G17: {=INDEX(G19:G21,$D$7)} -> 0.49 | H17: {=INDEX(H19:H21,$D$7)} -> 0.49 | I17: {=INDEX(I19:I21,$D$7)} -> 0.49 | J17: {=INDEX(J19:J21,$D$7)} -> 0.49 | K17: {=INDEX(K19:K21,$D$7)} -> 0.49 | L17: {=INDEX(L19:L21,$D$7)} -> 0.49 | M17: {=INDEX(M19:M21,$D$7)} -> 0.49 | N17: {=INDEX(N19:N21,$D$7)} -> 0.49 | O17: {=INDEX(O19:O21,$D$7)} -> 0.49
B19: =$B$12 -> Best Case | G19: 0.45 | H19: 0.45 | I19: 0.45 | J19: 0.45 | K19: 0.45 | L19: 0.45 | M19: 0.45 | N19: 0.45 | O19: 0.45
B20: =$B$13 -> Base Case | G20: 0.49 | H20: 0.49 | I20: 0.49 | J20: 0.49 | K20: 0.49 | L20: 0.49 | M20: 0.49 | N20: 0.49 | O20: 0.49
B21: =$B$14 -> Worst Case | G21: 0.5 | H21: 0.502 | I21: 0.505 | J21: 0.508 | K21: 0.51 | L21: 0.51 | M21: 0.51 | N21: 0.51 | O21: 0.51
B24: Capital Expenditure | G24: {=INDEX(G26:G28,$D$7)} -> 18840000 | H24: {=INDEX(H26:H28,$D$7)} -> 19544000 | I24: {=INDEX(I26:I28,$D$7)} -> 19480000 | J24: {=INDEX(J26:J28,$D$7)} -> 20376000 | K24: {=INDEX(K26:K28,$D$7)} -> 19608000 | L24: {=INDEX(L26:L28,$D$7)} -> 19520000 | M24: {=INDEX(M26:M28,$D$7)} -> 19520000 | N24: {=INDEX(N26:N28,$D$7)} -> 19520000 | O24: {=INDEX(O26:O28,$D$7)} -> 19520000
B26: =$B$12 -> Best Case | G26: =G27*0.8 -> 15072000 | H26: =H27*0.8 -> 15635200 | I26: =I27*0.8 -> 15584000 | J26: =J27*0.8 -> 16300800 | K26: =K27*0.8 -> 15686400 | L26: =L27*0.8 -> 15616000 | M26: =M27*0.8 -> 15616000 | N26: =N27*0.8 -> 15616000 | O26: =O27*0.8 -> 15616000
B27: =$B$13 -> Base Case | G27: 18840000 | H27: 19544000 | I27: 19480000 | J27: 20376000 | K27: 19608000 | L27: 19520000 | M27: 19520000 | N27: 19520000 | O27: 19520000
B28: =$B$14 -> Worst Case | G28: =G27*1.1 -> 20724000 | H28: =H27*1.1 -> 21498400 | I28: =I27*1.1 -> 21428000 | J28: =J27*1.1 -> 22413600 | K28: =K27*1.1 -> 21568800 | L28: =L27*1.1 -> 21472000 | M28: =M27*1.1 -> 21472000 | N28: =N27*1.1 -> 21472000 | O28: =O27*1.1 -> 21472000
B31: Inflation Rate | G31: 0.0531 | H31: 0.0432 | I31: 0.0339 | J31: 0.0296 | K31: 0.0296 | L31: 0.0296 | M31: 0.0296 | N31: 0.0296 | O31: 0.0296
B34: Working Capital 1
B35: Accounts Receivable | E35: (Days) | G35: 33.532739 | H35: 34 | I35: 34 | J35: 34 | K35: 34 | L35: 34 | M35: 34 | N35: 34 | O35: 34
B36: Inventory | E36: (Days) | G36: 60 | H36: 60 | I36: 60 | J36: 60 | K36: 60 | L36: 60 | M36: 60 | N36: 60 | O36: 60
B37: Accounts Payable | E37: (Days) | G37: 131.91009 | H37: 86.396187 | I37: 95.511381 | J37: 95.511381 | K37: 95.511381 | L37: 95.511381 | M37: 95.511381 | N37: 95.511381 | O37: 95.511381
L40: We have assumed working capital amounts per day in terminal year are equal to the previous year.
B44: Weighted Average Cost of Capital
B46: All figures in USD thousands unless stated
H48: Average | I48: Debt/ | J48: Debt/ | K48: Levered | L48: Unlevered
B49: Name | D49: Region | F49: Debt | G49: Equity | H49: Tax Rate 1 | I49: Equity | J49: Capital | K49: Beta 2 | L49: Beta 3
F50: Cost of Debt | G50: Cost of Capital
B51: Oil/Gas (Integrated) | D51: Emerging Markets | F51: 0.0738 | G51: 0.10559082 | H51: 0.20852008 | I51: 0.13320997 | J51: 0.11755101 | K51: 0.97960023 | L51: =K51/(1+(1-H51)*I51) -> 0.88616878
B52: Oil/Gas (Production and Exploration) | D52: Emerging Markets | F52: 0.0738 | G52: 0.10323198 | H52: 0.17395945 | I52: 0.27987954 | J52: 0.21867647 | K52: 1.0441717 | L52: =K52/(1+(1-H52)*I52) -> 0.84809831
B53: Oil/Gas Distribution | D53: Emerging Markets | F53: 0.0693 | G53: 0.07587536 | H53: 0.1288961 | I53: 0.56946739 | J53: 0.36284117 | K53: 0.64524477 | L53: =K53/(1+(1-H53)*I53) -> 0.43129453
B54: Oilfield Svcs/Equip. | D54: Emerging Markets | F54: 0.0738 | G54: 0.08869592 | H54: 0.14623911 | I54: 0.48347252 | J54: 0.32590595 | K54: 0.87086793 | L54: =K54/(1+(1-H54)*I54) -> 0.61642587
E57: Average | F57: =AVERAGE(F51:F55) -> 0.072675 | G57: =AVERAGE(G51:G55) -> 0.093348519 | H57: =AVERAGE(H51:H55) -> 0.16440369 | I57: =AVERAGE(I51:I55) -> 0.36650735 | J57: =AVERAGE(J51:J55) -> 0.25624365 | K57: =AVERAGE(K51:K55) -> 0.88497117 | L57: =AVERAGE(L51:L55) -> 0.69549688
E58: Median | F58: =MEDIAN(F51:F55) -> 0.0738 | G58: =MEDIAN(G51:G55) -> 0.095963949 | H58: =MEDIAN(H51:H55) -> 0.16009928 | I58: =MEDIAN(I51:I55) -> 0.38167603 | J58: =MEDIAN(J51:J55) -> 0.27229121 | K58: =MEDIAN(K51:K55) -> 0.92523408 | L58: =MEDIAN(L51:L55) -> 0.73226209
B61: PETR3.SA | H61: PETR4.SA
B63: Market return | F63: {='CAPM Beta '!$AD$12:$AE$12} -> 0.15072761 | G63: 0 | H63: Market return | L63: {='CAPM Beta '!$AD$12:$AE$12} -> 0.15072761 | M63: 0
B64: Risk Free | F64: 0.0404 | H64: Risk Free | L64: 0.0404
B65: Beta | F65: ='CAPM Beta '!$AD$13 -> 0.1300016 | H65: Beta | L65: ='CAPM Beta '!$AE$13 -> 0
B66: Cost of Equity | F66: =F64+F65*(F63-F64) -> 0.054742765 | H66: Cost of Equity | L66: =L64+L65*(L63-L64) -> 0.0404
B70: Capital Structure | H70: Cost of Debt
E72: Current | F72: Target | H72: Pre-Tax Cost of Debt | L72: =F57 -> 0.072675
B73: Total Debt | D73: 52240 | E73: =D73/$D$75 -> 0.40895295 | F73: 0.15 | H73: Tax Rate | L73: 0.34
B74: Market Cap Preferred | D74: 75500.858 | E74: =D74/$D$75 -> 0.59104705 | F74: =1-F73 -> 0.85 | H74: After-Tax Cost of Debt | L74: =L72*(1-L73) -> 0.0479655
B75: Total Capitalization | D75: =SUM(D73:D74) -> 127740.86 | E75: =SUM(E73:E74) -> 1 | F75: =SUM(F73:F74) -> 1
B77: Debt / Equity | E77: =E73/E74 -> 0.69191267 | F77: =F73/F74 -> 0.17647059 | H77: Weighted Average Cost of Capital
K79: Weight | L79: Cost
B80: Tax Rate is a 5-Year Average. | H80: Debt Capital | K80: =E73 -> 0.40895295 | L80: =L74 -> 0.0479655
H81: Equity Capital | K81: =E74 -> 0.59104705 | L81: =L66 -> 0.0404
H84: Weighted Average Cost of Capital | L84: =SUMPRODUCT(K80:K81,L80:L81) -> 0.043493934
B88: Other Inputs
B90: All figures in USD thousands unless stated
B93: Dates | H93: =CONCATENATE("End of ",G5-1," Balances") -> End of 2024 Balances
B94: Valuation Date | E94: (YY-MM-DD) | F94: 45931 | H94: Net Debt | L94: 5240000
B95: First Expected Cash Flow | E95: (YY-MM-DD) | F95: 45962 | H95: Property Plant & Equipment | L95: 136285000
B96: First Fiscal Year End for Forecast | E96: (YY-MM-DD) | F96: 46022 | H96: Tax Basis for PP&E | L96: 97716941
B97: First Year of Forecast | E97: (YYYY) | F97: =YEAR(F96) -> 2025 | H97: Tax Losses | L97: 0
B98: Incorrect Date Set for Valuation? | F98: =IF(F94>F95,1,0) -> 0
B99: Incorrect Date Set for First Cash Flow? | F99: =IF(F95>F96,1,0) -> 0
B100: Days in Period | F100: 365
H103: Other Inputs
B104: Valuation | H104: Plant Capacity | K104: (Units/Day) | L104: 0
B105: Shares Outstanding | E105: (FD 000) | F105: 12888733 | H105: Projected Interest Expense | L105: 2520000
B106: Current Stock Price | E106: (US$/sh) | F106: 11.6 | H106: First Year Tax Depreciation | L106: 0.5
B107: Terminal Growth Rate | F107: 0.01 | H107: Blended Tax Depreciation Rate | L107: 0.15
B108: Terminal EBITDA Multiple 1 | F108: ='Assumption Origin'!H33 -> 6.9249444 | H108: First Year Accounting Depreciation | L108: 0.5
B109: Weighted Average Cost of Capital (WACC) | F109: =L84 -> 0.043493934 | H109: Useful Life: Existing Assets | K109: (Years) | L109: 16
B110: Terminal Growth Greater Than or Equal To WACC? | F110: =IF(F107>=F109,1,0) -> 0 | H110: Useful Life: New Assets | K110: (Years) | L110: 20
L113: The Terminal EBITDA multiple should reflect a 'steady-state' industry multiple.

Sheet Model
B3: Revenue Schedule
B5: All figures in USD thousands unless stated | F5: =G5-1 -> 2020 | G5: =H5-1 -> 2021 | H5: =I5-1 -> 2022 | I5: =J5-1 -> 2023 | J5: =K5-1 -> 2024 | K5: =Inputs!$F$97 -> 2025 | L5: =K5+1 -> 2026 | M5: =L5+1 -> 2027 | N5: =M5+1 -> 2028 | O5: =N5+1 -> 2029 | P5: =O5+1 -> 2030 | Q5: =P5+1 -> 2031 | R5: =Q5+1 -> 2032 | S5: Term
B6: {=CONCATENATE("Model Running: ",INDEX(Inputs!$B$12:$B$14,Inputs!$D$7)," Drivers")} -> Model Running: Base Case Drivers
B8: Days in Period | C8: =Inputs!$F$100 -> 365 | F8: 365 | G8: 365 | H8: 365 | I8: 365 | J8: 365 | K8: =$C$8 -> 365 | L8: =$C$8 -> 365 | M8: =$C$8 -> 365 | N8: =$C$8 -> 365 | O8: =$C$8 -> 365 | P8: =$C$8 -> 365 | Q8: =$C$8 -> 365 | R8: =$C$8 -> 365 | S8: =$C$8 -> 365
B9: Plant Capacity | C9: =Inputs!$L$104 -> 0
B15: REVENUE
B17: Revenue Growth | D17: (Units) | G17: =G19/F19-1 -> 0.56410782 | H17: =H19/G19-1 -> 0.48243337 | I17: =I19/H19-1 -> -0.17726594 | J17: =J19/I19-1 -> -0.10734408 | K17: =Inputs!G10 -> 0.12 | L17: =Inputs!H10 -> 0.112 | M17: =Inputs!I10 -> 0.104 | N17: =Inputs!J10 -> 0.048 | O17: =Inputs!K10 -> 0.04 | P17: =Inputs!L10 -> 0.032 | Q17: =Inputs!M10 -> 0.028 | R17: =Inputs!N10 -> 0.028 | S17: =Inputs!O10 -> 0.028
B19: Revenue | F19: 53683000 | G19: 83966000 | H19: 124474000 | I19: 102409000 | J19: 91416000 | K19: =J19*(1+K17) -> 1.0238592e+08 | L19: =K19*(1+L17) -> 1.1385314e+08 | M19: =L19*(1+M17) -> 1.2569387e+08 | N19: =M19*(1+N17) -> 1.3172718e+08 | O19: =N19*(1+O17) -> 1.3699626e+08 | P19: =O19*(1+P17) -> 1.4138014e+08 | Q19: =P19*(1+Q17) -> 1.4533879e+08 | R19: =Q19*(1+R17) -> 1.4940827e+08 | S19: =R19*(1+S17) -> 1.535917e+08
B25: Cost Schedule
B27: All figures in USD thousands unless stated | F27: =F$5 -> 2020 | G27: =G$5 -> 2021 | H27: =H$5 -> 2022 | I27: =I$5 -> 2023 | J27: =J$5 -> 2024 | K27: =K$5 -> 2025 | L27: =L$5 -> 2026 | M27: =M$5 -> 2027 | ... S27: =S$5 -> Term
B29: COGS % | G29: =G31/G30 -> 0.51406522 | H29: =H31/H30 -> 0.477899 | I29: =I31/I30 -> 0.47295648 | J29: =J31/J30 -> 0.4971121 | K29: =Inputs!G17 -> 0.49 | L29: =Inputs!H17 -> 0.49 | M29: =Inputs!I17 -> 0.49 | N29: =Inputs!J17 -> 0.49 | O29: =Inputs!K17 -> 0.49 | P29: =Inputs!L17 -> 0.49 | Q29: =Inputs!M17 -> 0.49 | R29: =Inputs!N17 -> 0.49 | S29: =Inputs!O17 -> 0.49
B30: Revenue | F30: =F19 -> 53683000 | G30: =G19 -> 83966000 | H30: =H19 -> 124474000 | I30: =I19 -> 102409000 | J30: =J19 -> 91416000 | K30: =K19 -> 1.0238592e+08 | L30: =L19 -> 1.1385314e+08 | M30: =M19 -> 1.2569387e+08 | ... S30: =S19 -> 1.535917e+08
B31: COGS | F31: 29195000 | G31: 43164000 | H31: 59486000 | I31: 48435000 | J31: 45444000 | K31: =K30*K29 -> 50169101 | L31: =L30*L29 -> 55788040 | M31: =M30*M29 -> 61589996 | N31: =N30*N29 -> 64546316 | O31: =O30*O29 -> 67128169 | P31: =P30*P29 -> 69276270 | Q31: =Q30*Q29 -> 71216006 | R31: =R30*R29 -> 73210054 | S31: =S30*S29 -> 75259935
B35: Income Statement
B37: All figures in USD thousands unless stated | F37: =F$5 -> 2020 | G37: =G$5 -> 2021 | H37: =H$5 -> 2022 | I37: =I$5 -> 2023 | J37: =J$5 -> 2024 | K37: =K$5 -> 2025 | L37: =L$5 -> 2026 | M37: =M$5 -> 2027 | ... S37: =S$5 -> Term
B38: =$B$6 -> Model Running: Base Case Drivers
B40: Inflation | F40: 0.0373 | G40: 0.083 | H40: 0.0928 | I40: 0.0459 | J40: 0.0483 | K40: =Inputs!G31 -> 0.0531 | L40: =Inputs!H31 -> 0.0432 | M40: =Inputs!I31 -> 0.0339 | N40: =Inputs!J31 -> 0.0296 | O40: =Inputs!K31 -> 0.0296 | P40: =Inputs!L31 -> 0.0296 | Q40: =Inputs!M31 -> 0.0296 | R40: =Inputs!N31 -> 0.0296 | S40: =Inputs!O31 -> 0.0296
B42: Interest Expense | C42: =Inputs!$L$105 -> 2520000
B43: Tax Rate | C43: =Inputs!$L$73 -> 0.34
B45: Revenue | F45: =F19 -> 53683000 | G45: =G19 -> 83966000 | H45: =H19 -> 124474000 | I45: =I19 -> 102409000 | J45: =J19 -> 91416000 | K45: =K19 -> 1.0238592e+08 | L45: =L19 -> 1.1385314e+08 | M45: =M19 -> 1.2569387e+08 | ... S45: =S19 -> 1.535917e+08
B46: COGS | F46: =F31 -> 29195000 | G46: =G31 -> 43164000 | H46: =H31 -> 59486000 | I46: =I31 -> 48435000 | J46: =J31 -> 45444000 | K46: =K31 -> 50169101 | L46: =L31 -> 55788040 | M46: =M31 -> 61589996 | ... S46: =S31 -> 75259935
B47: Gross Profit | F47: =F45-F46 -> 24488000 | G47: =G45-G46 -> 40802000 | H47: =H45-H46 -> 64988000 | I47: =I45-I46 -> 53974000 | J47: =J45-J46 -> 45972000 | K47: =K45-K46 -> 52216819 | L47: =L45-L46 -> 58065103 | M47: =M45-M46 -> 64103874 | ... S47: =S45-S46 -> 78331769
B50: SG&A | F50: 4873000 | G50: 6313000 | H50: 6537000 | I50: 8061000 | J50: 9033000 | K50: =J50*(1+K$40) -> 9512652.3 | L50: =K50*(1+L$40) -> 9923598.9 | M50: =L50*(1+M$40) -> 10260009 | N50: =M50*(1+N$40) -> 10563705 | O50: =N50*(1+O$40) -> 10876391 | P50: =O50*(1+P$40) -> 11198332 | Q50: =P50*(1+Q$40) -> 11529803 | R50: =Q50*(1+R$40) -> 11871085 | S50: =R50*(1+S$40) -> 12222469
B51: Other | F51: 245000 | G51: 466000 | H51: 1926000 | I51: 5690000 | J51: 10432000 | K51: =J51*(1+K$40) -> 10985939 | L51: =K51*(1+L$40) -> 11460532 | M51: =L51*(1+M$40) -> 11849044 | N51: =M51*(1+N$40) -> 12199775 | O51: =N51*(1+O$40) -> 12560889 | P51: =O51*(1+P$40) -> 12932691 | Q51: =P51*(1+Q$40) -> 13315499 | R51: =Q51*(1+R$40) -> 13709638 | S51: =R51*(1+S$40) -> 14115443
B52: EBITDA | F52: =F47-SUM(F50:F51) -> 19370000 | G52: =G47-SUM(G50:G51) -> 34023000 | H52: =H47-SUM(H50:H51) -> 56525000 | I52: =I47-SUM(I50:I51) -> 40223000 | J52: =J47-SUM(J50:J51) -> 26507000 | K52: =K47-SUM(K50:K51) -> 31718228 | L52: =L47-SUM(L50:L51) -> 36680972 | M52: =M47-SUM(M50:M51) -> 41994821 | ... S52: =S47-SUM(S50:S51) -> 51993858
B55: Depreciation | F55: 653000 | G55: 696000 | H55: 894000 | I55: 732000 | J55: 816000 | K55: =K149 -> 8988812.5 | L55: =L149 -> 9948412.5 | M55: =M149 -> 10924012 | N55: =N149 -> 11920412 | O55: =O149 -> 12920012 | P55: =P149 -> 13410212 | Q55: =Q149 -> 13410212 | R55: =R149 -> 13410212 | S55: =Inputs!O24 -> 19520000
B56: EBIT | F56: =F52-F55 -> 18717000 | G56: =G52-G55 -> 33327000 | H56: =H52-H55 -> 55631000 | I56: =I52-I55 -> 39491000 | J56: =J52-J55 -> 25691000 | K56: =K52-K55 -> 22729415 | L56: =L52-L55 -> 26732560 | M56: =M52-M55 -> 31070808 | ... S56: =S52-S55 -> 32473858
B58: Interest | F58: 16738000 | G58: 5102000 | H58: 2106000 | I58: 4095000 | J58: 14549000 | K58: =$C$42 -> 2520000 | L58: =$C$42 -> 2520000 | M58: =$C$42 -> 2520000 | N58: =$C$42 -> 2520000 | O58: =$C$42 -> 2520000 | P58: =$C$42 -> 2520000 | Q58: =$C$42 -> 2520000 | R58: =$C$42 -> 2520000 | S58: =$C$42 -> 2520000
B59: EBT | F59: =F56-F58 -> 1979000 | G59: =G56-G58 -> 28225000 | H59: =H56-H58 -> 53525000 | I59: =I56-I58 -> 35396000 | J59: =J56-J58 -> 11142000 | K59: =K56-K58 -> 20209415 | L59: =L56-L58 -> 24212560 | M59: =M56-M58 -> 28550808 | ... S59: =S56-S58 -> 29953858
B61: Current Tax | F61: -1174000 | G61: 8239000 | H61: 16770000 | I61: 10401000 | J61: 3537000 | K61: =K218 -> 4463413.4 | L61: =L218 -> 5991552.2 | M61: =M218 -> 7646625.5 | N61: =N218 -> 8320189.2 | O61: =O218 -> 8873903.2 | P61: =P218 -> 9308797.3 | Q61: =Q218 -> 9678627.3 | R61: =R218 -> 10071550 | S61: =S59*C43 -> 10184312
B62: Deferred Tax | F62: 0 | G62: 0 | H62: 0 | I62: 0 | J62: 0 | K62: =K219 -> 2407787.8 | L62: =L219 -> 2240718.2 | M62: =M219 -> 2060649.4 | N62: =N219 -> 1871979.3 | O62: =O219 -> 1662969.4 | P62: =P219 -> 1585699.4 | Q62: =Q219 -> 1659443.6 | R62: =R219 -> 1722126.2 | S62: =S219 -> 0
B63: Total Tax | F63: =SUM(F61:F62) -> -1174000 | G63: =SUM(G61:G62) -> 8239000 | H63: =SUM(H61:H62) -> 16770000 | I63: =SUM(I61:I62) -> 10401000 | J63: =SUM(J61:J62) -> 3537000 | K63: =SUM(K61:K62) -> 6871201.2 | L63: =SUM(L61:L62) -> 8232270.3 | M63: =SUM(M61:M62) -> 9707274.9 | ... S63: =SUM(S61:S62) -> 10184312
B65: Net Income | F65: =F59-F63 -> 3153000 | G65: =G59-G63 -> 19986000 | H65: =H59-H63 -> 36755000 | I65: =I59-I63 -> 24995000 | J65: =J59-J63 -> 7605000 | K65: =K59-K63 -> 13338214 | L65: =L59-L63 -> 15980289 | M65: =M59-M63 -> 18843534 | ... S65: =S59-S63 -> 19769546
B69: Working Capital Schedule
B71: All figures in USD thousands unless stated | F71: =F$5 -> 2020 | G71: =G$5 -> 2021 | H71: =H$5 -> 2022 | I71: =I$5 -> 2023 | J71: =J$5 -> 2024 | K71: =K$5 -> 2025 | L71: =L$5 -> 2026 | M71: =M$5 -> 2027 | ... R71: =R$5 -> 2032 | S71: Term
B72: =$B$6 -> Model Running: Base Case Drivers
B74: Days in Period | F74: =F$8 -> 365 | G74: =G$8 -> 365 | H74: =H$8 -> 365 | I74: =I$8 -> 365 | J74: =J$8 -> 365 | K74: =K$8 -> 365 | L74: =L$8 -> 365 | M74: =M$8 -> 365 | ... S74: =S$8 -> 365
B75: Revenue | F75: =F45 -> 53683000 | G75: =G45 -> 83966000 | H75: =H45 -> 124474000 | I75: =I45 -> 102409000 | J75: =J45 -> 91416000 | K75: =K45 -> 1.0238592e+08 | L75: =L45 -> 1.1385314e+08 | M75: =M45 -> 1.2569387e+08 | ... S75: =S45 -> 1.535917e+08
B76: COGS | F76: =F46 -> 29195000 | G76: =G46 -> 43164000 | H76: =H46 -> 59486000 | I76: =I46 -> 48435000 | J76: =J46 -> 45444000 | K76: =K46 -> 50169101 | L76: =L46 -> 55788040 | M76: =M46 -> 61589996 | ... S76: =S46 -> 75259935
B79: AMOUNTS PER DAY 1
B80: Accounts Receivable | D80: (Days) | F80: =(F86/F75)*F$74 -> 49.810741 | G80: =(G86/G75)*G$74 -> 33.532739 | H80: =(H86/H75)*H$74 -> 18.523587 | I80: =(I86/I75)*I$74 -> 26.064555 | J80: =(J86/J75)*J$74 -> 22.087818 | K80: =Inputs!G35 -> 33.532739 | L80: =Inputs!H35 -> 34 | M80: =Inputs!I35 -> 34 | N80: =Inputs!J35 -> 34 | O80: =Inputs!K35 -> 34 | P80: =Inputs!L35 -> 34 | Q80: =Inputs!M35 -> 34 | R80: =Inputs!N35 -> 34 | S80: =Inputs!O35 -> 34
B81: Inventory | D81: (Days) | F81: =(F87/F76)*F$74 -> 70.974653 | G81: =(G87/G76)*G$74 -> 61.349157 | H81: =(H87/H76)*H$74 -> 53.867044 | I81: =(I87/I76)*I$74 -> 57.883039 | J81: =(J87/J76)*J$74 -> 53.893803 | K81: =Inputs!G36 -> 60 | L81: =Inputs!H36 -> 60 | M81: =Inputs!I36 -> 60 | N81: =Inputs!J36 -> 60 | O81: =Inputs!K36 -> 60 | P81: =Inputs!L36 -> 60 | Q81: =Inputs!M36 -> 60 | R81: =Inputs!N36 -> 60 | S81: =Inputs!O36 -> 60
B82: Accounts Payable | D82: (Days) | F82: =(F88/F76)*F$74 -> 131.91009 | G82: =(G88/G76)*G$74 -> 86.396187 | H82: =(H88/H76)*H$74 -> 95.511381 | I82: =(I88/I76)*I$74 -> 104.13069 | J82: =(J88/J76)*J$74 -> 107.8117 | K82: =Inputs!G37 -> 131.91009 | L82: =Inputs!H37 -> 86.396187 | M82: =Inputs!I37 -> 95.511381 | N82: =Inputs!J37 -> 95.511381 | O82: =Inputs!K37 -> 95.511381 | P82: =Inputs!L37 -> 95.511381 | Q82: =Inputs!M37 -> 95.511381 | R82: =Inputs!N37 -> 95.511381 | S82: =Inputs!O37 -> 95.511381
B85: TOTAL AMOUNTS
B86: Accounts Receivable | F86: 7326000 | G86: 7714000 | H86: 6317000 | I86: 7313000 | J86: 5532000 | K86: =(K80/K$74)*K75 -> 9406247.6 | L86: =(L80/L$74)*L75 -> 10605498 | M86: =(M80/M$74)*M75 -> 11708470 | N86: =(N80/N$74)*N75 -> 12270477 | O86: =(O80/O$74)*O75 -> 12761296 | P86: =(P80/P$74)*P75 -> 13169657 | Q86: =(Q80/Q$74)*Q75 -> 13538408 | R86: =(R80/R$74)*R75 -> 13917483 | S86: =(S80/S$74)*S75 -> 14307173
B87: Inventory | F87: 5677000 | G87: 7255000 | H87: 8779000 | I87: 7681000 | J87: 6710000 | K87: =(K81/K$74)*K76 -> 8246975.5 | L87: =(L81/L$74)*L76 -> 9170636.7 | M87: =(M81/M$74)*M76 -> 10124383 | N87: =(N81/N$74)*N76 -> 10610353 | O87: =(O81/O$74)*O76 -> 11034767 | P87: =(P81/P$74)*P76 -> 11387880 | Q87: =(Q81/Q$74)*Q76 -> 11706741 | R87: =(R81/R$74)*R76 -> 12034529 | S87: =(S81/S$74)*S76 -> 12371496
B88: Accounts Payable | F88: 10551000 | G88: 10217000 | H88: 15566000 | I88: 13818000 | J88: 13423000 | K88: =(K82/K$74)*K76 -> 18130988 | L88: =(L82/L$74)*L76 -> 13205134 | M88: =(M82/M$74)*M76 -> 16116563 | N88: =(N82/N$74)*N76 -> 16890158 | O88: =(O82/O$74)*O76 -> 17565765 | P88: =(P82/P$74)*P76 -> 18127869 | Q88: =(Q82/Q$74)*Q76 -> 18635449 | R88: =(R82/R$74)*R76 -> 19157242 | S88: =(S82/S$74)*S76 -> 19693645
B91: NET WORKING CAPITAL
B92: Current Assets | F92: =SUM(F86:F87) -> 13003000 | G92: =SUM(G86:G87) -> 14969000 | H92: =SUM(H86:H87) -> 15096000 | I92: =SUM(I86:I87) -> 14994000 | J92: =SUM(J86:J87) -> 12242000 | K92: =SUM(K86:K87) -> 17653223 | L92: =SUM(L86:L87) -> 19776135 | M92: =SUM(M86:M87) -> 21832853 | ... S92: =SUM(S86:S87) -> 26678669
B93: Current Liabilities | F93: =SUM(F88) -> 10551000 | G93: =SUM(G88) -> 10217000 | H93: =SUM(H88) -> 15566000 | I93: =SUM(I88) -> 13818000 | J93: =SUM(J88) -> 13423000 | K93: =SUM(K88) -> 18130988 | L93: =SUM(L88) -> 13205134 | M93: =SUM(M88) -> 16116563 | ... S93: =SUM(S88) -> 19693645
B94: Net Working Capital | F94: =F92-F93 -> 2452000 | G94: =G92-G93 -> 4752000 | H94: =H92-H93 -> -470000 | I94: =I92-I93 -> 1176000 | J94: =J92-J93 -> -1181000 | K94: =K92-K93 -> -477764.5 | L94: =L92-L93 -> 6571000.9 | M94: =M92-M93 -> 5716289.8 | ... S94: =S92-S93 -> 6985023.9
B97: Cash from Working Capital Items | G97: =F94-G94 -> -2300000 | H97: =G94-H94 -> 5222000 | I97: =H94-I94 -> -1646000 | J97: =I94-J94 -> 2357000 | K97: =J94-K94 -> -703235.5 | L97: =K94-L94 -> -7048765.4 | M97: =L94-M94 -> 854711.18 | N97: =M94-N94 -> -274381.91 | ... S97: =R94-S94 -> -190253.57
P100: We have assumed working capital amounts per day in terminal year are equal to the previous year.
B104: Depreciation Schedule
B106: All figures in USD thousands unless stated | F106: =F$5 -> 2020 | G106: =G$5 -> 2021 | H106: =H$5 -> 2022 | I106: =I$5 -> 2023 | J106: =J$5 -> 2024 | K106: =K$5 -> 2025 | L106: =L$5 -> 2026 | M106: =M$5 -> 2027 | ... R106: =R$5 -> 2032
B107: =$B$6 -> Model Running: Base Case Drivers
B109: Capital Expenditure | G109: 6421000 | H109: 13660000 | I109: 32768000 | J109: -2035000 | K109: =Inputs!G24 -> 18840000 | L109: =Inputs!H24 -> 19544000 | M109: =Inputs!I24 -> 19480000 | N109: =Inputs!J24 -> 20376000 | O109: =Inputs!K24 -> 19608000 | P109: =Inputs!L24 -> 19520000 | Q109: =Inputs!M24 -> 19520000 | R109: =Inputs!N24 -> 19520000
B112: EXISTING ASSET DEPRECIATION 1 | D112: Years | K112: Percent of Full Year
B113: Useful Life: Existing Assets | D113: =Inputs!$L$109 -> 16 | K113: 1 | L113: =K113+1 -> 2 | M113: =L113+1 -> 3 | N113: =M113+1 -> 4 | O113: =N113+1 -> 5 | P113: =O113+1 -> 6 | Q113: =P113+1 -> 7 | R113: =Q113+1 -> 8
B114: =CONCATENATE("PP&E at End of ",J106) -> PP&E at End of 2024 | D114: =Inputs!$L$95 -> 136285000 | K114: =MIN($D113-SUM($J114:J114),1) -> 1 | L114: =MIN($D113-SUM($J114:K114),1) -> 1 | M114: =MIN($D113-SUM($J114:L114),1) -> 1 | N114: =MIN($D113-SUM($J114:M114),1) -> 1 | O114: =MIN($D113-SUM($J114:N114),1) -> 1 | P114: =MIN($D113-SUM($J114:O114),1) -> 1 | Q114: =MIN($D113-SUM($J114:P114),1) -> 1 | R114: =MIN($D113-SUM($J114:Q114),1) -> 1
B118: NEW ASSET DEPRECIATION 1 | D118: Years | K118: Percent of Full Year
B119: Useful Life: New Assets | D119: =Inputs!$L$110 -> 20 | K119: 1 | L119: =K119+1 -> 2 | M119: =L119+1 -> 3 | N119: =M119+1 -> 4 | O119: =N119+1 -> 5 | P119: =O119+1 -> 6 | Q119: =P119+1 -> 7 | R119: =Q119+1 -> 8
B120: First Year Accounting Depreciation | D120: =Inputs!$L$108 -> 0.5 | K120: =IF(J120="",$D$120,MIN($D119-SUM($J120:J120),1)) -> 0.5 | L120: =IF(K120="",$D$120,MIN($D119-SUM($J120:K120),1)) -> 1 | M120: =IF(L120="",$D$120,MIN($D119-SUM($J120:L120),1)) -> 1 | N120: =IF(M120="",$D$120,MIN($D119-SUM($J120:M120),1)) -> 1 | O120: =IF(N120="",$D$120,MIN($D119-SUM($J120:N120),1)) -> 1 | P120: =IF(O120="",$D$120,MIN($D119-SUM($J120:O120),1)) -> 1 | Q120: =IF(P120="",$D$120,MIN($D119-SUM($J120:P120),1)) -> 1 | R120: =IF(Q120="",$D$120,MIN($D119-SUM($J120:Q120),1)) -> 1
K122: Percent of Full Year
H123: Year | I123: Life | K123: =K$106 -> 2025 | L123: =L$106 -> 2026 | M123: =M$106 -> 2027 | N123: =N$106 -> 2028 | O123: =O$106 -> 2029 | P123: =P$106 -> 2030 | Q123: =Q$106 -> 2031 | R123: =R$106 -> 2032
H124: =K106 -> 2025 | I124: =$D$119 -> 20 | K124: =K120 -> 0.5 | L124: =L120 -> 1 | M124: =M120 -> 1 | N124: =N120 -> 1 | O124: =O120 -> 1 | P124: =P120 -> 1 | Q124: =Q120 -> 1 | R124: =R120 -> 1
H125: =H124+1 -> 2026 | I125: =$D$119 -> 20 | K125: =J124 -> 0 | L125: =K124 -> 0.5 | M125: =L124 -> 1 | N125: =M124 -> 1 | O125: =N124 -> 1 | P125: =O124 -> 1 | Q125: =P124 -> 1 | R125: =Q124 -> 1
H126: =H125+1 -> 2027 | I126: =$D$119 -> 20 | K126: =J125 -> 0 | L126: =K125 -> 0 | M126: =L125 -> 0.5 | N126: =M125 -> 1 | O126: =N125 -> 1 | P126: =O125 -> 1 | Q126: =P125 -> 1 | R126: =Q125 -> 1
H127: =H126+1 -> 2028 | I127: =$D$119 -> 20 | K127: =J126 -> 0 | L127: =K126 -> 0 | M127: =L126 -> 0 | N127: =M126 -> 0.5 | O127: =N126 -> 1 | P127: =O126 -> 1 | Q127: =P126 -> 1 | R127: =Q126 -> 1
H128: =H127+1 -> 2029 | I128: =$D$119 -> 20 | K128: =J127 -> 0 | L128: =K127 -> 0 | M128: =L127 -> 0 | N128: =M127 -> 0 | O128: =N127 -> 0.5 | P128: =O127 -> 1 | Q128: =P127 -> 1 | R128: =Q127 -> 1
H129: =H128+1 -> 2030 | I129: =$D$119 -> 20 | K129: =J128 -> 0 | L129: =K128 -> 0 | M129: =L128 -> 0 | N129: =M128 -> 0 | O129: =N128 -> 0 | P129: =O128 -> 0.5 | Q129: =P128 -> 1 | R129: =Q128 -> 1
H130: =H129+1 -> 2031 | I130: =$D$119 -> 20 | K130: =J129 -> 0 | L130: =K129 -> 0 | M130: =L129 -> 0 | N130: =M129 -> 0 | O130: =N129 -> 0 | P130: =O129 -> 0 | Q130: =P129 -> 0.5 | R130: =Q129 -> 1
H131: =H130+1 -> 2032 | I131: =$D$119 -> 20 | K131: =J130 -> 0 | L131: =K130 -> 0 | M131: =L130 -> 0 | N131: =M130 -> 0 | O131: =N130 -> 0 | P131: =O130 -> 0 | Q131: =P130 -> 0 | R131: =Q130 -> 0.5
K134: Amounts for Depreciation
H135: Year | I135: Capex | J135: Per Yr | K135: =K$106 -> 2025 | L135: =L$106 -> 2026 | M135: =M$106 -> 2027 | N135: =N$106 -> 2028 | O135: =O$106 -> 2029 | P135: =P$106 -> 2030 | Q135: =Q$106 -> 2031 | R135: =R$106 -> 2032
H136: =H124 -> 2025 | I136: =SUMIF($K$106:$R$106,H136,$K$109:$R$109) -> 18840000 | J136: =I136/I124 -> 942000 | K136: =$J136*K124 -> 471000 | L136: =$J136*L124 -> 942000 | M136: =$J136*M124 -> 942000 | N136: =$J136*N124 -> 942000 | O136: =$J136*O124 -> 942000 | P136: =$J136*P124 -> 942000 | Q136: =$J136*Q124 -> 942000 | R136: =$J136*R124 -> 942000
H137: =H125 -> 2026 | I137: =SUMIF($K$106:$R$106,H137,$K$109:$R$109) -> 19544000 | J137: =I137/I125 -> 977200 | K137: =$J137*K125 -> 0 | L137: =$J137*L125 -> 488600 | M137: =$J137*M125 -> 977200 | N137: =$J137*N125 -> 977200 | O137: =$J137*O125 -> 977200 | P137: =$J137*P125 -> 977200 | Q137: =$J137*Q125 -> 977200 | R137: =$J137*R125 -> 977200
H138: =H126 -> 2027 | I138: =SUMIF($K$106:$R$106,H138,$K$109:$R$109) -> 19480000 | J138: =I138/I126 -> 974000 | K138: =$J138*K126 -> 0 | L138: =$J138*L126 -> 0 | M138: =$J138*M126 -> 487000 | N138: =$J138*N126 -> 974000 | O138: =$J138*O126 -> 974000 | P138: =$J138*P126 -> 974000 | Q138: =$J138*Q126 -> 974000 | R138: =$J138*R126 -> 974000
H139: =H127 -> 2028 | I139: =SUMIF($K$106:$R$106,H139,$K$109:$R$109) -> 20376000 | J139: =I139/I127 -> 1018800 | K139: =$J139*K127 -> 0 | L139: =$J139*L127 -> 0 | M139: =$J139*M127 -> 0 | N139: =$J139*N127 -> 509400 | O139: =$J139*O127 -> 1018800 | P139: =$J139*P127 -> 1018800 | Q139: =$J139*Q127 -> 1018800 | R139: =$J139*R127 -> 1018800
H140: =H128 -> 2029 | I140: =SUMIF($K$106:$R$106,H140,$K$109:$R$109) -> 19608000 | J140: =I140/I128 -> 980400 | K140: =$J140*K128 -> 0 | L140: =$J140*L128 -> 0 | M140: =$J140*M128 -> 0 | N140: =$J140*N128 -> 0 | O140: =$J140*O128 -> 490200 | P140: =$J140*P128 -> 980400 | Q140: =$J140*Q128 -> 980400 | R140: =$J140*R128 -> 980400
H141: =H129 -> 2030 | I141: =SUMIF($K$106:$R$106,H141,$K$109:$R$109) -> 19520000 | J141: =I141/I129 -> 976000 | K141: =$J141*K129 -> 0 | L141: =$J141*L129 -> 0 | M141: =$J141*M129 -> 0 | N141: =$J141*N129 -> 0 | O141: =$J141*O129 -> 0 | P141: =$J141*P129 -> 488000 | Q141: =$J141*Q129 -> 976000 | R141: =$J141*R129 -> 976000
H142: =H130 -> 2031 | I142: =SUMIF($K$106:$R$106,H142,$K$109:$R$109) -> 19520000 | J142: =I142/I130 -> 976000 | K142: =$J142*K130 -> 0 | L142: =$J142*L130 -> 0 | M142: =$J142*M130 -> 0 | N142: =$J142*N130 -> 0 | O142: =$J142*O130 -> 0 | P142: =$J142*P130 -> 0 | Q142: =$J142*Q130 -> 488000 | R142: =$J142*R130 -> 976000
H143: =H131 -> 2032 | I143: =SUMIF($K$106:$R$106,H143,$K$109:$R$109) -> 19520000 | J143: =I143/I131 -> 976000 | K143: =$J143*K131 -> 0 | L143: =$J143*L131 -> 0 | M143: =$J143*M131 -> 0 | N143: =$J143*N131 -> 0 | O143: =$J143*O131 -> 0 | P143: =$J143*P131 -> 0 | Q143: =$J143*Q131 -> 0 | R143: =$J143*R131 -> 488000
B146: TOTAL ASSET DEPRECIATION 2
B147: Existing Assets | K147: =($D$114/$D$113)*K114 -> 8517812.5 | L147: =($D$114/$D$113)*L114 -> 8517812.5 | M147: =($D$114/$D$113)*M114 -> 8517812.5 | N147: =($D$114/$D$113)*N114 -> 8517812.5 | O147: =($D$114/$D$113)*O114 -> 8517812.5 | P147: =($D$114/$D$113)*P114 -> 8517812.5 | Q147: =($D$114/$D$113)*Q114 -> 8517812.5 | R147: =($D$114/$D$113)*R114 -> 8517812.5
B148: New Assets | K148: =SUM(K136:K143) -> 471000 | L148: =SUM(L136:L140) -> 1430600 | M148: =SUM(M136:M140) -> 2406200 | N148: =SUM(N136:N140) -> 3402600 | O148: =SUM(O136:O140) -> 4402200 | P148: =SUM(P136:P140) -> 4892400 | Q148: =SUM(Q136:Q140) -> 4892400 | R148: =SUM(R136:R140) -> 4892400
B149: Total Depreciation | K149: =SUM(K147:K148) -> 8988812.5 | L149: =SUM(L147:L148) -> 9948412.5 | M149: =SUM(M147:M148) -> 10924012 | N149: =SUM(N147:N148) -> 11920412 | O149: =SUM(O147:O148) -> 12920012 | P149: =SUM(P147:P148) -> 13410212 | Q149: =SUM(Q147:Q148) -> 13410212 | R149: =SUM(R147:R148) -> 13410212
O152: All PP&E and capital expenditure is assumed depreciable (i.e. no land balance).
O153: This schedule calculates depreciation on a straight-line basis.
B157: Asset Schedule
B159: All figures in USD thousands unless stated | J159: =J$5 -> 2024 | K159: =K$5 -> 2025 | L159: =L$5 -> 2026 | M159: =M$5 -> 2027 | N159: =N$5 -> 2028 | O159: =O$5 -> 2029 | P159: =P$5 -> 2030 | Q159: =Q$5 -> 2031 | R159: =R$5 -> 2032
B160: =$B$6 -> Model Running: Base Case Drivers
B162: Capital Expenditure | K162: =K109 -> 18840000 | L162: =L109 -> 19544000 | M162: =M109 -> 19480000 | N162: =N109 -> 20376000 | O162: =O109 -> 19608000 | P162: =P109 -> 19520000 | Q162: =Q109 -> 19520000 | R162: =R109 -> 19520000
B164: First Year Tax Depreciation | D164: =Inputs!$L$106 -> 0.5
B165: Blended Tax Depreciation Rate | D165: =Inputs!$L$107 -> 0.15
B168: PROPERTY PLANT & EQUIPMENT 1
B169: Beginning | K169: =J172 -> 136285000 | L169: =K172 -> 1.4613619e+08 | M169: =L172 -> 155731775 | N169: =M172 -> 1.6428776e+08 | O169: =N172 -> 172743350 | P169: =O172 -> 1.7943134e+08 | Q169: =P172 -> 185541125 | R169: =Q172 -> 1.9165091e+08
B170: Capital Expenditure | K170: =K162 -> 18840000 | L170: =L162 -> 19544000 | M170: =M162 -> 19480000 | N170: =N162 -> 20376000 | O170: =O162 -> 19608000 | P170: =P162 -> 19520000 | Q170: =Q162 -> 19520000 | R170: =R162 -> 19520000
B171: Accounting Depreciation | K171: =-K149 -> -8988812.5 | L171: =-L149 -> -9948412.5 | M171: =-M149 -> -10924012 | N171: =-N149 -> -11920412 | O171: =-O149 -> -12920012 | P171: =-P149 -> -13410212 | Q171: =-Q149 -> -13410212 | R171: =-R149 -> -13410212
B172: Ending | J172: =$D$114 -> 136285000 | K172: =SUM(K169:K171) -> 1.4613619e+08 | L172: =SUM(L169:L171) -> 155731775 | M172: =SUM(M169:M171) -> 1.6428776e+08 | N172: =SUM(N169:N171) -> 172743350 | O172: =SUM(O169:O171) -> 1.7943134e+08 | P172: =SUM(P169:P171) -> 185541125 | Q172: =SUM(Q169:Q171) -> 1.9165091e+08 | R172: =SUM(R169:R171) -> 197760700
...

Sheet Comparables
B3: Comparable Company Analysis
C5: Market Data | G5: Financial Data | L5: Valuation
C6: Price | D6: Market Cap | E6: EV | G6: Sales | H6: EBITDA | I6: EBIT | J6: Earnings | L6: EV/Sales | M6: EV/EBITDA | N6: EV/EBIT | O6: P/E | S6: EV/Sales | T6: EV/EBITDA | U6: EV/EBIT | V6: P/E
B7: Company Name | C7: ($/share) | D7: ($MM) | E7: ($MM) | G7: ($MM) | H7: ($MM) | I7: ($MM) | J7: ($MM) | L7: x | M7: x | N7: x | O7: x | S7: x | T7: x | U7: x | V7: x
B8: Petroleo Brasileiro S.A.- Petrobras | C8: 11.61 | D8: 74750 | E8: 136820 | G8: 85530 | H8: 33190 | I8: 24160 | J8: 12990 | L8: =E8/G8 -> 1.5996726 | M8: =E8/H8 -> 4.122326 | N8: =E8/I8 -> 5.6630795 | O8: =D8/J8 -> 5.7544265 | Q8: Petroleo Brasileiro S.A.- Petrobras | S8: 1.5996726 | T8: 4.122326 | U8: 5.6630795 | V8: 5.7544265
B9: SHELL | C9: 74.21 | D9: 218930 | E9: 257930 | G9: 272010 | H9: 48290 | I9: 28930 | J9: 13600 | L9: =E9/G9 -> 0.9482372 | M9: =E9/H9 -> 5.3412715 | N9: =E9/I9 -> 8.9156585 | O9: =D9/J9 -> 16.097794 | Q9: SHELL | S9: 0.9482372 | T9: 5.3412715 | U9: 8.9156585 | V9: 16.097794
B10: Total Energies (TTE) | C10: 59.83 | D10: 143450 | E10: 166280 | G10: 187120 | H10: 37380 | I10: 23940 | J10: 12790 | L10: =E10/G10 -> 0.88862762 | M10: =E10/H10 -> 4.4483681 | N10: =E10/I10 -> 6.9456976 | O10: =D10/J10 -> 11.215794 | Q10: Total Energies (TTE) | S10: 0.88862762 | T10: 4.4483681 | U10: 6.9456976 | V10: 11.215794
B11: Equinor ASA (EQNR) | C11: 25.37 | D11: 74710 | E11: 73110 | G11: 106470 | H11: 37610 | I11: 29650 | J11: 8220 | L11: =E11/G11 -> 0.6866723 | M11: =E11/H11 -> 1.9438979 | N11: =E11/I11 -> 2.4657673 | O11: =D11/J11 -> 9.0888078 | Q11: Equinor ASA (EQNR) | S11: 0.6866723 | T11: 1.9438979 | U11: 2.4657673 | V11: 9.0888078
B12: Candadian Natural Resources (CNQ) | C12: 32.45 | D12: 67720 | E12: 77730 | F12: § | G12: 38000 | H12: 17670 | I12: 11060 | J12: 8320 | L12: =E12/G12 -> 2.0455263 | M12: =E12/H12 -> 4.3989813 | N12: =E12/I12 -> 7.0280289 | O12: =D12/J12 -> 8.1394231 | Q12: Candadian Natural Resources (CNQ) | S12: 2.0455263 | T12: 4.3989813 | U12: 7.0280289 | V12: 8.1394231
B13: ENI (E) | C13: 35.52 | D13: 59620 | E13: 74400 | G13: 87030 | H13: 12710 | I13: 6640 | J13: 2270 | L13: =E13/G13 -> 0.85487763 | M13: =E13/H13 -> 5.8536585 | N13: =E13/I13 -> 11.204819 | O13: =D13/J13 -> 26.264317 | Q13: ENI (E) | S13: 0.85487763 | T13: 5.8536585 | U13: 11.204819 | V13: 26.264317
B14: Suncor Energy | C14: 41.53 | D14: 50210 | E14: 58580 | G14: 49730 | H14: 15400 | I14: 8180 | J14: 5660 | L14: =E14/G14 -> 1.177961 | M14: =E14/H14 -> 3.8038961 | N14: =E14/I14 -> 7.1613692 | O14: =D14/J14 -> 8.8710247 | Q14: Suncor Energy | S14: 1.177961 | T14: 3.8038961 | U14: 7.1613692 | V14: 8.8710247
B15: BP | C15: 34.81 | D15: 87870 | E15: 127540 | G15: 186540 | H15: 26430 | I15: 9110 | J15: 560 | L15: =E15/G15 -> 0.68371395 | M15: =E15/H15 -> 4.825577 | N15: =E15/I15 -> 14 | O15: =D15/J15 -> 156.91071 | Q15: BP | S15: 0.68371395 | T15: 4.825577 | U15: 14 | V15: 156.91071
B17: Average | J17: Average | L17: =AVERAGE(L8:L14) -> 1.1716535 | M17: =AVERAGE(M8:M14) -> 4.2731999 | N17: =AVERAGE(N8:N14) -> 7.0549172 | O17: =AVERAGE(O8:O14) -> 12.204512
B18: Median | J18: Median | L18: =MEDIAN(L8:L14) -> 0.9482372 | M18: =MEDIAN(M8:M14) -> 4.3989813 | N18: =MEDIAN(N8:N14) -> 7.0280289 | O18: =MEDIAN(O8:O14) -> 9.0888078
B19: Minimum | J19: Minimum | L19: =MIN(L8:L14) -> 0.6866723 | M19: =MIN(M8:M14) -> 1.9438979 | N19: =MIN(N8:N14) -> 2.4657673 | O19: =MIN(O8:O14) -> 5.7544265
B20: Max | J20: Max | L20: =MAX(L8:L14) -> 2.0455263 | M20: =MAX(M8:M14) -> 5.8536585 | N20: =MAX(N8:N14) -> 11.204819 | O20: =MAX(O8:O14) -> 26.264317
B22: Net Debt | C22: =Inputs!L94/1000 -> 5240
B23: Number of shares | C23: =Inputs!F105/1000 -> 12888.733
C26: Implied EV (USD m) | G26: Implied Equity Value (USD | L26: Fair Price
B27: EV/Sales | C27: =L18*G8 -> 81102.727 | G27: =C27-$C$22 -> 75862.727 | L27: =G27/$C$23 -> 5.8859726
B28: EV/EBITDA | C28: =M18*H8 -> 146002.19 | G28: =C28-$C$22 -> 140762.19 | L28: =G28/$C$23 -> 10.921337
B29: EV/EBIT | C29: =N18*I8 -> 169797.18 | G29: =C29-$C$22 -> 164557.18 | L29: =G29/$C$23 -> 12.767522
B30: P/E | C30: =O18*J8 -> 118063.61 | G30: =C30-$C$22 -> 112823.61 | L30: =G30/$C$23 -> 8.7536622
B31: Average | L31: =AVERAGE(L27:O30) -> 9.5821234

Sheet CAPM Beta 
W3: Number of weeks | Y3: 52
A4: Date | B4: Adj Close | E4: Close | H4: High | K4: Low | N4: Open | Q4: Volume | W4: % Change Weekly
A5: Ticker | B5: PBR | C5: PBR-A | D5: ^GSPC | E5: PBR | F5: PBR-A | G5: ^GSPC | H5: High_PBR | I5: High_PBR-A | J5: High_^GSPC | K5: Low_PBR | L5: Low_PBR-A | M5: Low_^GSPC | N5: Open_PBR | O5: Open_PBR-A | P5: Open_^GSPC | Q5: Volume_PBR | R5: Volume_PBR-A | S5: Volume_^GSPC | W5: PBR | X5: PBR-A | Y5: S&P 500
A6: 43745 | B6: 4.3184981 | C6: 3.7396441 | D6: 2970.27 | E6: 14.4 | F6: 13.31 | G6: 2970.27 | H6: 14.52 | I6: 13.37 | J6: 2993.28 | K6: 13.95 | L6: 12.81 | M6: 2917.1201 | N6: 14.08 | O6: 12.92 | P6: 2918.55 | Q6: 25292900 | R6: 7548900 | S6: 6815720000 | AD6: PBR
A7: 43752 | B7: 4.3574848 | C7: 3.7593119 | D7: 2986.2 | E7: 14.53 | F7: 13.38 | G7: 2986.2 | H7: 14.77 | I7: 13.52 | J7: 3008.29 | K7: 14.13 | L7: 13.02 | M7: 2962.9399 | N7: 14.2 | O7: 13.11 | P7: 2965.8101 | Q7: 61471400 | R7: 14142900 | S7: 15507120000 | W7: =B7/B6-1 -> 0.0090278337 | X7: =C7/C6-1 -> 0.0052592877 | Y7: =D7/D6-1 -> 0.0053631258 | AB7: Covariance | AD7: =_xlfn.COVARIANCE.S(W7:W319,Y7:Y319) -> 0.00065995749
A8: 43759 | B8: 4.7533464 | C8: 4.1020894 | D8: 3022.55 | E8: 15.85 | F8: 14.6 | G8: 3022.55 | H8: 16.049999 | I8: 14.74 | J8: 3027.3899 | K8: 14.44 | L8: 13.27 | M8: 2991.21 | N8: 14.48 | O8: 13.33 | P8: 2996.48 | Q8: 101649000 | R8: 32232800 | S8: 17288670000 | W8: =B8/B7-1 -> 0.090846358 | X8: =C8/C7-1 -> 0.091180912 | Y8: =D8/D7-1 -> 0.012172694 | AB8: Variance | AD8: =_xlfn.VAR.S(W7:W319) -> 0.0050765336
A9: 43766 | B9: 4.9302859 | C9: 4.2790966 | D9: 3066.9099 | E9: 16.440001 | F9: 15.23 | G9: 3066.9099 | H9: 16.84 | I9: 15.67 | J9: 3066.95 | K9: 15.79 | L9: 14.59 | M9: 3023.1899 | N9: 15.92 | O9: 14.66 | P9: 3032.1201 | Q9: 118030900 | R9: 52604700 | S9: 19004660000 | W9: =B9/B8-1 -> 0.037224193 | X9: =C9/C8-1 -> 0.043150497 | Y9: =D9/D8-1 -> 0.014676304 | AB9: R(PBR) Weekly | AD9: =AVERAGE(W7:W754) -> 0.005741488
A10: 43773 | B10: 4.7443504 | C10: 4.0346575 | D10: 3093.0801 | E10: 15.82 | F10: 14.36 | G10: 3093.0801 | H10: 16.629999 | I10: 15.4 | J10: 3097.77 | K10: 15.53 | L10: 14.13 | M10: 3065.8899 | N10: 16.48 | O10: 15.35 | P10: 3078.96 | Q10: 139901000 | R10: 50447900 | S10: 20794290000 | W10: =B10/B9-1 -> -0.037712924 | X10: =C10/C9-1 -> -0.057124002 | Y10: =D10/D9-1 -> 0.008533073 | AB10: R(PBR) Yearly | AD10: =AD9*Y3 -> 0.29855738
A11: 43780 | B11: 4.6303887 | C11: 4.0065603 | D11: 3120.46 | E11: 15.44 | F11: 14.26 | G11: 3120.46 | H11: 16.049999 | I11: 14.68 | J11: 3120.46 | K11: 15.07 | L11: 13.93 | M11: 3075.8201 | N11: 15.76 | O11: 14.41 | P11: 3080.3301 | Q11: 77522700 | R11: 18401200 | S11: 16692290000 | W11: =B11/B10-1 -> -0.024020506 | X11: =C11/C10-1 -> -0.0069639499 | Y11: =D11/D10-1 -> 0.0088519799 | AB11: Rm weekly | AD11: =AVERAGE(Y7:Y319) -> 0.0028986078
A12: 43787 | B12: 4.6018844 | C12: 4.0208998 | D12: 3110.29 | E12: 15.25 | F12: 14.22 | G12: 3110.29 | H12: 15.56 | I12: 14.48 | J12: 3127.6399 | K12: 14.81 | L12: 13.65 | M12: 3091.4099 | N12: 15.27 | O12: 14.11 | P12: 3117.9099 | Q12: 91900100 | R12: 21447100 | S12: 18074100000 | W12: =B12/B11-1 -> -0.0061559349 | X12: =C12/C11-1 -> 0.0035789919 | Y12: =D12/D11-1 -> -0.0032591099 | AB12: Rm Yearly | AD12: =AD11*Y3 -> 0.15072761
A13: 43794 | B13: 4.4449673 | C13: 3.8795183 | D13: 3140.98 | E13: 14.73 | F13: 13.72 | G13: 3140.98 | H13: 15.28 | I13: 14.21 | J13: 3154.26 | K13: 14.57 | L13: 13.59 | M13: 3117.4399 | N13: 15.23 | O13: 14.2 | P13: 3117.4399 | Q13: 54940700 | R13: 22907000 | S13: 12893650000 | W13: =B13/B12-1 -> -0.034098444 | X13: =C13/C12-1 -> -0.035161658 | Y13: =D13/D12-1 -> 0.0098672281 | AB13: Beta | AD13: =AD7/AD8 -> 0.1300016
A14: 43801 | B14: 4.6803417 | C14: 4.1396599 | D14: 3145.9099 | E14: 15.51 | F14: 14.64 | G14: 3145.9099 | H14: 15.59 | I14: 14.68 | J14: 3150.6001 | K14: 14.55 | L14: 13.62 | M14: 3070.3301 | N14: 14.92 | O14: 13.88 | P14: 3143.8501 | Q14: 73806500 | R14: 40730900 | S14: 17504100000 | W14: =B14/B13-1 -> 0.052953022 | X14: =C14/C13-1 -> 0.067055132 | Y14: =D14/D13-1 -> 0.0015695521 | AB14: Rf | AD14: 0.0404
A15: 43808 | B15: 4.6199903 | C15: 4.1283503 | D15: 3168.8 | E15: 15.31 | F15: 14.6 | G15: 3168.8 | H15: 16.120001 | I15: 15.17 | J15: 3182.6799 | K15: 15.2 | L15: 14.48 | M15: 3126.0901 | N15: 15.28 | O15: 14.48 | P15: 3141.8601 | Q15: 83652800 | R15: 28673000 | S15: 17765280000 | W15: =B15/B14-1 -> -0.012894651 | X15: =C15/C14-1 -> -0.0027320176 | Y15: =D15/D14-1 -> 0.0072761577 | AB15: Expected Return | AD15: =AD14+AD13*(AD12-AD14) -> 0.054742765
A16: 43815 | B16: 4.6954308 | C16: 4.1453152 | D16: 3221.22 | E16: 15.56 | F16: 14.66 | G16: 3221.22 | H16: 15.98 | I16: 15.12 | J16: 3225.6499 | K16: 15.21 | L16: 14.47 | M16: 3183.6299 | N16: 15.21 | O16: 14.57 | P16: 3183.6299 | Q16: 79860600 | R16: 23957900 | S16: 22184930000 | W16: =B16/B15-1 -> 0.016329126 | X16: =C16/C15-1 -> 0.0041093685 | Y16: =D16/D15-1 -> 0.016542515 | AB16: Alpha | AD16: =AD10-AD15 -> 0.24381461
A17: 43822 | B17: 4.8040648 | C17: 4.2357998 | D17: 3240.02 | E17: 15.92 | F17: 14.98 | G17: 3240.02 | H17: 16.129999 | I17: 15.24 | J17: 3247.9299 | K17: 15.65 | L17: 14.73 | M17: 3220.51 | N17: 15.69 | O17: 14.76 | P17: 3226.05 | Q17: 34692000 | R17: 6962400 | S17: 8954750000 | W17: =B17/B16-1 -> 0.023136108 | X17: =C17/C16-1 -> 0.021828164 | Y17: =D17/D16-1 -> 0.0058363133
A18: 43829 | B18: 4.8251872 | C18: 4.3167663 | D18: 3234.8501 | E18: 15.99 | F18: 15.07 | G18: 3234.8501 | H18: 16.290001 | I18: 15.31 | J18: 3258.1399 | K18: 15.75 | L18: 14.8 | M18: 3212.03 | N18: 16.09 | O18: 15.15 | P18: 3240.0901 | Q18: 47135400 | R18: 16546100 | S18: 12861110000 | W18: =B18/B17-1 -> 0.0043967883 | X18: =C18/C17-1 -> 0.019114802 | Y18: =D18/D17-1 -> -0.001595645
A19: 43836 | B19: 4.7195716 | C19: 4.2136455 | D19: 3265.3501 | E19: 15.64 | F19: 14.71 | G19: 3265.3501 | H19: 16.299999 | I19: 15.25 | J19: 3282.99 | K19: 15.6 | L19: 14.68 | M19: 3214.6399 | N19: 15.84 | O19: 15.01 | P19: 3217.55 | Q19: 73897700 | R19: 27154600 | S19: 17721020000 | W19: =B19/B18-1 -> -0.021888398 | X19: =C19/C18-1 -> -0.023888438 | Y19: =D19/D18-1 -> 0.0094285667
A20: 43843 | B20: 4.5747261 | C20: 4.0847435 | D20: 3329.6201 | E20: 15.16 | F20: 14.26 | G20: 3329.6201 | H20: 15.59 | I20: 14.7 | J20: 3329.8799 | K20: 14.73 | L20: 13.94 | M20: 3268.4299 | N20: 15.54 | O20: 14.65 | P20: 3271.1299 | Q20: 86529900 | R20: 23782400 | S20: 18135300000 | W20: =B20/B19-1 -> -0.030690389 | X20: =C20/C19-1 -> -0.030591553 | Y20: =D20/D19-1 -> 0.019682428
A21: 43850 | B21: 4.457037 | C21: 4.0074024 | D21: 3295.47 | E21: 14.77 | F21: 13.99 | G21: 3295.47 | H21: 15.1 | I21: 14.23 | J21: 3337.77 | K21: 14.44 | L21: 13.77 | M21: 3281.53 | N21: 15.1 | O21: 14.21 | P21: 3321.03 | Q21: 69458800 | R21: 33810100 | S21: 15204110000 | W21: =B21/B20-1 -> -0.025725941 | X21: =C21/C20-1 -> -0.018934134 | Y21: =D21/D20-1 -> -0.010256469
A22: 43857 | B22: 4.257874 | C22: 3.7954307 | D22: 3225.52 | E22: 14.11 | F22: 13.25 | G22: 3225.52 | H22: 14.7 | I22: 13.86 | J22: 3293.47 | K22: 14.01 | L22: 13.17 | M22: 3214.6799 | N22: 14.17 | O22: 13.38 | P22: 3247.1599 | Q22: 94569600 | R22: 32642200 | S22: 19282920000 | W22: =B22/B21-1 -> -0.044685059 | X22: =C22/C21-1 -> -0.052895052 | Y22: =D22/D21-1 -> -0.021226093
A23: 43864 | B23: 4.399703 | C23: 3.8383982 | D23: 3327.71 | E23: 14.58 | F23: 13.4 | G23: 3327.71 | H23: 14.98 | I23: 13.79 | J23: 3347.96 | K23: 14.12 | L23: 13.21 | M23: 3235.6599 | N23: 14.24 | O23: 13.32 | P23: 3235.6599 | Q23: 214344700 | R23: 45498700 | S23: 19500010000 | W23: =B23/B22-1 -> 0.033309819 | X23: =C23/C22-1 -> 0.011320865 | Y23: =D23/D22-1 -> 0.031681695 | AB23: Beta PBR | AD23: =SLOPE('CAPM Beta '!Y7:Y317,'CAPM Beta '!W7:W317) -> 0.12976114
A24: 43871 | B24: 4.4178081 | C24: 3.9186041 | D24: 3380.1599 | E24: 14.64 | F24: 13.68 | G24: 3380.1599 | H24: 15.02 | I24: 13.91 | J24: 3385.0901 | K24: 14.23 | L24: 13.21 | M24: 3317.77 | N24: 14.45 | O24: 13.34 | P24: 3318.28 | Q24: 115798600 | R24: 25373100 | S24: 18077170000 | W24: =B24/B23-1 -> 0.0041150573 | X24: =C24/C23-1 -> 0.020895674 | Y24: =D24/D23-1 -> 0.015761575
A25: 43878 | B25: 4.2337327 | C25: 3.7868373 | D25: 3337.75 | E25: 14.03 | F25: 13.22 | G25: 3337.75 | H25: 14.94 | I25: 13.98 | J25: 3393.52 | K25: 13.89 | L25: 13.18 | M25: 3328.45 | N25: 14.32 | O25: 13.37 | P25: 3369.04 | Q25: 81059900 | R25: 23282500 | S25: 15292560000 | W25: =B25/B24-1 -> -0.041666671 | X25: =C25/C24-1 -> -0.033625952 | Y25: =D25/D24-1 -> -0.012546718
A26: 43885 | B26: 3.6513314 | C26: 3.2254009 | D26: 2954.22 | E26: 12.1 | F26: 11.26 | G26: 2954.22 | H26: 13.3 | I26: 12.52 | J26: 3259.8101 | K26: 11.51 | L26: 10.88 | M26: 2855.8401 | N26: 13.14 | O26: 12.5 | P26: 3257.6101 | Q26: 194648700 | R26: 56671200 | S26: 31566850000 | W26: =B26/B25-1 -> -0.13756213 | X26: =C26/C25-1 -> -0.14825998 | Y26: =D26/D25-1 -> -0.11490676
A27: 43892 | B27: 3.1745458 | C27: 2.8329673 | D27: 2972.3701 | E27: 10.52 | F27: 9.8900003 | G27: 2972.3701 | H27: 12.91 | I27: 12.24 | J27: 3136.72 | K27: 10.27 | L27: 9.7200003 | M27: 2901.54 | N27: 12.2 | O27: 11.44 | P27: 2974.28 | Q27: 185800000 | R27: 57378800 | S27: 29965390000 | W27: =B27/B26-1 -> -0.13057858 | X27: =C27/C26-1 -> -0.12166972 | Y27: =D27/D26-1 -> 0.0061438033
A28: 43899 | B28: 1.9855995 | C28: 1.8074844 | D28: 2711.02 | E28: 6.5799999 | F28: 6.3099999 | G28: 2711.02 | H28: 8.5699997 | I28: 7.8899999 | J28: 2882.5901 | K28: 4.8299999 | L28: 4.5500002 | M28: 2478.8601 | N28: 7.5500002 | O28: 7.1799998 | P28: 2863.8899 | Q28: 352597000 | R28: 105456400 | S28: 40664410000 | W28: =B28/B27-1 -> -0.37452484 | X28: =C28/C27-1 -> -0.3619819 | Y28: =D28/D27-1 -> -0.087926499 | AB28: SUMMARY OUTPUT PBR
A29: 43906 | B29: 1.4635496 | C29: 1.3634907 | D29: 2304.9199 | E29: 4.8499999 | F29: 4.7600002 | G29: 2304.9199 | H29: 5.96 | I29: 5.6700001 | J29: 2562.98 | K29: 4.0100002 | L29: 4.1599998 | M29: 2280.52 | N29: 5.4000001 | O29: 4.9200001 | P29: 2508.5901 | Q29: 230755900 | R29: 83601700 | S29: 41985050000 | W29: =B29/B28-1 -> -0.26291803 | X29: =C29/C28-1 -> -0.24564178 | Y29: =D29/D28-1 -> -0.14979605
A30: 43913 | B30: 1.5661492 | C30: 1.5009857 | D30: 2541.47 | E30: 5.1900001 | F30: 5.2399998 | G30: 2541.47 | H30: 6.1599998 | I30: 6.0799999 | J30: 2637.01 | K30: 4.4499998 | L30: 4.3800001 | M30: 2191.8601 | N30: 4.6100001 | O30: 4.4699998 | P30: 2290.71 | Q30: 202178800 | R30: 44837300 | S30: 37243200000 | W30: =B30/B29-1 -> 0.070103275 | X30: =C30/C29-1 -> 0.10084047 | Y30: =D30/D29-1 -> 0.10262832 | AB30: Regression Statistics
A31: 43920 | B31: 1.7381542 | C31: 1.6585315 | D31: 2488.6499 | E31: 5.7600002 | F31: 5.79 | G31: 2488.6499 | H31: 6.4200001 | I31: 6.3899999 | J31: 2641.3899 | K31: 4.8800001 | L31: 4.9499998 | M31: 2447.49 | N31: 5.1500001 | O31: 5.1799998 | P31: 2558.98 | Q31: 188500000 | R31: 52880500 | S31: 30852490000 | W31: =B31/B30-1 -> 0.10982666 | X31: =C31/C30-1 -> 0.10496156 | Y31: =D31/D30-1 -> -0.020783275 | AB31: Multiple R | AC31: 0.34287407
A32: 43927 | B32: 2.0278463 | C32: 1.8790966 | D32: 2789.8201 | E32: 6.7199998 | F32: 6.5599999 | G32: 2789.8201 | H32: 7.46 | I32: 7.3699999 | J32: 2818.5701 | K32: 5.8600001 | L32: 5.73 | M32: 2574.5701 | N32: 5.9499998 | O32: 5.9400001 | P32: 2578.28 | Q32: 165291000 | R32: 46832500 | S32: 27229510000 | W32: =B32/B31-1 -> 0.16666655 | X32: =C32/C31-1 -> 0.13298817 | Y32: =D32/D31-1 -> 0.12101749 | AB32: R Square | AC32: 0.11756263
A33: 43934 | B33: 1.9463705 | C33: 1.7616531 | D33: 2874.5601 | E33: 6.4499998 | F33: 6.1500001 | G33: 2874.5601 | H33: 6.8800001 | I33: 6.6999998 | J33: 2879.22 | K33: 6.0500002 | L33: 5.9099998 | M33: 2721.1699 | N33: 6.6799998 | O33: 6.52 | P33: 2782.46 | Q33: 136073600 | R33: 41113200 | S33: 27176880000 | W33: =B33/B32-1 -> -0.040178515 | X33: =C33/C32-1 -> -0.062500012 | Y33: =D33/D32-1 -> 0.030374715 | AB33: Adjusted R Square | AC33: 0.11472521
A34: 43941 | B34: 1.7079779 | C34: 1.6127005 | D34: 2836.74 | E34: 5.6599998 | F34: 5.6300001 | G34: 2836.74 | H34: 6.5999999 | I34: 6.4200001 | J34: 2868.98 | K34: 5.5100002 | L34: 5.4400001 | M34: 2727.1001 | N34: 6.0300002 | O34: 5.8699999 | P34: 2845.6201 | Q34: 202952000 | R34: 94496400 | S34: 26590900000 | W34: =B34/B33-1 -> -0.12248058 | X34: =C34/C33-1 -> -0.084552746 | Y34: =D34/D33-1 -> -0.01315682 | AB34: Standard Error | AC34: 0.067038252
A35: 43948 | B35: 1.9825824 | C35: 1.8103489 | D35: 2830.71 | E35: 6.5700002 | F35: 6.3200002 | G35: 2830.71 | H35: 7.2199998 | I35: 6.9000001 | J35: 2954.8601 | K35: 5.6900001 | L35: 5.6300001 | M35: 2821.6101 | N35: 5.8299999 | O35: 5.7600002 | P35: 2854.6499 | Q35: 156461900 | R35: 36301000 | S35: 28845520000 | W35: =B35/B34-1 -> 0.16077758 | X35: =C35/C34-1 -> 0.12255742 | Y35: =D35/D34-1 -> -0.0021256898 | AB35: Observations | AC35: 313
A36: 43955 | B36: 2.0700929 | C36: 1.8647742 | D36: 2929.8 | E36: 6.8600001 | F36: 6.5100002 | G36: 2929.8 | H36: 6.9699998 | I36: 6.71 | J36: 2932.1599 | K36: 6.23 | L36: 5.9400001 | M36: 2797.8501 | N36: 6.4499998 | O36: 6.2600002 | P36: 2815.01 | Q36: 132187400 | R36: 44792900 | S36: 24823610000 | W36: =B36/B35-1 -> 0.044139635 | X36: =C36/C35-1 -> 0.030063464 | Y36: =D36/D35-1 -> 0.035005384
A37: 43962 | B37: 1.8407536 | C37: 1.6929057 | D37: 2863.7 | E37: 6.0999999 | F37: 5.9099998 | G37: 2863.7 | H37: 6.8699999 | I37: 6.5599999 | J37: 2945.8201 | K37: 5.7399998 | L37: 5.6199999 | M37: 2766.6399 | N37: 6.7399998 | O37: 6.4200001 | P37: 2915.46 | Q37: 157511700 | R37: 43260600 | S37: 27249840000 | W37: =B37/B36-1 -> -0.11078699 | X37: =C37/C36-1 -> -0.092165883 | Y37: =D37/D36-1 -> -0.0225613 | AB37: ANOVA
A38: 43969 | B38: 2.1304457 | C38: 1.936386 | D38: 2955.45 | E38: 7.0599999 | F38: 6.7600002 | G38: 2955.45 | H38: 7.3400002 | I38: 7.0999999 | J38: 2980.29 | K38: 6.5500002 | L38: 6.29 | M38: 2913.8601 | N38: 6.6500001 | O38: 6.4200001 | P38: 2913.8601 | Q38: 140378100 | R38: 40989900 | S38: 25310860000 | W38: =B38/B37-1 -> 0.15737694 | X38: =C38/C37-1 -> 0.14382392 | Y38: =D38/D37-1 -> 0.032038971 | AC38: df | AD38: SS | AE38: MS | AF38: F | AG38: Significance F
A39: 43976 | B39: 2.3024509 | C39: 2.1598151 | D39: 3044.3101 | E39: 7.6300001 | F39: 7.54 | G39: 3044.3101 | H39: 7.8899999 | I39: 7.5799999 | J39: 3068.6699 | K39: 7.3899999 | L39: 7.1300001 | M39: 2969.75 | N39: 7.7600002 | O39: 7.4499998 | P39: 3004.0801 | Q39: 105351800 | R39: 56544700 | S39: 24991070000 | W39: =B39/B38-1 -> 0.080736709 | X39: =C39/C38-1 -> 0.11538458 | Y39: =D39/D38-1 -> 0.030066524 | AB39: Regression | AC39: 1 | AD39: 0.18620491 | AE39: 0.18620491 | AF39: 41.432942 | AG39: 4.6138567e-10
A40: 43983 | B40: 2.8033762 | C40: 2.5608418 | D40: 3193.9299 | E40: 9.29 | F40: 8.9399996 | G40: 3193.9299 | H40: 9.4099998 | I40: 9.0699997 | J40: 3211.72 | K40: 7.6300001 | L40: 7.4899998 | M40: 3031.54 | N40: 7.6999998 | O40: 7.54 | P40: 3038.78 | Q40: 154807100 | R40: 77335000 | S40: 30977470000 | W40: =B40/B39-1 -> 0.21756177 | X40: =C40/C39-1 -> 0.18567642 | Y40: =D40/D39-1 -> 0.049147383 | AB40: Residual | AC40: 311 | AD40: 1.3976736 | AE40: 0.0044941272
A41: 43990 | B41: 2.558949 | C41: 2.3517354 | D41: 3041.3101 | E41: 8.4799995 | F41: 8.21 | G41: 3041.3101 | H41: 9.7200003 | I41: 9.3500004 | J41: 3233.1299 | K41: 8.0299997 | L41: 7.8400002 | M41: 2984.47 | N41: 9.3400002 | O41: 9.0299997 | P41: 3199.9199 | Q41: 171198600 | R41: 59298100 | S41: 34390750000 | W41: =B41/B40-1 -> -0.087190297 | X41: =C41/C40-1 -> -0.081655355 | Y41: =D41/D40-1 -> -0.047784352 | AB41: Total | AC41: 312 | AD41: 1.5838785
A42: 43997 | B42: 2.5378263 | C42: 2.2829878 | D42: 3097.74 | E42: 8.4099998 | F42: 7.9699998 | G42: 3097.74 | H42: 8.9499998 | I42: 8.6099997 | J42: 3155.53 | K42: 7.54 | L42: 7.5500002 | M42: 2965.6599 | N42: 7.8099999 | O42: 7.6100001 | P42: 2993.76 | Q42: 113463300 | R42: 42640600 | S42: 28959080000 | W42: =B42/B41-1 -> -0.0082544412 | X42: =C42/C41-1 -> -0.029232677 | Y42: =D42/D41-1 -> 0.018554482
A43: 44004 | B43: 2.4231558 | C43: 2.1884604 | D43: 3009.05 | E43: 8.0299997 | F43: 7.6399999 | G43: 3009.05 | H43: 8.9499998 | I43: 8.5699997 | J43: 3154.8999 | K43: 7.98 | L43: 7.6300001 | M43: 3004.6299 | N43: 8.5200005 | O43: 8.2200003 | P43: 3094.4199 | Q43: 104773400 | R43: 30173900 | S43: 27951760000 | W43: =B43/B42-1 -> -0.04518454 | X43: =C43/C42-1 -> -0.041405163 | Y43: =D43/D42-1 -> -0.028630531 | AC43: Coefficients | AD43: Standard Error | AE43: t Stat | AF43: P-value | AG43: Lower 95% | AH43: Upper 95% | AI43: Lower 95,0% | AJ43: Upper 95,0%
A44: 44011 | B44: 2.558949 | C44: 2.3717866 | D44: 3130.01 | E44: 8.4799995 | F44: 8.2799997 | G44: 3130.01 | H44: 8.6899996 | I44: 8.4499998 | J44: 3165.8101 | K44: 7.9899998 | L44: 7.7199998 | M44: 2999.74 | N44: 8.1899996 | O44: 7.8299999 | P44: 3018.5901 | Q44: 68186600 | R44: 21232800 | S44: 17826770000 | W44: =B44/B43-1 -> 0.056039818 | X44: =C44/C43-1 -> 0.083769507 | Y44: =D44/D43-1 -> 0.04019872 | AB44: Intercept | AC44: 0.0031202284 | AD44: 0.0038110456 | AE44: 0.8187329 | AF44: 0.41356573 | AG44: -0.0043784654 | AH44: 0.010618922 | AI44: -0.0043784654 | AJ44: 0.010618922
A45: 44018 | B45: 2.6253371 | C45: 2.4319408 | D45: 3185.04 | E45: 8.6999998 | F45: 8.4899998 | G45: 3185.04 | H45: 8.9300003 | I45: 8.6599998 | J45: 3186.8201 | K45: 8.4300003 | L45: 8.2399998 | M45: 3115.7 | N45: 8.7299995 | O45: 8.5 | P45: 3155.29 | Q45: 92546200 | R45: 31220800 | S45: 23635640000 | W45: =B45/B44-1 -> 0.025943514 | X45: =C45/C44-1 -> 0.0253624 | Y45: =D45/D44-1 -> 0.017581423 | AB45: X Variable 1 | AC45: 0.90431676 | AD45: 0.14049074 | AE45: 6.4368426 | AF45: 4.6138567e-10 | AG45: 0.62788421 | AH45: 1.1807493 | AI45: 0.62788421 | AJ45: 1.1807493
A46: 44025 | B46: 2.6494782 | C46: 2.4118893 | D46: 3224.73 | E46: 8.7799997 | F46: 8.4200001 | G46: 3224.73 | H46: 9.0799999 | I46: 8.7600002 | J46: 3238.28 | K46: 8.29 | L46: 8.0500002 | M46: 3127.6599 | N46: 8.6400003 | O46: 8.3900003 | P46: 3205.0801 | Q46: 100762500 | R46: 30136000 | S46: 22082120000 | W46: =B46/B45-1 -> 0.0091954184 | X46: =C46/C45-1 -> -0.0082450524 | Y46: =D46/D45-1 -> 0.012461363
A47: 44032 | B47: 2.7158656 | C47: 2.5178754 | D47: 3215.6299 | E47: 9 | F47: 8.79 | G47: 3215.6299 | H47: 9.3800001 | I47: 9.1300001 | J47: 3279.99 | K47: 8.6599998 | L47: 8.3699999 | M47: 3200.05 | N47: 8.7200003 | O47: 8.3999996 | P47: 3224.29 | Q47: 115424200 | R47: 33637800 | S47: 20789280000 | W47: =B47/B46-1 -> 0.025056789 | X47: =C47/C46-1 -> 0.043943193 | Y47: =D47/D46-1 -> -0.002821972
A48: 44039 | B48: 2.64099 | C48: 2.443399 | D48: 3271.1201 | E48: 8.6700001 | F48: 8.5299997 | G48: 3271.1201 | H48: 9.3100004 | I48: 9.0699997 | J48: 3272.1699 | K48: 8.6499996 | L48: 8.4899998 | M48: 3204.1299 | N48: 8.9099998 | O48: 8.71 | P48: 3219.8401 | Q48: 84414500 | R48: 25472100 | S48: 21774140000 | W48: =B48/B47-1 -> -0.027569697 | X48: =C48/C47-1 -> -0.029579097 | Y48: =D48/D47-1 -> 0.017256412 | AB48: SUMMARY OUTPUT PBR-A
A49: 44046 | B49: 2.6257594 | C49: 2.4032962 | D49: 3351.28 | E49: 8.6199999 | F49: 8.3900003 | G49: 3351.28 | H49: 9.0799999 | I49: 8.8699999 | J49: 3352.54 | K49: 8.2399998 | L49: 8 | M49: 3284.53 | N49: 8.6300001 | O49: 8.4200001 | P49: 3288.26 | Q49: 106764500 | R49: 21808200 | S49: 21777340000 | W49: =B49/B48-1 -> -0.0057670251 | X49: =C49/C48-1 -> -0.016412678 | Y49: =D49/D48-1 -> 0.02450534
A50: 44053 | B50: 2.6227131 | C50: 2.3947024 | D50: 3372.8501 | E50: 8.6099997 | F50: 8.3599997 | G50: 3372.8501 | H50: 9.0699997 | I50: 8.8000002 | J50: 3387.8899 | K50: 8.5600004 | L50: 8.3100004 | M50: 3326.4399 | N50: 8.7799997 | O50: 8.54 | P50: 3356.04 | Q50: 90638600 | R50: 21426800 | S50: 19619500000 | W50: =B50/B49-1 -> -0.0011601498 | X50: =C50/C49-1 -> -0.0035758379 | Y50: =D50/D49-1 -> 0.0064363671 | AB50: Regression Statistics
A51: 44060 | B51: 2.5130527 | C51: 2.3087683 | D51: 3397.1599 | E51: 8.25 | F51: 8.0600004 | G51: 3397.1599 | H51: 8.8199997 | I51: 8.54 | J51: 3399.96 | K51: 8.1000004 | L51: 7.8899999 | M51: 3354.6899 | N51: 8.6000004 | O51: 8.3800001 | P51: 3380.8601 | Q51: 82543300 | R51: 13086000 | S51: 17745410000 | W51: =B51/B50-1 -> -0.041811812 | X51: =C51/C50-1 -> -0.035885111 | Y51: =D51/D50-1 -> 0.0072074992 | AB51: Multiple R | AC51: 0.3380083
A52: 44067 | B52: 2.5892062 | C52: 2.3775156 | D52: 3508.01 | E52: 8.5 | F52: 8.3000002 | G52: 3508.01 | H52: 8.54 | I52: 8.3199997 | J52: 3509.23 | K52: 8.0600004 | L52: 7.8499999 | M52: 3413.1299 | N52: 8.3800001 | O52: 8.1599998 | P52: 3418.0901 | Q52: 77264900 | R52: 15828500 | S52: 18975990000 | W52: =B52/B51-1 -> 0.030303191 | X52: =C52/C51-1 -> 0.029776605 | Y52: =D52/D51-1 -> 0.032630227 | AB52: R Square | AC52: 0.11424961
A53: 44074 | B53: 2.6836367 | C53: 2.4892306 | D53: 3426.96 | E53: 8.8100004 | F53: 8.6899996 | G53: 3426.96 | H53: 8.9700003 | I53: 8.7600002 | J53: 3588.1101 | K53: 8.1499996 | L53: 7.9899998 | M53: 3349.6299 | N53: 8.3599997 | O53: 8.1700001 | P53: 3509.73 | Q53: 113317200 | R53: 41818900 | S53: 22095960000 | W53: =B53/B52-1 -> 0.036470809 | X53: =C53/C52-1 -> 0.046988159 | Y53: =D53/D52-1 -> -0.023104281 | AB53: Adjusted R Square | AC53: 0.11140154
A54: 44081 | B54: 2.522191 | C54: 2.3689225 | D54: 3340.97 | E54: 8.2799997 | F54: 8.2700005 | G54: 3340.97 | H54: 8.7299995 | I54: 8.6199999 | J54: 3425.55 | K54: 8.2200003 | L54: 8.1099997 | M54: 3310.47 | N54: 8.3900003 | O54: 8.29 | P54: 3371.8799 | Q54: 80802000 | R54: 40341200 | S54: 16545570000 | W54: =B54/B53-1 -> -0.060159268 | X54: =C54/C53-1 -> -0.048331464 | Y54: =D54/D53-1 -> -0.025092207 | AB54: Standard Error | AC54: 0.066659992
A55: 44088 | B55: 2.5008683 | C55: 2.3087683 | D55: 3319.47 | E55: 8.21 | F55: 8.0600004 | G55: 3319.47 | H55: 8.5799999 | I55: 8.4899998 | J55: 3428.9199 | K55: 8.1000004 | L55: 8.0500002 | M55: 3292.3999 | N55: 8.2799997 | O55: 8.2200003 | P55: 3363.5601 | Q55: 110750100 | R55: 40353700 | S55: 24071910000 | W55: =B55/B54-1 -> -0.0084540492 | X55: =C55/C54-1 -> -0.025393064 | Y55: =D55/D54-1 -> -0.0064352569 | AB55: Observations | AC55: 313
A56: 44095 | B56: 2.2724094 | C56: 2.0882034 | D56: 3298.46 | E56: 7.46 | F56: 7.29 | G56: 3298.46 | H56: 8.0699997 | I56: 7.9200001 | J56: 3323.3501 | K56: 7.3200002 | L56: 7.1300001 | M56: 3209.45 | N56: 7.9400001 | O56: 7.8099999 | P56: 3285.5701 | Q56: 116173600 | R56: 32311600 | S56: 21594480000 | W56: =B56/B55-1 -> -0.091351823 | X56: =C56/C55-1 -> -0.095533556 | Y56: =D56/D55-1 -> -0.0063293267
A57: 44102 | B57: 2.0835493 | C57: 1.9306573 | D57: 3348.4199 | E57: 6.8400002 | F57: 6.7399998 | G57: 3348.4199 | H57: 7.6199999 | I57: 7.4299998 | J57: 3397.1799 | K57: 6.8000002 | L57: 6.73 | M57: 3323.6899 | N57: 7.5599999 | O57: 7.4099998 | P57: 3333.8999 | Q57: 138124900 | R57: 36300900 | S57: 20402660000 | W57: =B57/B56-1 -> -0.083110101 | X57: =C57/C56-1 -> -0.075445792 | Y57: =D57/D56-1 -> 0.015146451 | AB57: ANOVA
A58: 44109 | B58: 2.2084405 | C58: 2.056694 | D58: 3477.1399 | E58: 7.25 | F58: 7.1799998 | G58: 3477.1399 | H58: 7.52 | I58: 7.4899998 | J58: 3482.3401 | K58: 6.8800001 | L58: 6.8299999 | M58: 3354.54 | N58: 6.96 | O58: 6.8699999 | P58: 3367.27 | Q58: 103432600 | R58: 35585800 | S58: 19772590000 | W58: =B58/B57-1 -> 0.059941602 | X58: =C58/C57-1 -> 0.06528179 | Y58: =D58/D57-1 -> 0.038442004 | AC58: df | AD58: SS | AE58: MS | AF58: F | AG58: Significance F
A59: 44116 | B59: 2.0896413 | C59: 1.9621665 | D59: 3483.8101 | E59: 6.8600001 | F59: 6.8499999 | G59: 3483.8101 | H59: 7.3499999 | I59: 7.3200002 | J59: 3549.8501 | K59: 6.8499999 | L59: 6.8200002 | M59: 3440.8899 | N59: 7.25 | O59: 7.1999998 | P59: 3500.02 | Q59: 79408200 | R59: 31514700 | S59: 19317950000 | W59: =B59/B58-1 -> -0.053793257 | X59: =C59/C58-1 -> -0.045960888 | Y59: =D59/D58-1 -> 0.001918291 | AB59: Regression | AC59: 1 | AD59: 0.17825194 | AE59: 0.17825194 | AF59: 40.114719 | AG59: 8.3759566e-10
A60: 44123 | B60: 2.2297637 | C60: 2.1025257 | D60: 3465.3899 | E60: 7.3200002 | F60: 7.3400002 | G60: 3465.3899 | H60: 7.5300002 | I60: 7.54 | J60: 3502.4199 | K60: 6.8600001 | L60: 6.8299999 | M60: 3415.3401 | N60: 6.9099998 | O60: 6.8899999 | P60: 3493.6599 | Q60: 105040700 | R60: 30727800 | S60: 19936550000 | W60: =B60/B59-1 -> 0.067055725 | X60: =C60/C59-1 -> 0.071532747 | Y60: =D60/D59-1 -> -0.0052873623 | AB60: Residual | AC60: 311 | AD60: 1.3819455 | AE60: 0.0044435545
A61: 44130 | B61: 2.0195806 | C61: 1.8934187 | D61: 3269.96 | E61: 6.6300001 | F61: 6.6100001 | G61: 3269.96 | H61: 7.27 | I61: 7.27 | J61: 3441.4199 | K61: 6.1500001 | L61: 6.1599998 | M61: 3233.9399 | N61: 7.2600002 | O61: 7.2600002 | P61: 3441.4199 | Q61: 133746700 | R61: 34902000 | S61: 22860370000 | W61: =B61/B60-1 -> -0.094262517 | X61: =C61/C60-1 -> -0.099455165 | Y61: =D61/D60-1 -> -0.056394789 | AB61: Total | AC61: 312 | AD61: 1.5601974
A62: 44137 | B62: 2.2449937 | C62: 2.1025257 | D62: 3509.4399 | E62: 7.3699999 | F62: 7.3400002 | G62: 3509.4399 | H62: 7.4000001 | I62: 7.3800001 | J62: 3529.05 | K62: 6.54 | L62: 6.5 | M62: 3279.74 | N62: 6.71 | O62: 6.71 | P62: 3296.2 | Q62: 94654100 | R62: 19153000 | S62: 23047080000 | W62: =B62/B61-1 -> 0.11161381 | X62: =C62/C61-1 -> 0.11043888 | Y62: =D62/D61-1 -> 0.073236365
A63: 44144 | B63: 2.5983438 | C63: 2.3947024 | D63: 3585.1499 | E63: 8.5299997 | F63: 8.3599997 | G63: 3585.1499 | H63: 8.8000002 | I63: 8.6400003 | J63: 3645.99 | K63: 7.9699998 | L63: 7.9499998 | M63: 3511.9099 | N63: 8.3400002 | O63: 8.2700005 | P63: 3583.04 | Q63: 177331100 | R63: 38656800 | S63: 28872780000 | W63: =B63/B62-1 -> 0.15739472 | X63: =C63/C62-1 -> 0.13896464 | Y63: =D63/D62-1 -> 0.021573232 | AC63: Coefficients | AD63: Standard Error | AE63: t Stat | AF63: P-value | AG63: Lower 95% | AH63: Upper 95% | AI63: Lower 95,0% | AJ63: Upper 95,0%
A64: 44151 | B64: 2.7628353 | C64: 2.512146 | D64: 3557.54 | E64: 9.0699997 | F64: 8.7700005 | G64: 3557.54 | H64: 9.3599997 | I64: 9.1000004 | J64: 3628.51 | K64: 8.75 | L64: 8.5299997 | M64: 3543.8401 | N64: 8.9700003 | O64: 8.75 | P64: 3600.1599 | Q64: 110342400 | R64: 40659200 | S64: 23992240000 | W64: =B64/B63-1 -> 0.063306254 | X64: =C64/C63-1 -> 0.049043071 | Y64: =D64/D63-1 -> -0.007701174 | AB64: Intercept | AC64: 0.0033881815 | AD64: 0.0037895419 | AE64: 0.89408735 | AF64: 0.37196654 | AG64: -0.0040682013 | AH64: 0.010844564 | AI64: -0.0040682013 | AJ64: 0.010844564
A65: 44158 | B65: 3.0278473 | C65: 2.7785425 | D65: 3638.3501 | E65: 9.9399996 | F65: 9.6999998 | G65: 3638.3501 | H65: 10.16 | I65: 9.9799995 | J65: 3644.3101 | K65: 9.21 | L65: 8.9899998 | M65: 3552.77 | N65: 9.3199997 | O65: 9.04 | P65: 3566.8201 | Q65: 107548100 | R65: 50308200 | S65: 19026670000 | W65: =B65/B64-1 -> 0.095920314 | X65: =C65/C64-1 -> 0.10604341 | Y65: =D65/D64-1 -> 0.022715151 | AB65: X Variable 1 | AC65: 0.88479395 | AD65: 0.13969802 | AE65: 6.3336182 | AF65: 8.3759566e-10 | AG65: 0.60992116 | AH65: 1.1596667 | AI65: 0.60992116 | AJ65: 1.1596667
A66: 44165 | B66: 3.3263679 | C66: 3.0649896 | D66: 3699.1201 | E66: 10.92 | F66: 10.7 | G66: 3699.1201 | H66: 11.01 | I66: 10.76 | J66: 3699.2 | K66: 9.54 | L66: 9.1899996 | M66: 3594.3899 | N66: 9.8000002 | O66: 9.6499996 | P66: 3634.1799 | Q66: 139482900 | R66: 45327600 | S66: 26933100000 | W66: =B66/B65-1 -> 0.098591685 | X66: =C66/C65-1 -> 0.10309256 | Y66: =D66/D65-1 -> 0.016702631
A67: 44172 | B67: 3.390337 | C67: 3.1337373 | D67: 3663.46 | E67: 11.13 | F67: 10.94 | G67: 3663.46 | H67: 11.39 | I67: 11.17 | J67: 3712.3899 | K67: 10.42 | L67: 10.23 | M67: 3633.3999 | N67: 10.96 | O67: 10.79 | P67: 3694.73 | Q67: 135950500 | R67: 33662100 | S67: 23655640000 | W67: =B67/B66-1 -> 0.019230926 | X67: =C67/C66-1 -> 0.022430014 | Y67: =D67/D66-1 -> -0.0096401726
A68: 44179 | B68: 3.4390743 | C68: 3.1767037 | D68: 3709.4099 | E68: 11.29 | F68: 11.09 | G68: 3709.4099 | H68: 11.53 | I68: 11.25 | J68: 3726.7 | K68: 10.87 | L68: 10.72 | M68: 3645.8401 | N68: 11.2 | O68: 11.05 | P68: 3675.27 | Q68: 89722500 | R68: 26696600 | S68: 24367880000 | W68: =B68/B67-1 -> 0.014375352 | X68: =C68/C67-1 -> 0.013710902 | Y68: =D68/D67-1 -> 0.012542774
A69: 44186 | B69: 3.3415987 | C69: 3.0964997 | D69: 3703.0601 | E69: 10.97 | F69: 10.81 | G69: 3703.0601 | H69: 11.16 | I69: 10.91 | J69: 3711.24 | K69: 10.66 | L69: 10.47 | M69: 3636.48 | N69: 10.73 | O69: 10.5 | P69: 3684.28 | Q69: 55672600 | R69: 16933900 | S69: 14464830000 | W69: =B69/B68-1 -> -0.028343537 | X69: =C69/C68-1 -> -0.025247558 | Y69: =D69/D68-1 -> -0.0017118231
A70: 44193 | B70: 3.4207983 | C70: 3.1681113 | D70: 3756.0701 | E70: 11.23 | F70: 11.06 | G70: 3756.0701 | H70: 11.27 | I70: 11.07 | J70: 3760.2 | K70: 10.91 | L70: 10.68 | M70: 3723.03 | N70: 10.99 | O70: 10.8 | P70: 3723.03 | Q70: 56122500 | R70: 21385500 | S70: 13262640000 | W70: =B70/B69-1 -> 0.023701096 | X70: =C70/C69-1 -> 0.023126643 | Y70: =D70/D69-1 -> 0.01431519
A71: 44200 | B71: 3.56092 | C71: 3.2970123 | D71: 3824.6799 | E71: 11.69 | F71: 11.51 | G71: 3824.6799 | H71: 11.89 | I71: 11.72 | J71: 3826.6899 | K71: 10.91 | L71: 10.66 | M71: 3662.71 | N71: 11.43 | O71: 11.27 | P71: 3764.6101 | Q71: 125309900 | R71: 41811300 | S71: 25542330000 | W71: =B71/B70-1 -> 0.040961695 | X71: =C71/C70-1 -> 0.040687019 | Y71: =D71/D70-1 -> 0.018266396
A72: 44207 | B72: 3.3202755 | C72: 3.0392094 | D72: 3768.25 | E72: 10.9 | F72: 10.61 | G72: 3768.25 | H72: 11.76 | I72: 11.65 | J72: 3823.6001 | K72: 10.85 | L72: 10.59 | M72: 3749.6201 | N72: 11.38 | O72: 11.12 | P72: 3803.1399 | Q72: 134048100 | R72: 28825800 | S72: 24631190000 | W72: =B72/B71-1 -> -0.067579293 | X72: =C72/C71-1 -> -0.078192902 | Y72: =D72/D71-1 -> -0.014754158
A73: 44214 | B73: 3.104001 | C73: 2.8329673 | D73: 3841.47 | E73: 10.19 | F73: 9.8900003 | G73: 3841.47 | H73: 11.07 | I73: 10.92 | J73: 3861.45 | K73: 10.04 | L73: 9.7799997 | M73: 3780.3701 | N73: 10.94 | O73: 10.7 | P73: 3781.8799 | Q73: 86607200 | R73: 24877500 | S73: 19193280000 | W73: =B73/B72-1 -> -0.065137516 | X73: =C73/C72-1 -> -0.06786044 | Y73: =D73/D72-1 -> 0.019430762
A74: 44221 | B74: 3.0613551 | C74: 2.8014576 | D74: 3714.24 | E74: 10.05 | F74: 9.7799997 | G74: 3714.24 | H74: 10.73 | I74: 10.5 | J74: 3870.8999 | K74: 9.8100004 | L74: 9.5799999 | M74: 3694.1201 | N74: 10.11 | O74: 9.8199997 | P74: 3851.6799 | Q74: 124255400 | R74: 37630500 | S74: 36751000000 | W74: =B74/B73-1 -> -0.01373902 | X74: =C74/C73-1 -> -0.011122486 | Y74: =D74/D73-1 -> -0.033120129
A75: 44228 | B75: 3.3720603 | C75: 3.0964997 | D75: 3886.8301 | E75: 11.07 | F75: 10.81 | G75: 3886.8301 | H75: 11.48 | I75: 11.23 | J75: 3894.5601 | K75: 10.05 | L75: 9.8000002 | M75: 3725.6201 | N75: 10.18 | O75: 9.96 | P75: 3731.1699 | Q75: 122011400 | R75: 28274100 | S75: 25573900000 | W75: =B75/B74-1 -> 0.1014927 | X75: =C75/C74-1 -> 0.10531733 | Y75: =D75/D74-1 -> 0.046467134
A76: 44235 | B76: 3.213661 | C76: 3.0248873 | D76: 3934.8301 | E76: 10.55 | F76: 10.56 | G76: 3934.8301 | H76: 11.04 | I76: 10.79 | J76: 3937.23 | K76: 10.13 | L76: 10.05 | M76: 3884.9399 | N76: 10.88 | O76: 10.65 | P76: 3892.5901 | Q76: 157318900 | R76: 34576200 | S76: 22779770000 | W76: =B76/B75-1 -> -0.046974054 | X76: =C76/C75-1 -> -0.023126874 | Y76: =D76/D75-1 -> 0.012349395
A77: 44242 | B77: 3.0613551 | C77: 2.9074435 | D77: 3906.71 | E77: 10.05 | F77: 10.15 | G77: 3906.71 | H77: 11.09 | I77: 11.08 | J77: 3950.4299 | K77: 9.9300003 | L77: 10.05 | M77: 3885.03 | N77: 10.7 | O77: 10.73 | P77: 3939.6101 | Q77: 147465300 | R77: 26969600 | S77: 19428610000 | W77: =B77/B76-1 -> -0.047393251 | X77: =C77/C76-1 -> -0.038825843 | Y77: =D77/D76-1 -> -0.0071464629
... A319: 45936 | B319: 11.6 | C319: 10.89 | D319: 6552.5098 | E319: 11.6 | F319: 10.89 | G319: 6552.5098 | H319: 12.53 | I319: 11.73 | J319: 6764.5801 | K319: 11.56 | L319: 10.875 | M319: 6550.7798 | N319: 12.46 | O319: 11.69 | P319: 6733.8599 | Q319: 144761987 | R319: 47321408 | S319: 30834404000 | W319: =B319/B318-1 -> -0.064516069 | X319: =C319/C318-1 -> -0.062015447 | Y319: =D319/D318-1 -> -0.024312891

Sheet Assumption Origin
A3: Capex
A4: Industry Name | B4: Number of Firms | C4: Capital Expenditures (US $ millions) | D4: Depreciation & Amort ((US $ millions) | E4: Cap Ex/Deprecn | F4: Acquisitions (US $ millions) | G4: Net R&D (US $ millions) | H4: Net Cap Ex/Sales | I4: Net Cap Ex/ EBIT (1-t) | J4: Sales/ Invested Capital (LTM)
A5: Oil/Gas (Integrated) | B5: 16 | C5: 134000.87 | D5: 94754.431 | E5: 1.4141911 | F5: 119.56 | G5: 458.4336 | H5: 0.024878342 | I5: 0.24370902 | J5: 1.6614566
A6: Oil/Gas (Production and Exploration) | B6: 107 | C6: 36628.439 | D6: 20018.191 | E6: 1.8297577 | F6: 581.095 | G6: 67.6406 | H6: 0.12803494 | I6: 0.49118159 | J6: 0.69009198
A7: Oil/Gas Distribution | B7: 114 | C7: 12408.627 | D7: 5200.327 | E7: 2.3861244 | F7: 744.807 | G7: -1.2308 | H7: 0.05249038 | I7: 0.71075431 | J7: 1.3616032
A8: Oilfield Svcs/Equip. | B8: 231 | C8: 48844.391 | D8: 18395.986 | E8: 2.6551657 | F8: 1464.586 | G8: 145.798 | H8: 0.04090491 | I8: 1.1203162 | J8: 1.8902384
C9: =AVERAGE(C5:C8) -> 57970.582
A11: Inflation | C11: 2025 | D11: 2026 | E11: 2027 | F11: 2028 | G11: 2029 | H11: 2030 | I11: 2031 | J11: 2032
A12: Link: https://www.statista.com/statistics/270812/inflation-rate-in-brazil/ | C12: 0.0531 | D12: 0.0432 | E12: 0.0339 | F12: 0.0296 | G12: 0.0296 | H12: 0.0296 | I12: 0.0296
A14: Industry Name | B14: Number of Firms | C14: ROE | D14: Retention Ratio | E14: Fundamental Growth
A15: Oil/Gas (Integrated) | B15: 16 | C15: 0.18539314 | D15: 0.023678222 | E15: 0.0043897798
A16: Oil/Gas (Production and Exploration) | B16: 107 | C16: 0.2041186 | D16: 0.61615781 | E16: 0.12576927 | F16: =AVERAGE(E16:E18) -> 0.066252138
A17: Oil/Gas Distribution | B17: 114 | C17: 0.12946556 | D17: 0.38307555 | E17: 0.04959509
A18: Oilfield Svcs/Equip. | B18: 231 | C18: 0.077377615 | D18: 0.30231039 | E18: 0.023392057
A21: Industry Name | B21: Number of firms | C21: % of Money Losing firms (Trailing) | D21: Current PE | E21: Trailing PE | F21: Forward PE | G21: Aggregate Mkt Cap/ Net Income (all firms) | H21: Aggregate Mkt Cap/ Trailing Net Income (only money making firms) | I21: Expected growth - next 5 years | J21: PEG Ratio
A22: Oil/Gas (Integrated) | B22: 16 | C22: 0.0625 | D22: 13.269849 | E22: 13.873799 | F22: 9.2634496 | G22: 13.497112 | H22: 14.524554 | I22: -0.035151667 | J22: NA
A23: Oil/Gas (Production and Exploration) | B23: 107 | C23: 0.34579439 | D23: 18.308903 | E23: 16.583415 | F23: 10.332455 | G23: 8.8396194 | H23: 7.1936159 | I23: 0.13173077 | J23: 0.54608471
A24: Oil/Gas Distribution | B24: 114 | C24: 0.28070175 | D24: 28.785715 | E24: 29.032067 | F24: 13.238545 | G24: 11.81363 | H24: 10.495837 | I24: 0.142225 | J24: 0.73797414 | O24: =111/4 -> 27.75
A25: Oilfield Svcs/Equip. | B25: 231 | C25: 0.31168831 | D25: 38.445908 | E25: 47.680259 | F25: 13.705427 | G25: 13.974806 | H25: 16.024041 | I25: 0.10008261 | J25: 1.6010815
A28: Industry Name | B28: Number of firms | C28: EV/EBITDAR&D | D28: EV/EBITDA | E28: EV/EBIT | F28: EV/EBIT (1-t) | G28: EV/EBITDAR&D | H28: EV/EBITDA | I28: EV/EBIT | J28: EV/EBIT (1-t)
A29: Oil/Gas (Integrated) | B29: 16 | C29: 6.3716102 | D29: 6.4910779 | E29: 8.4487573 | F29: 14.758196 | G29: 6.031739 | H29: 6.1386827 | I29: 8.449675 | J29: 14.759799
A30: Oil/Gas (Production and Exploration) | B30: 107 | C30: 3.870222 | D30: 3.9174712 | E30: 5.7944438 | F30: 7.9471817 | G30: 4.3156102 | H30: 4.3726588 | I30: 5.9732072 | J30: 8.1923588 | K30: =AVERAGE(C29:C32) -> 6.8919083
A31: Oil/Gas Distribution | B31: 114 | C31: 8.2195711 | D31: 8.3354787 | E31: 11.831129 | F31: 13.574772 | G31: 8.6656214 | H31: 8.7929993 | I31: 11.972943 | J31: 13.737486
A32: Oilfield Svcs/Equip. | B32: 231 | C32: 9.1062301 | D32: 9.4204189 | E32: 15.119007 | F32: 20.07069 | G32: 8.1545809 | H32: 8.3954367 | I32: 15.73958 | J32: 20.894508
G33: =AVERAGE(G29:G32) -> 6.7918879 | H33: =AVERAGE(H29:H32) -> 6.9249444
A36: Industry Name | B36: Number of Firms | C36: Beta | D36: Cost of Equity | E36: E/(D+E) | F36: Std Dev in Stock | G36: Cost of Debt | H36: Tax Rate | I36: After-tax Cost of Debt | J36: D/(D+E) | K36: Cost of Capital | L36: Cost of Capital (Local Currency) | M36: D/E
A37: Oil/Gas (Integrated) | B37: 16 | C37: 0.97960023 | D37: 0.11231486 | E37: 0.88244899 | F37: 0.32648391 | G37: 0.0738 | H37: 0.20852008 | I37: 0.05511384 | J37: 0.11755101 | K37: 0.10559082 | L37: 0.16999417 | M37: =J37/E37 -> 0.13320997
A38: Oil/Gas (Production and Exploration) | B38: 107 | C38: 1.0441717 | D38: 0.11669926 | E38: 0.78132353 | F38: 0.3641026 | G38: 0.0738 | H38: 0.17395945 | I38: 0.05511384 | J38: 0.21867647 | K38: 0.10323198 | L38: 0.16749792 | M38: =J38/E38 -> 0.27987954
A39: Oil/Gas Distribution | B39: 114 | C39: 0.64524477 | D39: 0.08961212 | E39: 0.63715883 | F39: 0.27750198 | G39: 0.0693 | H39: 0.1288961 | I39: 0.05175324 | J39: 0.36284117 | K39: 0.07587536 | L39: 0.13854771 | M39: =J39/E39 -> 0.56946739
A40: Oilfield Svcs/Equip. | B40: 231 | C40: 0.87086793 | D40: 0.10493193 | E40: 0.67409405 | F40: 0.37800031 | G40: 0.0738 | H40: 0.14623911 | I40: 0.05511384 | J40: 0.32590595 | K40: 0.08869592 | L40: 0.1521151 | M40: =J40/E40 -> 0.48347252
C41: =AVERAGE(C38:C40) -> 0.85342814
A43: Industry Name | B43: Number of firms | C43: Total Dividends (US $ millions) | D43: Special Dividends as % of Total Dividends | E43: Dividend Payout | F43: Dividend Yield | G43: Market Cap (US $ millions) | H43: ROE | I43: Institutional Holdings | J43: Std Dev in Stock Prices
A44: Oil/Gas (Integrated) | B44: 4 | C44: 4026.8 | D44: 0 | E44: 0.32620777 | F44: 0.038545664 | G44: 104468.3 | H44: 0.17768048 | I44: 0.47545 | J44: 0.38036214
A45: Oil/Gas (Production and Exploration) | B45: 210 | C45: 9512.4579 | D45: 0.080331709 | E45: 0.66305618 | F45: 0.047705954 | G45: 199397.71 | H45: 0.092683546 | I45: 0.13408204 | J45: 0.58775055
A46: Oil/Gas Distribution | B46: 9 | C46: 10358.08 | D46: -0.00011102444 | E46: 0.98813918 | F46: 0.058441073 | G46: 177239.73 | H46: 0.13169869 | I46: 0.3728 | J46: 0.28841974
A47: Oilfield Svcs/Equip. | B47: 30 | C47: 967.76 | D47: 0.010312474 | E47: 0.66419043 | F47: 0.045046873 | G47: 21483.4 | H47: 0.12450906 | I47: 0.30156913 | J47: 0.46485369

Sheet Sheet2
B3: 0.11 | C3: 0.27 | D3: 0.09 | E3: 2.04 | F3: 6.45 | G3: 2.98 | H3: 2.35
C4: =C3/B3-1 -> 1.4545455 | D4: =D3/C3-1 -> -0.66666667 | E4: =E3/D3-1 -> 21.666667 | F4: =F3/E3-1 -> 2.1617647 | G4: =G3/F3-1 -> -0.5379845 | H4: =H3/G3-1 -> -0.2114094

Sheet Ratios
B6: Income Statement Analysis
B7: Years | C7: 2020 | D7: =C7+1 -> 2021 | E7: =D7+1 -> 2022 | F7: =E7+1 -> 2023 | G7: =F7+1 -> 2024
B8: Sales&Revenues | C8: ='Income Statement PBR'!B3 -> 53683000000 | D8: ='Income Statement PBR'!C3 -> 83966000000 | E8: ='Income Statement PBR'!D3 -> 124474000000 | F8: ='Income Statement PBR'!E3 -> 102409000000 | G8: ='Income Statement PBR'!F3 -> 91416000000
B9: Variation | D9: =(D8-C8)/C8 -> 0.56410782 | E9: =(E8-D8)/D8 -> 0.48243337 | F9: =(F8-E8)/E8 -> -0.17726594 | G9: =(G8-F8)/F8 -> -0.10734408
B10: COGS | C10: ='Income Statement PBR'!B6 -> -29195000000 | D10: ='Income Statement PBR'!C6 -> -43164000000 | E10: ='Income Statement PBR'!D6 -> -59486000000 | F10: ='Income Statement PBR'!E6 -> -48435000000 | G10: ='Income Statement PBR'!F6 -> -45444000000
B11: Gross Profit | C11: =C8+C10 -> 24488000000 | D11: =D8+D10 -> 40802000000 | E11: =E8+E10 -> 64988000000 | F11: =F8+F10 -> 53974000000 | G11: =G8+G10 -> 45972000000
B12: Gross Margin (%) | C12: =C11/C8 -> 0.45615931 | D12: =D11/D8 -> 0.48593478 | E12: =E11/E8 -> 0.522101 | F12: =F11/F8 -> 0.52704352 | G12: =G11/G8 -> 0.5028879
B13: EBITDA | C13: =C16-C15 -> 17165000000 | D13: =D16-D15 -> 34023000000 | E13: =E16-E15 -> 56525000000 | F13: =F16-F15 -> 40223000000 | G13: =G16-G15 -> 26507000000
B14: EBITDA margin | C14: =C13/C8 -> 0.31974741 | D14: =D13/D8 -> 0.40519972 | E14: =E13/E8 -> 0.4541109 | F14: =F13/F8 -> 0.39276821 | G14: =G13/G8 -> 0.28996018
B15: Depr&Amort | C15: ='Income Statement PBR'!B24 -> -653000000 | D15: ='Income Statement PBR'!C24 -> -696000000 | E15: ='Income Statement PBR'!D24 -> -894000000 | F15: ='Income Statement PBR'!E24 -> -732000000 | G15: ='Income Statement PBR'!F24 -> -816000000
B16: EBIT | C16: ='Income Statement PBR'!B33 -> 16512000000 | D16: ='Income Statement PBR'!C33 -> 33327000000 | E16: ='Income Statement PBR'!D33 -> 55631000000 | F16: ='Income Statement PBR'!E33 -> 39491000000 | G16: ='Income Statement PBR'!F33 -> 25691000000
B17: EBIT margin | C17: =C16/C8 -> 0.30758341 | D17: =D16/D8 -> 0.39691065 | E17: =E16/E8 -> 0.44692868 | F17: =F16/F8 -> 0.3856204 | G17: =G16/G8 -> 0.28103395
B18: Intrest Charges | C18: ='Income Statement PBR'!B36 -> -5692000000 | D18: ='Income Statement PBR'!C36 -> -4977000000 | E18: ='Income Statement PBR'!D36 -> -2638000000 | F18: ='Income Statement PBR'!E36 -> -3620000000 | G18: ='Income Statement PBR'!F36 -> -3841000000
B19: Taxes | C19: ='Income Statement PBR'!B61 -> 1174000000 | D19: ='Income Statement PBR'!C61 -> -8239000000 | E19: ='Income Statement PBR'!D61 -> -16770000000 | F19: ='Income Statement PBR'!E61 -> -10401000000 | G19: ='Income Statement PBR'!F61 -> -3537000000
B20: Net Income | C20: ='Income Statement PBR'!B66 -> 1141000000 | D20: ='Income Statement PBR'!C66 -> 19875000000 | E20: ='Income Statement PBR'!D66 -> 36623000000 | F20: ='Income Statement PBR'!E66 -> 24884000000 | G20: ='Income Statement PBR'!F66 -> 7528000000
B21: Variation | D21: =(D20-C20)/C20 -> 16.418931 | E21: =(E20-D20)/D20 -> 0.84266667 | F21: =(F20-E20)/E20 -> -0.32053628 | G21: =(G20-F20)/F20 -> -0.69747629
B22: Earnings per share | C22: =C20/C25 -> 0.087471818 | D22: =D20/D25 -> 1.5236655 | E22: =E20/E25 -> 2.8076077 | F22: =F20/F25 -> 1.923009 | G22: =G20/G25 -> 0.58407604
B23: Number of Common share | C23: 7442231382 | D23: 7442231382 | E23: 7442231382 | F23: 7442231382 | G23: 7442231382
B24: Number of Preferred share | C24: 5601969879 | D24: 5601969879 | E24: 5601969879 | F24: 5497905879 | G24: 5446501379
B25: Total number of Shares | C25: =C23+C24 -> 13044201261 | D25: =D23+D24 -> 13044201261 | E25: =E23+E24 -> 13044201261 | F25: =F23+F24 -> 12940137261 | G25: =G23+G24 -> 12888732761
B26: Dividends per share | C26: ='Income Statement PBR'!B88 -> 0.04 | D26: ='Income Statement PBR'!C88 -> 1.05 | E26: ='Income Statement PBR'!D88 -> 3.31 | F26: ='Income Statement PBR'!E88 -> 1.46 | G26: ='Income Statement PBR'!F88 -> 1.21
B27: Div Yield PBR | C27: =C26/C66 -> 0.0035618878 | D27: =D26/D66 -> 0.095628415 | E27: =E26/E66 -> 0.31079812 | F27: =F26/F66 -> 0.091421415 | G27: =G26/G66 -> 0.094090202
B28: Div Yield PBR.A | C28: =C26/C68 -> 0.0003115648 | D28: =D26/D68 -> 0.14570572 | E28: =E26/E68 -> 0.8725992 | F28: =F26/F68 -> 0.1758042 | G28: =G26/G68 -> 0.054955833
B30: Balance Sheet
B31: Total Assets | C31: ='Balance Sheet PBR'!B2 -> 190010000000 | D31: ='Balance Sheet PBR'!C2 -> 174348000000 | E31: ='Balance Sheet PBR'!D2 -> 187191000000 | F31: ='Balance Sheet PBR'!E2 -> 217067000000 | G31: ='Balance Sheet PBR'!F2 -> 181645000000
B32: Cash & cash equivalents | C32: ='Balance Sheet PBR'!B5 -> 11711000000 | D32: ='Balance Sheet PBR'!C5 -> 10467000000 | E32: ='Balance Sheet PBR'!D5 -> 7996000000 | F32: ='Balance Sheet PBR'!E5 -> 12727000000 | G32: ='Balance Sheet PBR'!F5 -> 3271000000
B33: Accounts Receivable | C33: ='Balance Sheet PBR'!B13 -> 7326000000 | D33: ='Balance Sheet PBR'!C13 -> 7714000000 | E33: ='Balance Sheet PBR'!D13 -> 6317000000 | F33: ='Balance Sheet PBR'!E13 -> 7313000000 | G33: ='Balance Sheet PBR'!F13 -> 5532000000
B34: Inventory | C34: ='Balance Sheet PBR'!B10 -> 5677000000 | D34: ='Balance Sheet PBR'!C10 -> 7255000000 | E34: ='Balance Sheet PBR'!D10 -> 8779000000 | F34: ='Balance Sheet PBR'!E10 -> 7681000000 | G34: ='Balance Sheet PBR'!F10 -> 6710000000
B35: Current Assets | C35: ='Balance Sheet PBR'!B3 -> 27388000000 | D35: ='Balance Sheet PBR'!C3 -> 30149000000 | E35: ='Balance Sheet PBR'!D3 -> 31250000000 | F35: ='Balance Sheet PBR'!E3 -> 32445000000 | G35: ='Balance Sheet PBR'!F3 -> 21836000000
B36: Accounts Payable | C36: ='Balance Sheet PBR'!B76 -> 6859000000 | D36: ='Balance Sheet PBR'!C76 -> 5483000000 | E36: ='Balance Sheet PBR'!D76 -> 5464000000 | F36: ='Balance Sheet PBR'!E76 -> 4813000000 | G36: ='Balance Sheet PBR'!F76 -> 6082000000
B37: Current liabilities | C37: ='Balance Sheet PBR'!B73 -> 26225000000 | D37: ='Balance Sheet PBR'!C73 -> 24176000000 | E37: ='Balance Sheet PBR'!D73 -> 31380000000 | F37: ='Balance Sheet PBR'!E73 -> 33860000000 | G37: ='Balance Sheet PBR'!F73 -> 31460000000
B38: Debt | C38: ='Balance Sheet PBR'!B80 -> 9884000000 | D38: ='Balance Sheet PBR'!C80 -> 9073000000 | E38: ='Balance Sheet PBR'!D80 -> 9133000000 | F38: ='Balance Sheet PBR'!E80 -> 11522000000 | G38: ='Balance Sheet PBR'!F80 -> 11108000000
B39: Book Equity | C39: ='Balance Sheet PBR'!B114 -> 59876000000 | D39: ='Balance Sheet PBR'!C114 -> 69812000000 | E39: ='Balance Sheet PBR'!D114 -> 69836000000 | F39: ='Balance Sheet PBR'!E114 -> 78975000000 | G39: ='Balance Sheet PBR'!F114 -> 59350000000
B40: Price/Book | C40: =(C25*C66)/C39 -> 2.4464958 | D40: =(D25*D66)/D39 -> 2.0515861 | E40: =(E25*E66)/E39 -> 1.9892426 | F40: =(F25*F66)/F39 -> 2.6167014 | G40: =(G25*G66)/G39 -> 2.7927397
B41: BV per share | C41: =C39/C25 -> 4.5902389 | D41: =D39/D25 -> 5.3519567 | E41: =E39/E25 -> 5.3537966 | F41: =F39/F25 -> 6.1031037 | G41: =G39/G25 -> 4.6047972
B43: Liquidity Ratios | H43: Average
B44: Current Ratio | C44: =C35/C37 -> 1.044347 | D44: =D35/D37 -> 1.2470632 | E44: =E35/E37 -> 0.99585723 | F44: =F35/F37 -> 0.95821028 | G44: =G35/G37 -> 0.69408773 | H44: =AVERAGE(C44:G44) -> 0.98791309
B45: Quick Ration | C45: =(C35-C34)/C37 -> 0.82787417 | D45: =(D35-D34)/D37 -> 0.9469722 | E45: =(E35-E34)/E37 -> 0.71609305 | F45: =(F35-F34)/F37 -> 0.73136444 | G45: =(G35-G34)/G37 -> 0.48080102 | H45: =AVERAGE(C45:G45) -> 0.74062098
B46: Cash Ratio | C46: =C32/C37 -> 0.44655863 | D46: =D32/D37 -> 0.43295003 | E46: =E32/E37 -> 0.25481198 | F46: =F32/F37 -> 0.37587123 | G46: =G32/G37 -> 0.1039733 | H46: =AVERAGE(C46:G46) -> 0.32283304
B48: Efficiency Ratio | H48: Average
B49: Inventory Turnover | C49: =(-C10)/C34 -> 5.142681 | D49: =(-D10)/D34 -> 5.949552 | E49: =(-E10)/E34 -> 6.7759426 | F49: =(-F10)/F34 -> 6.3058196 | G49: =(-G10)/G34 -> 6.7725782 | H49: =AVERAGE(C49:G49) -> 6.1893147
B50: Receivable Turnover | C50: =C8/C33 -> 7.3277368 | D50: =D8/D33 -> 10.884885 | E50: =E8/E33 -> 19.704607 | F50: =F8/F33 -> 14.003692 | G50: =G8/G33 -> 16.524946 | H50: =AVERAGE(C50:G50) -> 13.689173
B51: Assets Turnover | C51: =C8/C31 -> 0.28252724 | D51: =D8/D31 -> 0.48160002 | E51: =E8/E31 -> 0.66495718 | F51: =F8/F31 -> 0.47178521 | G51: =G8/G31 -> 0.50326736 | H51: =AVERAGE(C51:G51) -> 0.4808274
B52: Cash Turnover | C52: =C8/C32 -> 4.5839809 | D52: =D8/D32 -> 8.0219738 | E52: =E8/E32 -> 15.567034 | F52: =F8/F32 -> 8.0465939 | G52: =G8/G32 -> 27.947417 | H52: =AVERAGE(C52:G52) -> 12.8334
B54: Solvency Ratios | H54: Average
B55: Debt Ratio | C55: =C38/C31 -> 0.052018315 | D55: =D38/D31 -> 0.052039599 | E55: =E38/E31 -> 0.048789739 | F55: =F38/F31 -> 0.053080385 | G55: =G38/G31 -> 0.061152248 | H55: =AVERAGE(C55:G55) -> 0.053416057
B56: Equity Ratio | C56: =C39/C31 -> 0.31512026 | D56: =D39/D31 -> 0.40041756 | E56: =E39/E31 -> 0.37307349 | F56: =F39/F31 -> 0.36382776 | G56: =G39/G31 -> 0.32673622 | H56: =AVERAGE(C56:G56) -> 0.35583506
B57: EBITDA Coverage | C57: =C13/(-C18) -> 3.015636 | D57: =D13/(-D18) -> 6.8360458 | E57: =E13/(-E18) -> 21.427218 | F57: =F13/(-F18) -> 11.111326 | G57: =G13/(-G18) -> 6.9010674 | H57: =AVERAGE(C57:G57) -> 9.8582586
B58: EBIT Coverage | C58: =C16/(-C18) -> 2.9009136 | D58: =D16/(-D18) -> 6.6962025 | E58: =E16/(-E18) -> 21.088324 | F58: =F16/(-F18) -> 10.909116 | G58: =G16/(-G18) -> 6.6886228 | H58: =AVERAGE(C58:G58) -> 9.6566359
B60: Profitability Ratios | H60: Average
B61: Profit Margin | C61: =C20/C8 -> 0.021254401 | D61: =D20/D8 -> 0.23670295 | E61: =E20/E8 -> 0.29422209 | F61: =F20/F8 -> 0.24298646 | G61: =G20/G8 -> 0.082348823 | H61: =AVERAGE(C61:G61) -> 0.17550294
B62: ROE | C62: =C20/C39 -> 0.019056049 | D62: =D20/D39 -> 0.28469318 | E62: =E20/E39 -> 0.52441434 | F62: =F20/F39 -> 0.31508705 | G62: =G20/G39 -> 0.12684078 | H62: =AVERAGE(C62:G62) -> 0.25401828
B63: ROA | C63: =C20/C31 -> 0.0060049471 | D63: =D20/D31 -> 0.11399615 | E63: =E20/E31 -> 0.19564509 | F63: =F20/F31 -> 0.11463742 | G63: =G20/G31 -> 0.041443475 | H63: =AVERAGE(C63:G63) -> 0.094345415
B65: Valuation Ratios | H65: Average
B66: Closing Price per year PBR | C66: 11.23 | D66: 10.98 | E66: 10.65 | F66: 15.97 | G66: 12.86 | H66: =AVERAGE(C66:G66) -> 12.338
B67: Closing Price per year PBR.A | C67: 11.06 | D67: 10.11 | E67: 9.29 | F67: 15.28 | G67: 11.84 | H67: =AVERAGE(C67:G67) -> 11.516
B68: P/E PBR | C68: =C66/C22 -> 128.38421 | D68: =D66/D22 -> 7.2063059 | E68: =E66/E22 -> 3.793265 | F68: =F66/F22 -> 8.3046935 | G68: =G66/G22 -> 22.017681 | H68: =AVERAGE(C68:G68) -> 33.94123
B69: M/B PBR | C69: =C66/C41 -> 2.4464958 | D69: =D66/D41 -> 2.0515861 | E69: =E66/E41 -> 1.9892426 | F69: =F66/F41 -> 2.6167014 | G69: =G66/G41 -> 2.7927397 | H69: =AVERAGE(C69:G69) -> 2.3793531
B78: Resources
B79: Petróleo Brasileiro S.A. - Petrobras. (2020). Annual Report and Form 20-F 2020. https://www.annualreports.com/HostedData/AnnualReportArchive/p/NYSE_PBR_2020.pdf
B80: Petróleo Brasileiro S.A. - Petrobras. (2021). Annual Report and Form 20-F 2021. https://www.annualreports.com/HostedData/AnnualReportArchive/p/NYSE_PBR_2021.pdf
B81: Petróleo Brasileiro S.A. - Petrobras. (2022). Annual Report and Form 20-F 2022. https://www.annualreports.com/HostedData/AnnualReportArchive/p/NYSE_PBR_2022.pdf
B82: Petróleo Brasileiro S.A. - Petrobras. (2023). Annual Report and Form 20-F 2023. https://www.annualreports.com/HostedData/AnnualReportArchive/p/NYSE_PBR_2023.pdf
B83: Petróleo Brasileiro S.A. - Petrobras. (2025). FORM 6-K. In sec.gov. SECURITIES AND EXCHANGE COMMISSION. https://www.sec.gov/Archives/edgar/data/1119639/000129281425002053/pbrfs1q25rs_6k.htm
B84: Petroleo Brasileiro SA Petrobras (PBR). (2025, October 6). Morningstar, Inc. https://www.morningstar.com/stocks/bvmf/PBR/quote

Sheet 3-Statement Analysis
D1: Historical Results | I1: Forecast Period
D2: 2020 | E2: =+D2+1 -> 2021 | F2: =+E2+1 -> 2022 | G2: =+F2+1 -> 2023 | H2: =+G2+1 -> 2024 | I2: =+H2+1 -> 2025 | J2: =+I2+1 -> 2026 | K2: =+J2+1 -> 2027 | L2: =+K2+1 -> 2028 | ... P2: =+O2+1 -> 2032
A3: Balance Sheet Check | D3: =IFERROR(IF(ABS(D60)>1,"ERROR","OK"),"OK") -> OK | E3: =IFERROR(IF(ABS(E60)>1,"ERROR","OK"),"OK") -> OK | F3: =IFERROR(IF(ABS(F60)>1,"ERROR","OK"),"OK") -> OK | G3: =IFERROR(IF(ABS(G60)>1,"ERROR","OK"),"OK") -> OK | H3: =IFERROR(IF(ABS(H60)>1,"ERROR","OK"),"OK") -> OK | I3: =IFERROR(IF(ABS(I60)>1,"ERROR","OK"),"OK") -> OK | J3: =IFERROR(IF(ABS(J60)>1,"ERROR","OK"),"OK") -> OK | K3: =IFERROR(IF(ABS(K60)>1,"ERROR","OK"),"OK") -> OK | ... P3: =IFERROR(IF(ABS(P60)>1,"ERROR","OK"),"OK") -> OK
A4: All-in ($000's)
A5: Assumptions
A7: Key Assumptions
A8: Revenue Growth (% Change) | E8: =E26/D26-1 -> 0.56410782 | F8: =F26/E26-1 -> 0.48243337 | G8: =G26/F26-1 -> -0.17726594 | H8: =H26/G26-1 -> -0.10734408 | I8: 0.1162 | J8: 0.1162 | K8: 0.0618 | L8: 0.0618 | M8: 0.0618 | N8: 0.0618 | O8: 0.0618 | P8: 0.0618
A9: Cost of Goods Sold (% of Revenue) | D9: =D27/D26 -> 0.54384069 | E9: =E27/E26 -> 0.51406522 | F9: =F27/F26 -> 0.477899 | G9: =G27/G26 -> 0.47295648 | H9: =H27/H26 -> 0.4971121 | I9: 0.5011747 | J9: 0.5011747 | K9: 0.5011747 | L9: 0.5011747 | M9: 0.5011747 | N9: 0.5011747 | O9: 0.5011747 | P9: 0.5011747
A10: Salaries and Benefits (% of Revenue) | D10: =D30/D26 -> 0.0085315649 | E10: =E30/E26 -> 0.0299526 | F10: =F30/F26 -> 0.017577968 | G10: =G30/G26 -> 0.032516673 | H10: =H30/H26 -> 0.04876608 | I10: 0.0419 | J10: 0.0419 | K10: 0.0419 | L10: 0.0419 | M10: 0.0419 | N10: 0.0419 | O10: 0.0419 | P10: 0.0419
A11: Rent and Overhead ($000's) | D11: =D31 -> 4415000 | E11: =E31 -> 3798000 | F11: =F31 -> 4349000 | G11: =G31 -> 4731000 | H11: =H31 -> 4575000 | I11: 4741859.2 | J11: 4741859.2 | K11: 4741859.2 | L11: 4741859.2 | M11: 4741859.2 | N11: 4741860.2 | O11: 4741861.2 | P11: 4741862.2
A12: Depreciation & Amortization (% of PP&E) | D12: =D32/D47 -> 0.0052542772 | E12: =E32/E47 -> 0.00554835 | F12: =F32/F47 -> 0.0069586931 | G12: =G32/G47 -> 0.0047807329 | H12: =H32/H47 -> 0.0059800109 | I12: 0.005687497 | J12: 0.005687497 | K12: 0.005687497 | L12: 0.005687497 | M12: 0.005687497 | N12: 0.005687497 | O12: 0.005687497 | P12: 0.005687497
A13: Interest (% of Debt) | D13: =D33/D52 -> 0.075460092 | E13: =E33/E52 -> 0.064016155 | F13: =F33/F52 -> 0.032322133 | G13: =G33/G52 -> 0.036314099 | H13: =H33/H52 -> 0.040299651 | I13: 0.049682426 | J13: 0.049682426 | K13: 0.049682426 | L13: 0.049682426 | M13: 0.049682426 | N13: 0.049682426 | O13: 0.049682426 | P13: 0.049682426
A14: Tax Rate (% of Earnings Before Tax) | D14: =D37/D35 -> -0.088470234 | E14: =E37/E35 -> 0.28591755 | F14: =F37/F35 -> 0.3053588 | G14: =G37/G35 -> 0.25025866 | H14: =H37/H35 -> 0.1095657 | I14: 0.325 | J14: 0.33 | K14: 0.335 | L14: 0.34 | M14: 0.34 | N14: 0.34 | O14: 0.34 | P14: 0.34
A15: Accounts Receivable (Days) | D15: =D45/D26*365 -> 32.166887 | E15: =E45/E26*365 -> 27.681681 | F15: =F45/F26*365 -> 14.69102 | G15: =G45/G26*365 -> 21.865998 | H15: =H45/H26*365 -> 14.238098 | I15: 22 | J15: 22 | K15: 22 | L15: 22 | M15: 22 | N15: 22 | O15: 22 | P15: 22
A16: Inventory (Days) | D16: =D46/D27*365 -> 70.974653 | E16: =E46/E27*365 -> 61.349157 | F16: =F46/F27*365 -> 53.867044 | G16: =G46/G27*365 -> 57.883039 | H16: =H46/H27*365 -> 53.893803 | I16: 36.799453 | J16: 32.968511 | K16: 31.049644 | L16: 29.24246 | M16: 27.540459 | N16: 27.540459 | O16: 27.540459 | P16: 27.540459
A17: Accounts Payable (Days) | D17: =D51/D27*365 -> 85.752184 | E17: =E51/E27*365 -> 46.364911 | F17: =F51/F27*365 -> 33.526544 | G17: =G51/G27*365 -> 36.270156 | H17: =H51/H27*365 -> 48.849793 | I17: 29.255473 | J17: 26.209884 | K17: 24.684389 | L17: 23.247682 | M17: 21.894596 | N17: 21.894596 | O17: 21.894596 | P17: 21.894596
A18: Capital Expenditures ($000's) | D18: =D72 -> -4510000 | E18: =E72 -> 2157000 | F18: =F72 -> -432000 | G18: =G72 -> -7955000 | H18: =H72 -> -13369000 | I18: -4821800 | J18: -4821800 | K18: -4821800 | L18: -4821800 | M18: -4821800 | N18: -4821800 | O18: -4821800 | P18: -4821800
A19: Debt Issuance (Repayment) ($000's) | D19: =D76 -> -8704000 | E19: =E76 -> -19528000 | F19: =F76 -> -6454000 | G19: =G76 -> -1983000 | H19: =H76 -> -4407000 | I19: -8215200 | J19: -8215200 | K19: -8215200 | L19: -8215200 | M19: -8215200 | N19: -8215200 | O19: -8215200 | P19: -8215200
A20: Equity Issued (Repaid) ($000's) | D20: =D77 -> 0 | E20: =E77 -> 0 | F20: =F77 -> 0 | G20: =G77 -> -735000 | H20: =H77 -> -380000 | I20: -223000 | J20: -223000 | K20: -223000 | L20: -223000 | M20: -223000 | N20: -223000 | O20: -223000 | P20: -223000
A21: Days in Period | D21: 365 | E21: 365 | F21: 365 | G21: 365 | H21: 365 | I21: 365 | J21: 365 | K21: 365 | L21: 365 | M21: 365 | N21: 365 | O21: 365 | P21: 365
A24: Income Statement
A26: Revenue | D26: =('Income Statement PBR'!B3)/1000 -> 53683000 | E26: =('Income Statement PBR'!C3)/1000 -> 83966000 | F26: =('Income Statement PBR'!D3)/1000 -> 124474000 | G26: =('Income Statement PBR'!E3)/1000 -> 102409000 | H26: =('Income Statement PBR'!F3)/1000 -> 91416000 | I26: =H26*(1+I8) -> 1.0203854e+08 | J26: =I26*(1+J8) -> 1.1389542e+08 | K26: =J26*(1+K8) -> 1.2093415e+08 | L26: =K26*(1+L8) -> 1.2840788e+08 | M26: =L26*(1+M8) -> 1.3634349e+08 | N26: =M26*(1+N8) -> 1.4476952e+08 | O26: =N26*(1+O8) -> 1.5371628e+08 | P26: =O26*(1+P8) -> 1.6321594e+08
A27: Cost of Goods Sold (COGS) | D27: =(('Income Statement PBR'!B6)*-1)/1000 -> 29195000 | E27: =(('Income Statement PBR'!C6)*-1)/1000 -> 43164000 | F27: =(('Income Statement PBR'!D6)*-1)/1000 -> 59486000 | G27: =(('Income Statement PBR'!E6)*-1)/1000 -> 48435000 | H27: =(('Income Statement PBR'!F6)*-1)/1000 -> 45444000 | I27: =I26*I9 -> 51139134 | J27: =J26*J9 -> 57081501 | K27: =K26*K9 -> 60609138 | L27: =L26*L9 -> 64354783 | M27: =M26*M9 -> 68331909 | N27: =N26*N9 -> 72554821 | O27: =O26*O9 -> 77038708 | P27: =P26*P9 -> 81799701
A28: Gross Profit | D28: =D26-D27 -> 24488000 | E28: =E26-E27 -> 40802000 | F28: =F26-F27 -> 64988000 | G28: =G26-G27 -> 53974000 | H28: =H26-H27 -> 45972000 | I28: =I26-I27 -> 50899405 | J28: =J26-J27 -> 56813916 | K28: =K26-K27 -> 60325016 | ... P28: =P26-P27 -> 81416242
A29: Expenses
A30: Salaries and Benefits | D30: =(('Income Statement PBR'!B13)*-1)/1000 -> 458000 | E30: =(('Income Statement PBR'!C13)*-1)/1000 -> 2515000 | F30: =(('Income Statement PBR'!D13)*-1)/1000 -> 2188000 | G30: =(('Income Statement PBR'!E13)*-1)/1000 -> 3330000 | H30: =(('Income Statement PBR'!F13)*-1)/1000 -> 4458000 | I30: =I10*I26 -> 4275414.8 | J30: =J10*J26 -> 4772218 | K30: =K10*K26 -> 5067141.1 | L30: =L10*L26 -> 5380290.4 | M30: =M10*M26 -> 5712792.3 | N30: =N10*N26 -> 6065842.9 | O30: =O10*O26 -> 6440712 | P30: =P10*P26 -> 6838748
A31: Rent and Overhead | D31: =(('Income Statement PBR'!B16)*-1)/1000 -> 4415000 | E31: =(('Income Statement PBR'!C16)*-1)/1000 -> 3798000 | F31: =(('Income Statement PBR'!D16)*-1)/1000 -> 4349000 | G31: =(('Income Statement PBR'!E16)*-1)/1000 -> 4731000 | H31: =(('Income Statement PBR'!F16)*-1)/1000 -> 4575000 | I31: =I11 -> 4741859.2 | J31: =J11 -> 4741859.2 | K31: =K11 -> 4741859.2 | L31: =L11 -> 4741859.2 | M31: =M11 -> 4741859.2 | N31: =N11 -> 4741860.2 | O31: =O11 -> 4741861.2 | P31: =P11 -> 4741862.2
A32: Depreciation & Amortization | D32: 653000 | E32: 696000 | F32: 894000 | G32: 732000 | H32: 816000 | I32: =I67 -> 822398.99 | J32: =J67 -> 845145.57 | K32: =K67 -> 867762.78 | L32: =L67 -> 890251.36 | M32: =M67 -> 912612.03 | N32: =N67 -> 934845.52 | O32: =O67 -> 956952.56 | P32: =P67 -> 978933.87
A33: Interest | D33: =(('Income Statement PBR'!B36)*-1)/1000 -> 5692000 | E33: =(('Income Statement PBR'!C36)*-1)/1000 -> 4977000 | F33: =(('Income Statement PBR'!D36)*-1)/1000 -> 2638000 | G33: =(('Income Statement PBR'!E36)*-1)/1000 -> 3620000 | H33: =(('Income Statement PBR'!F36)*-1)/1000 -> 3841000 | I33: =I105 -> 2050214.9 | J33: =J105 -> 1642063.8 | K33: =K105 -> 1233912.7 | L33: =L105 -> 825761.67 | M33: =M105 -> 417610.6 | N33: =N105 -> 9459.5339 | O33: =O105 -> -398691.53 | P33: =P105 -> -806842.6
A34: Total Expenses | D34: =SUM(D30:D33) -> 11218000 | E34: =SUM(E30:E33) -> 11986000 | F34: =SUM(F30:F33) -> 10069000 | G34: =SUM(G30:G33) -> 12413000 | H34: =SUM(H30:H33) -> 13690000 | I34: =SUM(I30:I33) -> 11889888 | J34: =SUM(J30:J33) -> 12001287 | K34: =SUM(K30:K33) -> 11910676 | ... P34: =SUM(P30:P33) -> 11752701
A35: Earnings Before Tax | D35: =D28-D34 -> 13270000 | E35: =E28-E34 -> 28816000 | F35: =F28-F34 -> 54919000 | G35: =G28-G34 -> 41561000 | H35: =H28-H34 -> 32282000 | I35: =I28-I34 -> 39009517 | J35: =J28-J34 -> 44812629 | K35: =K28-K34 -> 48414340 | ... P35: =P28-P34 -> 69663540
A37: Taxes | D37: -1174000 | E37: 8239000 | F37: 16770000 | G37: 10401000 | H37: 3537000 | I37: =I35*I14 -> 12678093 | J37: =J35*J14 -> 14788168 | K37: =K35*K14 -> 16218804 | L37: =L35*L14 -> 17753079 | M37: =M35*M14 -> 19117081 | N37: =N35*N14 -> 20557315 | O37: =O35*O14 -> 22078489 | P37: =P35*P14 -> 23685604
A38: Net Earnings | D38: =D35-D37 -> 14444000 | E38: =E35-E37 -> 20577000 | F38: =F35-F37 -> 38149000 | G38: =G35-G37 -> 31160000 | H38: =H35-H37 -> 28745000 | I38: =I35-I37 -> 26331424 | J38: =J35-J37 -> 30024462 | K38: =K35-K37 -> 32195536 | ... P38: =P35-P37 -> 45977937
A41: Balance Sheet
A43: Assets
A44: Cash | D44: 11711000 | E44: 10467000 | F44: 7996000 | G44: 12727000 | H44: 3271000 | I44: =I82 -> 14151589 | J44: =J82 -> 31046535 | K44: =K82 -> 50425582 | L44: =L82 -> 72067221 | M44: =M82 -> 96351151 | N44: =N82 -> 1.2335818e+08 | O44: =O82 -> 1.5330477e+08 | P44: =P82 -> 1.8635541e+08
A45: Accounts Receivable | D45: 4731000 | E45: 6368000 | F45: 5010000 | G45: 6135000 | H45: 3566000 | I45: =I26*I15/I21 -> 6150268.1 | J45: =J26*J15/J21 -> 6864929.3 | K45: =K26*K15/K21 -> 7289181.9 | L45: =L26*L15/L21 -> 7739653.3 | M45: =M26*M15/M21 -> 8217963.9 | N45: =N26*N15/N21 -> 8725834.1 | O45: =O26*O15/O21 -> 9265090.6 | P45: =P26*P15/P21 -> 9837673.2
A46: Inventory | D46: 5677000 | E46: 7255000 | F46: 8779000 | G46: 7681000 | H46: 6710000 | I46: =I27*I16/I21 -> 5155868.9 | J46: =J27*J16/J21 -> 5155868.9 | K46: =K27*K16/K21 -> 5155868.9 | L46: =L27*L16/L21 -> 5155868.9 | M46: =M27*M16/M21 -> 5155868.9 | N46: =N27*N16/N21 -> 5474501.6 | O46: =O27*O16/O21 -> 5812825.8 | P46: =P27*P16/P21 -> 6172058.4
A47: Property & Equipment | D47: 124279700 | E47: 125442700 | F47: 128472400 | G47: 153114600 | H47: 136454600 | I47: =I99 -> 1.485971e+08 | J47: =J99 -> 1.5257376e+08 | K47: =K99 -> 1.5652779e+08 | L47: =L99 -> 1.6045934e+08 | M47: =M99 -> 1.6436853e+08 | N47: =N99 -> 1.6825548e+08 | O47: =O99 -> 1.7212033e+08 | P47: =P99 -> 1.759632e+08
A48: Total Assets | D48: =SUM(D44:D47) -> 146398700 | E48: =SUM(E44:E47) -> 149532700 | F48: =SUM(F44:F47) -> 150257400 | G48: =SUM(G44:G47) -> 179657600 | H48: =SUM(H44:H47) -> 150001600 | I48: =SUM(I44:I47) -> 1.7405483e+08 | J48: =SUM(J44:J47) -> 1.9564109e+08 | K48: =SUM(K44:K47) -> 2.1939842e+08 | ... P48: =SUM(P44:P47) -> 3.7832834e+08
A50: Liabilities
A51: Accounts Payable | D51: 6859000 | E51: 5483000 | F51: 5464000 | G51: 4813000 | H51: 6082000 | I51: =I27*I17/I21 -> 4098902.9 | J51: =J27*J17/J21 -> 4098902.9 | K51: =K27*K17/K21 -> 4098902.9 | L51: =L27*L17/L21 -> 4098902.9 | M51: =M27*M17/M21 -> 4098902.9 | N51: =N27*N17/N21 -> 4352215.1 | O51: =O27*O17/O21 -> 4621182 | P51: =P27*P17/P21 -> 4906771
A52: Debt | D52: 75430600 | E52: 77746000 | F52: 81615900 | G52: 99685800 | H52: 95311000 | I52: 95238900 | J52: 87023700 | K52: 78808500 | L52: 70593300 | M52: 62378100 | N52: 54162900 | O52: 45947700 | P52: 37732500
A53: Total Liabilities | D53: =SUM(D51:D52) -> 82289600 | E53: =SUM(E51:E52) -> 83229000 | F53: =SUM(F51:F52) -> 87079900 | G53: =SUM(G51:G52) -> 104498800 | H53: =SUM(H51:H52) -> 101393000 | I53: =SUM(I51:I52) -> 99337803 | J53: =SUM(J51:J52) -> 91122603 | K53: =SUM(K51:K52) -> 82907403 | ... P53: =SUM(P51:P52) -> 42639271
A54: Shareholder's Equity
A55: Equity Capital | D55: 39556400 | E55: 36845500 | F55: 38859000 | G55: 42347500 | H55: 33216700 | I55: =H55+I77 -> 32993700 | J55: =I55+J77 -> 32770700 | K55: =J55+K77 -> 32547700 | L55: =K55+L77 -> 32324700 | M55: =L55+M77 -> 32101700 | N55: =M55+N77 -> 31878700 | O55: =N55+O77 -> 31655700 | P55: =O55+P77 -> 31432700
A56: Retained Earnings | D56: 24552700 | E56: 29458200 | F56: 24318500 | G56: 32811300 | H56: 15391900 | I56: =H56+I38 -> 41723324 | J56: =I56+J38 -> 71747786 | K56: =J56+K38 -> 1.0394332e+08 | L56: =K56+L38 -> 1.3840518e+08 | M56: =L56+M38 -> 1.7551481e+08 | N56: =M56+N38 -> 2.1542019e+08 | O56: =N56+O38 -> 2.5827843e+08 | P56: =O56+P38 -> 3.0425637e+08
A57: Shareholder's Equity | D57: =SUM(D55:D56) -> 64109100 | E57: =SUM(E55:E56) -> 66303700 | F57: =SUM(F55:F56) -> 63177500 | G57: =SUM(G55:G56) -> 75158800 | H57: =SUM(H55:H56) -> 48608600 | I57: =SUM(I55:I56) -> 74717024 | J57: =SUM(J55:J56) -> 1.0451849e+08 | K57: =SUM(K55:K56) -> 1.3649102e+08 | ... P57: =SUM(P55:P56) -> 3.3568907e+08
A58: Total Liabilities & Shareholder's Equity | D58: =D53+D57 -> 146398700 | E58: =E53+E57 -> 149532700 | F58: =F53+F57 -> 150257400 | G58: =G53+G57 -> 179657600 | H58: =H53+H57 -> 150001600 | I58: =I53+I57 -> 1.7405483e+08 | J58: =J53+J57 -> 1.9564109e+08 | K58: =K53+K57 -> 2.1939842e+08 | ... P58: =P53+P57 -> 3.7832834e+08
D59: 1000 | R59: Mismatch sum
A60: Check | D60: =D58-D48 -> 0 | E60: =E58-E48 -> 0 | F60: =F58-F48 -> 0 | G60: =G58-G48 -> 0 | H60: =H58-H48 -> 0 | I60: =I58-I48 -> 0 | J60: =J58-J48 -> 0 | K60: =K58-K48 -> 0 | ... P60: =P58-P48 -> 0 | R60: =SUM(D60:P60) -> 0
A63: Cash Flow Statement
A65: Operating Cash Flow
A66: Net Earnings | D66: 14479000 | E66: 15988000 | F66: 12681000 | G66: 18437000 | H66: 11557000 | I66: =I38 -> 26331424 | J66: =J38 -> 30024462 | K66: =K38 -> 32195536 | L66: =L38 -> 34461860 | M66: =M38 -> 37109628 | N66: =N38 -> 39905376 | O66: =O38 -> 42858244 | P66: =P38 -> 45977937
A67: Plus: Depreciation & Amortization | D67: 653000 | E67: 696000 | F67: 894000 | G67: 732000 | H67: 816000 | I67: =I98 -> 822398.99 | J67: =J98 -> 845145.57 | K67: =K98 -> 867762.78 | L67: =L98 -> 890251.36 | M67: =M98 -> 912612.03 | N67: =N98 -> 934845.52 | O67: =O98 -> 956952.56 | P67: =P98 -> 978933.87
A68: Less: Changes in Working Capital | D68: 2430000 | E68: -558000 | F68: -9173000 | G68: -3765000 | H68: -3673000 | I68: =I93 -> 3013234.1 | J68: =J93 -> 714661.16 | K68: =K93 -> 424252.63 | L68: =L93 -> 450471.44 | M68: =M93 -> 478310.58 | N68: =N93 -> 573190.67 | O68: =O93 -> 608613.85 | P68: =P93 -> 646226.19
A69: Cash from Operations | D69: =D66+D67+D68 -> 17562000 | E69: =E66+E67+E68 -> 16126000 | F69: =F66+F67+F68 -> 4402000 | G69: =G66+G67+G68 -> 15404000 | H69: =H66+H67+H68 -> 8700000 | I69: =I66+I67-I68 -> 24140589 | J69: =J66+J67-J68 -> 30154946 | K69: =K66+K67-K68 -> 32639046 | L69: =L66+L67-L68 -> 34901640 | M69: =M66+M67-M68 -> 37543930 | N69: =N66+N67-N68 -> 40267031 | O69: =O66+O67-O68 -> 43206583 | P69: =P66+P67-P68 -> 46310644
A71: Investing Cash Flow
A72: Investments in Property & Equipment | D72: -4510000 | E72: 2157000 | F72: -432000 | G72: -7955000 | H72: -13369000 | I72: =I97 -> -4821800 | J72: =J97 -> -4821800 | K72: =K97 -> -4821800 | L72: =L97 -> -4821800 | M72: =M97 -> -4821800 | N72: =N97 -> -4821800 | O72: =O97 -> -4821800 | P72: =P97 -> -4821800
A73: Cash from Investing | D73: =SUM(D72) -> -4510000 | E73: =SUM(E72) -> 2157000 | F73: =SUM(F72) -> -432000 | G73: =SUM(G72) -> -7955000 | H73: =SUM(H72) -> -13369000 | I73: =SUM(I72) -> -4821800 | J73: =SUM(J72) -> -4821800 | K73: =SUM(K72) -> -4821800 | ... P73: =SUM(P72) -> -4821800
A75: Financing Cash Flow
A76: Issuance (repayment) of debt | D76: -8704000 | E76: -19528000 | F76: -6454000 | G76: -1983000 | H76: -4407000 | I76: =I103 -> -8215200 | J76: =J103 -> -8215200 | K76: =K103 -> -8215200 | L76: =L103 -> -8215200 | M76: =M103 -> -8215200 | N76: =N103 -> -8215200 | O76: =O103 -> -8215200 | P76: =P103 -> -8215200
A77: Issuance (repayment) of equity | G77: -735000 | H77: -380000 | I77: =I20 -> -223000 | J77: =J20 -> -223000 | K77: =K20 -> -223000 | L77: =L20 -> -223000 | M77: =M20 -> -223000 | N77: =N20 -> -223000 | O77: =O20 -> -223000 | P77: =P20 -> -223000
A78: Cash from Financing | D78: =SUM(D76:D77) -> -8704000 | E78: =SUM(E76:E77) -> -19528000 | F78: =SUM(F76:F77) -> -6454000 | G78: =SUM(G76:G77) -> -2718000 | H78: =SUM(H76:H77) -> -4787000 | I78: =SUM(I76:I77) -> -8438200 | J78: =SUM(J76:J77) -> -8438200 | K78: =SUM(K76:K77) -> -8438200 | ... P78: =SUM(P76:P77) -> -8438200
A80: Net Increase (decrease) in Cash | D80: =D69+D73+D78 -> 4348000 | E80: =E69+E73+E78 -> -1245000 | F80: =F69+F73+F78 -> -2484000 | G80: =G69+G73+G78 -> 4731000 | H80: =H69+H73+H78 -> -9456000 | I80: =I69+I73+I78 -> 10880589 | J80: =J69+J73+J78 -> 16894946 | K80: =K69+K73+K78 -> 19379046 | ... P80: =P69+P73+P78 -> 33050644
A81: Opening Cash Balance | D81: 7377000 | E81: =D82 -> 11725000 | F81: =E82 -> 10480000 | G81: =F82 -> 7996000 | H81: =G82 -> 12727000 | I81: =H82 -> 3271000 | J81: =I82 -> 14151589 | K81: =J82 -> 31046535 | L81: =K82 -> 50425582 | ... P81: =O82 -> 1.5330477e+08
A82: Closing Cash Balance | D82: =SUM(D80:D81) -> 11725000 | E82: =SUM(E80:E81) -> 10480000 | F82: =SUM(F80:F81) -> 7996000 | G82: =SUM(G80:G81) -> 12727000 | H82: =SUM(H80:H81) -> 3271000 | I82: =SUM(I80:I81) -> 14151589 | J82: =SUM(J80:J81) -> 31046535 | K82: =SUM(K80:K81) -> 50425582 | ... P82: =SUM(P80:P81) -> 1.8635541e+08
A86: Supporting Schedules
A88: Working Capital Schedule
A89: Accounts Receivable | D89: =D45 -> 4731000 | E89: =E45 -> 6368000 | F89: =F45 -> 5010000 | G89: =G45 -> 6135000 | H89: =H45 -> 3566000 | I89: =I45 -> 6150268.1 | J89: =J45 -> 6864929.3 | K89: =K45 -> 7289181.9 | ... P89: =P45 -> 9837673.2
A90: Inventory | D90: =D46 -> 5677000 | E90: =E46 -> 7255000 | F90: =F46 -> 8779000 | G90: =G46 -> 7681000 | H90: =H46 -> 6710000 | I90: =I46 -> 5155868.9 | J90: =J46 -> 5155868.9 | K90: =K46 -> 5155868.9 | ... P90: =P46 -> 6172058.4
A91: Accounts Payable | D91: =D51 -> 6859000 | E91: =E51 -> 5483000 | F91: =F51 -> 5464000 | G91: =G51 -> 4813000 | H91: =H51 -> 6082000 | I91: =I51 -> 4098902.9 | J91: =J51 -> 4098902.9 | K91: =K51 -> 4098902.9 | ... P91: =P51 -> 4906771
A92: Net Working Capital (NWC) | D92: =D89+D90-D91 -> 3549000 | E92: =E89+E90-E91 -> 8140000 | F92: =F89+F90-F91 -> 8325000 | G92: =G89+G90-G91 -> 9003000 | H92: =H89+H90-H91 -> 4194000 | I92: =I89+I90-I91 -> 7207234.1 | J92: =J89+J90-J91 -> 7921895.2 | K92: =K89+K90-K91 -> 8346147.9 | ... P92: =P89+P90-P91 -> 11102961
A93: Change in NWC | D93: =D92-C92 -> 3549000 | E93: =E92-D92 -> 4591000 | F93: =F92-E92 -> 185000 | G93: =G92-F92 -> 678000 | H93: =H92-G92 -> -4809000 | I93: =I92-H92 -> 3013234.1 | J93: =J92-I92 -> 714661.16 | K93: =K92-J92 -> 424252.63 | ... P93: =P92-O92 -> 646226.19
A95: Depreciation Schedule
A96: PPE Opening | D96: =D47 -> 124279700 | E96: =D99 -> 128136700 | F96: =E99 -> 125283700 | G96: =F99 -> 124821700 | H96: =G99 -> 132044700 | I96: =H99 -> 144597700 | J96: =I99 -> 1.485971e+08 | K96: =J99 -> 1.5257376e+08 | L96: =K99 -> 1.5652779e+08 | ... P96: =O99 -> 1.7212033e+08
A97: Plus Capex | D97: =D72 -> -4510000 | E97: =E72 -> 2157000 | F97: =F72 -> -432000 | G97: =G72 -> -7955000 | H97: =H72 -> -13369000 | I97: =I18 -> -4821800 | J97: =J18 -> -4821800 | K97: =K18 -> -4821800 | L97: =L18 -> -4821800 | M97: =M18 -> -4821800 | N97: =N18 -> -4821800 | O97: =O18 -> -4821800 | P97: =P18 -> -4821800
A98: Less Depreciation | D98: =D67 -> 653000 | E98: =E67 -> 696000 | F98: =F67 -> 894000 | G98: =G67 -> 732000 | H98: =H67 -> 816000 | I98: =I96*I12 -> 822398.99 | J98: =J96*J12 -> 845145.57 | K98: =K96*K12 -> 867762.78 | L98: =L96*L12 -> 890251.36 | M98: =M96*M12 -> 912612.03 | N98: =N96*N12 -> 934845.52 | O98: =O96*O12 -> 956952.56 | P98: =P96*P12 -> 978933.87
A99: PPE Closing | D99: =D96-D97-D98 -> 128136700 | E99: =E96-E97-E98 -> 125283700 | F99: =F96-F97-F98 -> 124821700 | G99: =G96-G97-G98 -> 132044700 | H99: =H96-H97-H98 -> 144597700 | I99: =I96-I97-I98 -> 1.485971e+08 | J99: =J96-J97-J98 -> 1.5257376e+08 | K99: =K96-K97-K98 -> 1.5652779e+08 | ... P99: =P96-P97-P98 -> 1.759632e+08
A101: Debt & Interest Schedule
A102: Debt Opening | D102: 86450000 | E102: =D104 -> 77746000 | F102: =E104 -> 58218000 | G102: =F104 -> 51764000 | H102: =G104 -> 49781000 | I102: =H104 -> 45374000 | J102: =I104 -> 37158800 | K102: =J104 -> 28943600 | L102: =K104 -> 20728400 | ... P102: =O104 -> -12132400
A103: Issuance (repayment) | D103: =D76 -> -8704000 | E103: =E76 -> -19528000 | F103: =F76 -> -6454000 | G103: =G76 -> -1983000 | H103: =H76 -> -4407000 | I103: =I19 -> -8215200 | J103: =J19 -> -8215200 | K103: =K19 -> -8215200 | L103: =L19 -> -8215200 | M103: =M19 -> -8215200 | N103: =N19 -> -8215200 | O103: =O19 -> -8215200 | P103: =P19 -> -8215200
A104: Debt Closing | D104: =D102+D103 -> 77746000 | E104: =E102+E103 -> 58218000 | F104: =F102+F103 -> 51764000 | G104: =G102+G103 -> 49781000 | H104: =H102+H103 -> 45374000 | I104: =I102+I103 -> 37158800 | J104: =J102+J103 -> 28943600 | K104: =K102+K103 -> 20728400 | ... P104: =P102+P103 -> -20347600
A105: Interest Expense | D105: =D33 -> 5692000 | E105: =E33 -> 4977000 | F105: =F33 -> 2638000 | G105: =G33 -> 3620000 | H105: =H33 -> 3841000 | I105: =AVERAGE(I102,I104)*I13 -> 2050214.9 | J105: =AVERAGE(J102,J104)*J13 -> 1642063.8 | K105: =AVERAGE(K102,K104)*K13 -> 1233912.7 | L105: =AVERAGE(L102,L104)*L13 -> 825761.67 | M105: =AVERAGE(M102,M104)*M13 -> 417610.6 | N105: =AVERAGE(N102,N104)*N13 -> 9459.5339 | O105: =AVERAGE(O102,O104)*O13 -> -398691.53 | P105: =AVERAGE(P102,P104)*P13 -> -806842.6
A109: Charts and Graphs
A111: Revenue | D111: =D26 -> 53683000 | E111: =E26 -> 83966000 | F111: =F26 -> 124474000 | G111: =G26 -> 102409000 | H111: =H26 -> 91416000 | I111: =I26 -> 1.0203854e+08 | J111: =J26 -> 1.1389542e+08 | K111: =K26 -> 1.2093415e+08 | ... P111: =P26 -> 1.6321594e+08
A112: Gross Profit Margin (%) | D112: =D28/D26 -> 0.45615931 | E112: =E28/E26 -> 0.48593478 | F112: =F28/F26 -> 0.522101 | G112: =G28/G26 -> 0.52704352 | H112: =H28/H26 -> 0.5028879 | I112: =I28/I26 -> 0.4988253 | J112: =J28/J26 -> 0.4988253 | K112: =K28/K26 -> 0.4988253 | ... P112: =P28/P26 -> 0.4988253
A114: Operating Cash Flow | D114: =D69 -> 17562000 | E114: =E69 -> 16126000 | F114: =F69 -> 4402000 | G114: =G69 -> 15404000 | H114: =H69 -> 8700000 | I114: =I69 -> 24140589 | J114: =J69 -> 30154946 | K114: =K69 -> 32639046 | ... P114: =P69 -> 46310644
A115: Investing Cash Flow | D115: =-D73 -> 4510000 | E115: =-E73 -> -2157000 | F115: =-F73 -> 432000 | G115: =-G73 -> 7955000 | H115: =-H73 -> 13369000 | I115: =-I73 -> 4821800 | J115: =-J73 -> 4821800 | K115: =-K73 -> 4821800 | ... P115: =-P73 -> 4821800
A116: Financing Cash Flow | D116: =D78 -> -8704000 | E116: =E78 -> -19528000 | F116: =F78 -> -6454000 | G116: =G78 -> -2718000 | H116: =H78 -> -4787000 | I116: =I78 -> -8438200 | J116: =J78 -> -8438200 | K116: =K78 -> -8438200 | ... P116: =P78 -> -8438200

Sheet Income Statement PBR
A1: PBR_income-statement_Annual_As_Originally_Reported | B1: 2020 | C1: 2021 | D1: 2022 | E1: 2023 | F1: 2024
A2: Gross Profit | B2: 24488000000 | C2: 40802000000 | D2: 64988000000 | E2: 53974000000 | F2: 45972000000
A3: Total Revenue | B3: 53683000000 | C3: 83966000000 | D3: 124474000000 | E3: 102409000000 | F3: 91416000000
A4: Business Revenue | B4: 53683000000 | C4: 83966000000 | D4: 124474000000 | E4: 102409000000 | F4: 91416000000
A5: Excise Taxes
A6: Cost of Revenue | B6: -29195000000 | C6: -43164000000 | D6: -59486000000 | E6: -48435000000 | F6: -45444000000
A7: Cost of Goods and Services | B7: -12699000000 | C7: -20869000000 | D7: -32354000000 | E7: -23858000000 | F7: -22387000000
A8: Taxes, Cost of Revenue | B8: -5920000000 | C8: -11136000000 | D8: -14953000000 | E8: -12108000000 | F8: -11392000000
A9: Staff Cost, Cost of Revenue | B9: -1729000000 | C9: -1882000000 | D9: -1665000000 | E9: -1690000000 | F9: -1888000000
A10: Dpreciation & Amortization, Cost of Revenue | B10: -8847000000 | C10: -9277000000 | D10: -10514000000 | E10: -10779000000 | F10: -9777000000
A11: Operating Income/Expenses | B11: -7976000000 | C11: -7475000000 | D11: -9357000000 | E11: -14483000000 | F11: -20281000000
A12: Selling, General and Administrative Expenses | B12: -4873000000 | C12: -6313000000 | D12: -6537000000 | E12: -8061000000 | F12: -9033000000
A13: Staff Costs | B13: -458000000 | C13: -2515000000 | D13: -2188000000 | E13: -3330000000 | F13: -4458000000
A14: Pension and Other Employee Benefits Costs | B14: 889000000 | C14: -1467000000 | D14: -1095000000 | E14: -1172000000 | F14: -2196000000
A15: Other Staff Costs | B15: -1347000000 | C15: -1048000000 | D15: -1093000000 | E15: -2158000000 | F15: -2262000000
A16: Rent Expense | B16: -4415000000 | C16: -3798000000 | D16: -4349000000 | E16: -4731000000 | F16: -4575000000
A17: General and Administrative Expenses
A18: Legal, Accounting, Auditing and Consulting Fee
A19: Legal Fees
A20: Selling and Marketing Expenses
A21: Operation and Maintenance Expenses | E21: -2205000000 | F21: -2617000000
A22: Exploration Expenses | B22: -803000000 | C22: -687000000 | D22: -887000000 | E22: -982000000 | F22: -913000000
A23: Research and Development Expenses | B23: -355000000 | C23: -563000000 | D23: -792000000 | E23: -726000000 | F23: -789000000
A24: Depreciation, Amortization and Depletion | B24: -653000000 | C24: -696000000 | D24: -894000000 | E24: -732000000 | F24: -816000000
A25: Accretion of Asset Retirement Obligation | B25: -342000000 | C25: 99000000 | D25: -225000000 | E25: -1195000000 | F25: -2584000000
A26: Taxes Other Than Income Taxes | B26: -952000000 | C26: 673000000 | D26: -285000000 | E26: -686000000 | F26: -3211000000
A27: Provisions | B27: 2000000 | C27: 12000000 | D27: -58000000 | E27: -22000000 | F27: -258000000
A28: Provision for Doubtful Accounts | B28: 2000000 | C28: 12000000 | D28: -58000000 | E28: -22000000 | F28: -258000000
A29: Other Provisions
A30: Other Income/Expense, Operating | D30: 321000000 | E30: 126000000 | F30: -60000000
A31: Income from Grants Received, Operating | D31: 471000000 | E31: 315000000 | F31: 161000000
A32: Other Expenses, Operating | D32: -150000000 | E32: -189000000 | F32: -221000000
A33: Total Operating Profit/Loss | B33: 16512000000 | C33: 33327000000 | D33: 55631000000 | E33: 39491000000 | F33: 25691000000
A34: Non-Operating Income/Expense, Total | B34: -16738000000 | C34: -5102000000 | D34: -2106000000 | E34: -4095000000 | F34: -14549000000
A35: Total Net Finance Income/Expense | B35: -5655000000 | C35: -4644000000 | D35: -2827000000 | E35: -3410000000 | F35: -3725000000
A36: Net Interest Income/Expense | B36: -5692000000 | C36: -4977000000 | D36: -2638000000 | E36: -3620000000 | F36: -3841000000
A37: Interest Expense Net of Capitalized Interest | B37: -5771000000 | C37: -4977000000 | D37: -3311000000 | E37: -3620000000 | F37: -3841000000
A38: Gross Interest | B38: -6712000000 | C38: -5953000000 | D38: -4343000000 | E38: -4910000000 | F38: -5411000000
A39: Interest Capitalized | B39: 941000000 | C39: 976000000 | D39: 1032000000 | E39: 1290000000 | F39: 1570000000
A40: Interest Income | B40: 79000000 | D40: 673000000
A41: Other Finance Income/Expenses | B41: 37000000 | C41: 333000000 | D41: -189000000 | E41: 210000000 | F41: 116000000
A42: Other Finance Income | B42: 270000000 | C42: 506000000 | E42: 512000000 | F42: 447000000
A43: Other Finance Expenses | B43: -233000000 | C43: -173000000 | D43: -189000000 | E43: -302000000 | F43: -331000000
A44: Net Investment Income | B44: -4942000000 | C44: -5312000000 | D44: -1104000000 | E44: 344000000 | F44: -10007000000
A45: Income from Associates, JointVentures and Other Participating Interests | B45: -659000000 | C45: 1607000000 | D45: 251000000 | E45: -304000000 | F45: -627000000
A46: Gain/Loss on Foreign Currency Exchange | B46: -4177000000 | C46: -2570000000 | D46: 1619000000 | E46: 2743000000 | F46: -7937000000
A47: Gain/Loss on Derivatives | B47: -308000000 | C47: -4664000000 | D47: -5127000000 | E47: -3752000000 | F47: -2950000000
A48: Other Investment Income | B48: 202000000 | C48: 315000000 | D48: 1159000000 | E48: 1657000000 | F48: 1507000000
A49: Dividend and Investment Income | D49: 994000000
A50: Fair Value or Unrealized Gain/Loss on Financial Assets
A51: Irregular Income/Expense | B51: -9558000000 | C51: 3544000000 | D51: -2738000000 | E51: -1862000000 | F51: -1969000000
A52: Fixed Asset Disposals | B52: 499000000 | C52: 1941000000 | D52: 1144000000 | E52: 1295000000 | F52: 228000000
A53: Write Off/Write Down of Other Assets | D53: -151000000 | E53: -2680000000 | F53: -1531000000
A54: Litigation Income/Expense | B54: -493000000 | C54: -740000000 | D54: -1362000000 | E54: -561000000 | F54: -996000000
A55: Other Irregular Income/Expense | B55: -1165000000 | C55: -817000000 | D55: -1205000000 | E55: 84000000 | F55: 330000000
A56: Impairment/Write Off/Write Down of Capital Assets | B56: -7339000000 | C56: 3190000000 | D56: -1164000000
A57: Disposal of Businesses | B57: -43000000 | C57: -41000000
A58: Restructuring and Reorganization Income/Expense | B58: -1017000000 | C58: 11000000
A59: Other Income/Expense, Non-Operating | B59: 3417000000 | C59: 1310000000 | D59: 4563000000 | E59: 833000000 | F59: 1152000000
A60: Pretax Income | B60: -226000000 | C60: 28225000000 | D60: 53525000000 | E60: 35396000000 | F60: 11142000000
A61: Provision for Income Tax | B61: 1174000000 | C61: -8239000000 | D61: -16770000000 | E61: -10401000000 | F61: -3537000000
A62: Net Income before Extraordinary Items and Discontinued Operations | B62: 948000000 | C62: 19986000000 | D62: 36755000000 | E62: 24995000000 | F62: 7605000000
A63: Net Income after Extraordinary Items and Discontinued Operations | B63: 948000000 | C63: 19986000000 | D63: 36755000000 | E63: 24995000000 | F63: 7605000000
A64: Non-Controlling/Minority Interests | B64: 193000000 | C64: -111000000 | D64: -132000000 | E64: -111000000 | F64: -77000000
A65: Net Income after Non-Controlling/Minority Interests | B65: 1141000000 | C65: 19875000000 | D65: 36623000000 | E65: 24884000000 | F65: 7528000000
A66: Net Income Available to Common Stockholders | B66: 1141000000 | C66: 19875000000 | D66: 36623000000 | E66: 24884000000 | F66: 7528000000
A67: Diluted Net Income Available to Common Stockholders | B67: 1141000000 | C67: 19875000000 | D67: 36623000000 | E67: 24884000000 | F67: 7528000000
A68: Income Statement Supplemental Section
A69: Reported Normalized and Operating Income/Expense Supplemental Section
A70: Total Revenue as Reported, Supplemental | B70: 53683000000 | C70: 83966000000 | D70: 124474000000 | E70: 102409000000 | F70: 91416000000
A71: Reported Effective Tax Rate | B71: 5.195 | C71: 0.29 | D71: 0.313 | E71: 0.294 | F71: 0.317
A72: Reported Normalized EBITDA | B72: 28391000000 | C72: 43558000000 | D72: 66217000000 | E72: 52414000000 | F72: 40399000000
A73: Operating Income/Expense, Supplemental Section
A74: Depreciation, Amortization and Depletion, Supplemental | B74: -12392000000 | C74: -13015000000 | D74: -14695000000
A75: Depreciation and Amortization, Supplemental | B75: -12392000000 | C75: -13015000000 | D75: -14695000000
A76: Depreciation, Supplemental | B76: -12326000000 | C76: -12955000000 | D76: -14618000000
A77: Amortization, Supplemental | B77: -66000000 | C77: -60000000 | D77: -77000000
A78: Discontinued Operations | C78: 0
A79: Basic EPS | B79: 0.09 | C79: 1.52 | D79: 2.81 | E79: 1.91 | F79: 0.58
A80: Basic EPS from Continuing Operations | B80: 0.09 | C80: 1.52 | D80: 2.81 | E80: 1.91 | F80: 0.58
A81: Basic EPS from Discontinued Operations | C81: 0
A82: Diluted EPS | B82: 0.09 | C82: 1.52 | D82: 2.81 | E82: 1.91 | F82: 0.58
A83: Diluted EPS from Continuing Operations | B83: 0.09 | C83: 1.52 | D83: 2.81 | E83: 1.91 | F83: 0.58
A84: Diluted EPS from Discontinued Operations | C84: 0
A85: Basic Weighted Average Shares Outstanding | B85: 13044201262 | C85: 13044201262 | D85: 13044201262 | E85: 13022289244 | F85: 12898762128
A86: Diluted Weighted Average Shares Outstanding | B86: 13044201262 | C86: 13044201262 | D86: 13044201262 | E86: 13022289244 | F86: 12898762128
A87: Total Dividend Per Share | B87: 0.04 | C87: 1.05 | D87: 3.31 | E87: 1.46 | F87: 1.48
A88: Regular Dividend Per Share Calc | B88: 0.04 | C88: 1.05 | D88: 3.31 | E88: 1.46 | F88: 1.21
A89: Special Dividend Per Share Calc | F89: 0.27
A90: Preferred Dividend Per Share
A91: Basic EPS | B91: 0.18 | C91: 3.04 | D91: 5.62 | E91: 3.82 | F91: 1.16
A92: Diluted EPS | B92: 0.18 | C92: 3.04 | D92: 5.62 | E92: 3.82 | F92: 1.16
A93: Basic WASO | B93: 6522100630 | C93: 6522100630 | D93: 6522100630 | E93: 6511144622 | F93: 6449381064
A94: Diluted WASO | B94: 6522100630 | C94: 6522100630 | D94: 6522100630 | E94: 6511144622 | F94: 6449381064
A95: Fiscal year ends in Dec 31 | USD

Sheet Balance Sheet PBR
A1: PBR_balance-sheet_Annual_As_Originally_Reported | B1: 2020 | C1: 2021 | D1: 2022 | E1: 2023 | F1: 2024
A2: Total Assets | B2: 190010000000 | C2: 174348000000 | D2: 187191000000 | E2: 217067000000 | F2: 181645000000
A3: Total Current Assets | B3: 27388000000 | C3: 30149000000 | D3: 31250000000 | E3: 32445000000 | F3: 21836000000
A4: Cash, Cash Equivalents and Short Term Investments | B4: 12370000000 | C4: 11117000000 | D4: 10769000000 | E4: 15546000000 | F4: 7534000000
A5: Cash and Cash Equivalents | B5: 11711000000 | C5: 10467000000 | D5: 7996000000 | E5: 12727000000 | F5: 3271000000
A6: Cash | B6: 552000000 | C6: 299000000 | D6: 216000000 | E6: 103000000 | F6: 136000000
A7: Cash Equivalents | B7: 11159000000 | C7: 10168000000 | D7: 7780000000 | E7: 12624000000 | F7: 3135000000
A8: Short Term Investments | B8: 659000000 | C8: 650000000 | D8: 2773000000 | E8: 2819000000 | F8: 4263000000
A9: Other Short Term Investments | B9: 659000000 | C9: 650000000 | D9: 2773000000 | E9: 2819000000 | F9: 4263000000
A10: Inventories | B10: 5677000000 | C10: 7255000000 | D10: 8779000000 | E10: 7681000000 | F10: 6710000000
A11: l | B11: 954000000 | C11: 804000000 | D11: 1023000000 | E11: 1383000000 | F11: 1356000000
A12: Finished Goods and Merchandise | B12: 4723000000 | C12: 6451000000 | D12: 7756000000 | E12: 6298000000 | F12: 5354000000
A13: Trade and Other Receivables, Current | B13: 7326000000 | C13: 7714000000 | D13: 6317000000 | E13: 7313000000 | F13: 5532000000
... A17: Other Current Assets | B17: 1230000000 | C17: 1573000000 | D17: 1777000000 | E17: 1570000000 | F17: 1550000000
A18: Cash Restricted or Pledged, Current
A19: Prepayments and Deposits, Current
A20: Total Non-Current Assets | B20: 162622000000 | C20: 144199000000 | D20: 155941000000 | E20: 184622000000 | F20: 159809000000
A21: Net Property, Plant and Equipment | B21: 93035000000 | C21: 89483000000 | D21: 91735000000 | E21: 112992000000 | F21: 100364000000
A22: Gross Property, Plant and Equipment | B22: 163973000000 | C22: 154501000000 | D22: 163380000000 | E22: 199103000000 | F22: 173545000000
A23: Properties | B23: 6829000000 | C23: 5833000000 | D23: 6621000000 | E23: 7604000000 | F23: 6235000000
A24: Land and Improvements | B24: 5450000000 | C24: 4080000000 | D24: 4343000000 | E24: 4634000000 | F24: 3895000000
A25: Leasehold and Improvements | B25: 1379000000 | C25: 1753000000 | D25: 2278000000 | E25: 2970000000 | F25: 2340000000
A26: Machinery, Furniture and Equipment | B26: 11257000000 | C26: 11267000000 | D26: 14788000000 | E26: 18000000000 | F26: 17542000000
A27: Flight, Fleet, Vehicle and Related Equipment | B27: 11257000000 | C27: 11267000000 | D27: 14788000000 | E27: 18000000000 | F27: 17542000000
A28: Construction in Progress and Advance Payments | B28: 27544000000 | C28: 25954000000 | D28: 23938000000 | E28: 31467000000 | F28: 30321000000
A29: Leased Property, Plant and Equipment | B29: 11144000000 | C29: 13362000000 | D29: 12604000000 | E29: 23859000000 | F29: 22484000000
A30: Other Property, Plant and Equipment | B30: 107199000000 | C30: 98085000000 | D30: 105429000000 | E30: 118173000000 | F30: 96963000000
A31: Accumulated Depreciation and Impairment | B31: -70938000000 | C31: -65018000000 | D31: -71645000000 | E31: -86111000000 | F31: -73181000000
... A60: Investment in Financial Assets, Non-Current | B60: 44000000 | C60: 44000000 | D60: 1564000000 | E60: 2409000000 | F60: 582000000
A61: Financial Assets Designated as Fair Value Through Profit or Loss, Non-Current | F61: 582000000
A62: Other Financial Assets, Non-Current | B62: 44000000 | C62: 44000000 | D62: 1564000000 | E62: 2409000000
A63: Other Investments, Non-Current | B63: 5000000 | C63: 3000000 | D63: 4000000 | E63: 4000000 | F63: 3000000
A64: Trade and Other Receivables, Non-Current | B64: 5789000000 | C64: 5161000000 | D64: 6218000000 | E64: 6363000000 | F64: 4857000000
A65: Trade/Accounts Receivable, Non-Current | B65: 2631000000 | C65: 1900000000 | D65: 2440000000 | E65: 1847000000 | F65: 1256000000
A66: Taxes Receivable, Non-Current | B66: 3158000000 | C66: 3261000000 | D66: 3778000000 | E66: 4516000000 | F66: 3601000000
A67: Cash Restricted or Pledged, Non-Current | B67: 7281000000 | C67: 8038000000 | D67: 11053000000 | E67: 14746000000 | F67: 11748000000
A68: Deferred Tax Assets, Non-Current | B68: 6451000000 | C68: 604000000 | D68: 832000000 | E68: 965000000 | F68: 922000000
A69: Other Non-Current Assets | B69: 635000000 | C69: 487000000 | D69: 1553000000 | E69: 2315000000 | F69: 2501000000
A70: Prepayments and Deposits, Non-Current
A71: Prepayments, Non-Current
A72: Total Liabilities | B72: 130134000000 | C72: 104536000000 | D72: 117355000000 | E72: 138092000000 | F72: 122295000000
A73: Total Current Liabilities | B73: 26225000000 | C73: 24176000000 | D73: 31380000000 | E73: 33860000000 | F73: 31460000000
A74: Payables and Accrued Expenses, Current | B74: 10551000000 | C74: 10217000000 | D74: 15566000000 | E74: 13818000000 | F74: 13423000000
A75: Trade and Other Payables, Current | B75: 10551000000 | C75: 10217000000 | D75: 15566000000 | E75: 13818000000 | F75: 13423000000
A76: Trade/Accounts Payable, Current | B76: 6859000000 | C76: 5483000000 | D76: 5464000000 | E76: 4813000000 | F76: 6082000000
A77: Dividends Payable, Current | B77: 858000000 | C77: 0 | D77: 4171000000 | E77: 3539000000 | F77: 2657000000
A78: Taxes Payable, Current | B78: 2834000000 | C78: 4734000000 | D78: 5931000000 | E78: 5466000000 | F78: 4684000000
A79: Accrued Expenses, Current
A80: Financial Liabilities, Current | B80: 9884000000 | C80: 9073000000 | D80: 9133000000 | E80: 11522000000 | F80: 11108000000
A81: Current Debt and Capital Lease Obligation | B81: 9884000000 | C81: 9073000000 | D81: 9133000000 | E81: 11522000000 | F81: 11108000000
A82: Current Debt | B82: 1803000000 | C82: 578000000 | D82: 465000000 | E82: 546000000 | F82: 434000000
A83: Other Loans, Current Debt | B83: 1803000000 | C83: 578000000 | D83: 465000000 | E83: 546000000 | F83: 434000000
A84: Current Portion of Long Term Debt and Capital Lease | B84: 8081000000 | C84: 8495000000 | D84: 8668000000 | E84: 10976000000 | F84: 10674000000
A85: Current Portion of Long Term Debt | B85: 2383000000 | C85: 3063000000 | D85: 3111000000 | E85: 3776000000 | F85: 2132000000
A86: Capital Lease Obligations, Current | B86: 5698000000 | C86: 5432000000 | D86: 5557000000 | E86: 7200000000 | F86: 8542000000
A87: Provisions, Current | B87: 3502000000 | C87: 2144000000 | D87: 2215000000 | E87: 4964000000 | F87: 4011000000
A88: Provision for Employee Entitlements, Current | B88: 3502000000 | C88: 2144000000 | D88: 2215000000 | E88: 2932000000 | F88: 2315000000
A89: Pension and Other Post-Retirement Benefit Plans, Current | B89: 1549000000 | C89: 2144000000
A90: Other Employee-Related Liabilities, Current | B90: 1953000000
A91: Provision for Asset Retirement Obligation/Site Restoration and Rehabilitation, Current | E91: 2032000000 | F91: 1696000000
A92: Other Provisions, Current
A93: Discontinued Operations Liabilities, Current | B93: 685000000 | C93: 867000000 | D93: 1465000000 | E93: 541000000 | F93: 713000000
A94: Other Current Liabilities | B94: 1603000000 | C94: 1875000000 | D94: 3001000000 | E94: 3015000000 | F94: 2205000000
A95: Total Non-Current Liabilities | B95: 103909000000 | C95: 80360000000 | D95: 85975000000 | E95: 104232000000 | F95: 90835000000
A96: Financial Liabilities, Non-Current | B96: 65654000000 | C96: 49670000000 | D96: 44666000000 | E96: 51078000000 | F96: 49203000000
A97: Long Term Debt and Capital Lease Obligation | B97: 65654000000 | C97: 49670000000 | D97: 44666000000 | E97: 51078000000 | F97: 49203000000
A98: Long Term Debt | B98: 49702000000 | C98: 32059000000 | D98: 26378000000 | E98: 24479000000 | F98: 20596000000
A99: Notes Payables, Non-Current
A100: Bank/Institutional Loans, Non-Current
A101: Other Loans, Non-Current
A102: Capital Lease Obligations, Non-Current | B102: 15952000000 | C102: 17611000000 | D102: 18288000000 | E102: 26599000000 | F102: 28607000000
A103: Provisions, Non-Current | B103: 35499000000 | C103: 27011000000 | D103: 32285000000 | E103: 40055000000 | F103: 38012000000
A104: Provision for Employee Entitlements, Non-Current | B104: 14520000000 | C104: 9374000000 | D104: 10675000000 | E104: 15579000000 | F104: 10672000000
A105: Pension and Other Post-Retirement Benefit Plans, Non-Current | B105: 14520000000 | C105: 9374000000
A106: Provision for Asset Retirement Obligation/Site Restoration and Rehabilitation, Non-Current | B106: 18780000000 | C106: 15619000000 | D106: 18600000000 | E106: 21171000000 | F106: 24507000000
A107: Other Provisions, Non-Current | B107: 2199000000 | C107: 2018000000 | D107: 3010000000 | E107: 3305000000 | F107: 2833000000
A108: Tax Liabilities, Non-Current | B108: 195000000 | C108: 1229000000 | D108: 6750000000 | E108: 10910000000 | F108: 1470000000
A109: Deferred Tax Liabilities, Non-Current | B109: 195000000 | C109: 1229000000 | D109: 6750000000 | E109: 10910000000 | F109: 1470000000
A110: Payables and Accrued Expenses, Non-Current | B110: 357000000 | C110: 300000000 | D110: 302000000 | E110: 299000000 | F110: 530000000
A111: Trade and Other Payables, Non-Current | B111: 357000000 | C111: 300000000 | D111: 302000000 | E111: 299000000 | F111: 530000000
A112: Taxes Payable, Non-Current | B112: 357000000 | C112: 300000000 | D112: 302000000 | E112: 299000000 | F112: 530000000
A113: Other Non-Current Liabilities | B113: 2204000000 | C113: 2150000000 | D113: 1972000000 | E113: 1890000000 | F113: 1620000000
A114: Total Equity | B114: 59876000000 | C114: 69812000000 | D114: 69836000000 | E114: 78975000000 | F114: 59350000000
A115: Equity Attributable to Parent Stockholders | B115: 59348000000 | C115: 69407000000 | D115: 69492000000 | E115: 78583000000 | F115: 59106000000
A116: Paid in Capital | B116: 107101000000 | C116: 107101000000 | D116: 107101000000 | E116: 107101000000 | F116: 107101000000
A117: Capital Stock | B117: 107101000000 | C117: 107101000000 | D117: 107101000000 | E117: 107101000000 | F117: 107101000000
... A122: Other Reserves/Accum.Comp.Inc | B122: -114734000000 | C122: -111648000000 | D122: -105187000000 | E122: -101569000000 | F122: -109470000000
A123: Other Equity Interest
A124: Non-Controlling/Minority Interests in Equity | B124: 528000000 | C124: 405000000 | D124: 344000000 | E124: 392000000 | F124: 244000000
A125: Debt Maturity Schedule Total | B125: 53888000000 | C125: 35700000000 | D125: 29954000000 | E125: 28801000000 | F125: 23162000000
A126: Debt due in Year 1 | B126: 4186000000 | C126: 3641000000 | D126: 3576000000 | E126: 4322000000 | F126: 2566000000
A127: Debt due in Year 2 | B127: 3282000000 | C127: 2973000000 | D127: 3943000000 | E127: 3066000000 | F127: 1864000000
A128: Debt due in Year 3 | B128: 5892000000 | C128: 3988000000 | D128: 3079000000 | E128: 2551000000 | F128: 2264000000
A129: Debt due in Year 4 | B129: 5961000000 | C129: 3449000000 | D129: 2523000000 | E129: 2547000000 | F129: 1791000000
A130: Debt due in Year 5 | B130: 6229000000 | C130: 2832000000 | D130: 2892000000 | E130: 1816000000 | F130: 1780000000
A131: Debt due Beyond | B131: 28338000000 | C131: 18817000000 | D131: 13941000000 | E131: 14499000000 | F131: 12897000000
A132: Capital Lease Obligation Maturity Schedule Total | B132: 21650000000 | C132: 31427000000 | D132: 23845000000 | E132: 33799000000 | F132: 37149000000
A133: Capital Lease due in Year 1 | B133: 5756000000 | C133: 5567000000 | D133: 5710000000 | E133: 7442000000 | F133: 8837000000
A134: Capital Lease due in Year 2 | B134: 4310000000 | C134: 3944000000 | D134: 4621000000 | E134: 6137000000 | F134: 6140000000
A135: Capital Lease due in Year 3 | B135: 2896000000 | C135: 3027000000 | D135: 3380000000 | E135: 4547000000 | F135: 4817000000
...

Sheet Cash Flow PBR
A1: PBR_cash-flow_Annual_As_Originally_Reported | B1: 2020 | C1: 2021 | D1: 2022 | E1: 2023 | F1: 2024
A2: Cash Flow from Operating Activities, Indirect | B2: 28890000000 | C2: 37791000000 | D2: 49717000000 | E2: 43212000000 | F2: 37984000000
A3: Net Cash Flow from Continuing Operating Activities, Indirect | B3: 28890000000 | C3: 37791000000 | D3: 47087000000 | E3: 43212000000 | F3: 37984000000
A4: Cash Generated from Operating Activities | B4: 29222000000 | C4: 39929000000 | D4: 58603000000 | E4: 53244000000 | F4: 44891000000
A5: Income/Loss before Non-Cash Adjustment | B5: 948000000 | C5: 19986000000 | D5: 36755000000 | E5: 24995000000 | F5: 7605000000
A6: Total Adjustments for Non-Cash Items | B6: 25844000000 | C6: 20501000000 | D6: 31021000000 | E6: 32014000000 | F6: 40959000000
A7: Depreciation, Amortization and Depletion, Non-Cash Adjustment | B7: 11445000000 | C7: 11695000000 | D7: 13218000000 | E7: 13280000000 | F7: 12479000000
A8: Depreciation and Amortization, Non-Cash Adjustment | D8: 13218000000 | E8: 13280000000 | F8: 12479000000
A9: Depreciation, Non-Cash Adjustment | D9: 13141000000 | E9: 13176000000 | F9: 12345000000
A10: Amortization, Non-Cash Adjustment | D10: 77000000 | E10: 104000000 | F10: 134000000
A11: Pension and Employee Benefit Expense, Non-Cash Adjustment | B11: -1001000000 | C11: 2098000000 | D11: 1228000000 | E11: 1542000000 | F11: 2934000000
A12: Deferred Taxes, Non-Cash Adjustment | B12: -4916000000 | C12: 3072000000 | D12: 16769000000 | E12: 10401000000 | F12: 3537000000
A13: Other Provisions, Non-Cash Adjustment | B13: 144000000 | C13: -30000000 | D13: 65000000 | E13: 40000000 | F13: 260000000
A14: Net Investment Income/Loss, Non-Cash Adjustment | B14: 11753000000 | C14: 9188000000 | D14: 4306000000 | E14: 2802000000 | F14: 16034000000
A15: Share of Profit/Loss from Associates, Joint Ventures and other Equity Investments, Non-Cash Adjustment | B15: 659000000 | C15: -1607000000 | D15: -251000000 | E15: 304000000 | F15: 627000000
A16: Net Foreign Currency Exchange Gain/Loss, Non-Cash Adjustment | B16: 11094000000 | C16: 10795000000 | D16: 4557000000 | E16: 2498000000 | F16: 15407000000
A17: Gain/Loss for Other Investment, Non-Cash Adjustment
A18: Irregular Income/Loss, Non-Cash Adjustment | B18: 8419000000 | C18: -4727000000 | D18: -1641000000 | E18: 3436000000 | F18: 4978000000
A19: Gain/Loss on Disposals, Non-Cash Adjustment | B19: -456000000 | C19: -1900000000 | D19: -1144000000 | E19: -1295000000 | F19: -228000000
A20: Gain/Loss on Disposal/Sale of Other Assets, Non-Cash Adjustment | B20: -456000000 | C20: -1900000000 | D20: -1144000000 | E20: -1295000000 | F20: -228000000
A21: Accretion of Asset Retirement Obligation, Non-Cash Adjustment | B21: 981000000 | C21: 661000000 | D21: 745000000 | E21: 2052000000 | F21: 3584000000
A22: Write off/Write down/Impairment of Capital Assets Loss/Reversal, Non-Cash Adjustment | B22: 456000000 | C22: 248000000 | D22: -473000000 | E22: 3204000000 | F22: 482000000
A23: Write Down and Write off of Other Assets, Non-Cash Adjustment | B23: 7714000000 | C23: -3191000000 | D23: -140000000 | E23: -110000000 | F23: 1489000000
A24: Other Irregular Income/Loss, Non-Cash Adjustment | B24: -276000000 | C24: -545000000 | D24: -629000000 | E24: -415000000 | F24: -349000000
A25: Other Non-Cash Items | C25: -795000000 | D25: -2924000000 | E25: 513000000 | F25: 737000000
A26: Changes in Operating Capital | B26: 2430000000 | C26: -558000000 | D26: -9173000000 | E26: -3765000000 | F26: -3673000000
A27: Change in Inventories | B27: 724000000 | C27: -2334000000 | D27: -1217000000 | E27: 1564000000 | F27: -295000000
A28: Change in Trade and Other Receivables | B28: 1000000 | C28: -2075000000 | D28: 355000000 | E28: 88000000 | F28: 1822000000
A29: Change in Cash Restricted or Pledged | B29: -859000000 | C29: -1032000000 | D29: -1709000000 | E29: -1723000000 | F29: 229000000
A30: Change in Other Current Assets | B30: 159000000 | C30: -289000000 | D30: -413000000 | E30: 324000000 | F30: -165000000
A31: Change in Payables and Accrued Expenses | B31: 3462000000 | C31: 8089000000 | D31: -2800000000 | E31: -1385000000 | F31: -2002000000
A32: Change in Trade and Other Payables | B32: 3462000000 | C32: 8089000000 | D32: -2800000000 | E32: -1385000000 | F32: -2002000000
A33: Change in Trade/Accounts Payable | B33: 216000000 | C33: 1073000000 | D33: -359000000 | E33: -954000000 | F33: 986000000
A34: Change in Taxes Payable | B34: 3246000000 | C34: 7016000000 | D34: -2441000000 | E34: -431000000 | F34: -2988000000
A35: Change in Provisions | B35: -1010000000 | C35: -3293000000 | D35: -3294000000 | E35: -2064000000 | F35: -2525000000
A36: Change in Other Current Liabilities | B36: -47000000 | C36: 376000000 | D36: -95000000 | E36: -569000000 | F36: -737000000
A37: Change in Other Operating Capital
A38: Taxes Refund/Paid, Indirect | B38: -332000000 | C38: -2138000000 | D38: -11516000000 | E38: -10032000000 | F38: -6907000000
A39: Net Cash Flow from Discontinuing Operating Activities | C39: 0
A40: Cash Flow from Investing Activities | B40: -4510000000 | C40: 2157000000 | D40: -432000000 | E40: -7955000000 | F40: -13369000000
A41: Cash Flow from Continuing Investing Activities | B41: -4510000000 | C41: 2157000000 | D41: -432000000 | E41: -7955000000 | F41: -13369000000
A42: Purchase/Sale and Disposal of Property, Plant and Equipment, Net | B42: -5874000000 | C42: -6325000000 | D42: -9581000000 | E42: -12114000000 | F42: -14644000000
A43: Purchase of Property, Plant and Equipment | B43: -5874000000 | C43: -6325000000 | D43: -9581000000 | E43: -12114000000 | F43: -14644000000
A44: Purchase of Mineral Properties/Rights/Interests
A45: Purchase/Sale of Equity Investments | B45: -942000000 | C45: -24000000 | D45: -27000000 | E45: -24000000 | F45: -22000000
A46: Purchase of Joint Venture/Associate | B46: -942000000 | C46: -24000000 | D46: -27000000 | E46: -24000000 | F46: -22000000
A47: Purchase/Sale of Investments, Net | B47: 66000000 | C47: 4000000 | D47: -3328000000 | E47: 98000000 | F47: -109000000
A48: Purchase of Investments | D48: -3328000000 | F48: -109000000
A49: Sale of Investments | E49: 98000000
A50: Purchase/Sale of Other Non-Current Assets, Net | B50: 1997000000 | C50: 4783000000 | D50: 4846000000 | E50: 3606000000 | F50: 863000000
A51: Sales of Other Non-Current Assets | B51: 1997000000 | C51: 4783000000 | D51: 4846000000 | E51: 3606000000 | F51: 863000000
A52: Dividends Received/Paid, CFI | B52: 243000000 | C52: 781000000 | D52: 374000000 | E52: 88000000 | F52: 146000000
A53: Other Investing Cash Flow | C53: 2938000000 | D53: 7284000000 | E53: 391000000 | F53: 397000000
A54: Purchase/Sale of Intangibles, Net
A55: Sale of Intangibles
A56: Capital Expenditure, Reported
A57: Net Cash Flow from Discontinuing Investing Activities | C57: 0
A58: Cash Flow from Financing Activities | B58: -19259000000 | C58: -40791000000 | D58: -51453000000 | E58: -30700000000 | F58: -33088000000
A59: Cash Flow from Continuing Financing Activities | B59: -19259000000 | C59: -40791000000 | D59: -51453000000 | E59: -30700000000 | F59: -33088000000
A60: Issuance of/Payments for Common Stock, Net | E60: -735000000 | F60: -380000000
A61: Payments for Common Stock | E61: -735000000 | F61: -380000000
A62: Issuance of/Repayments for Debt, Net | B62: -8704000000 | C62: -19528000000 | D62: -6454000000 | E62: -1983000000 | F62: -4407000000
A63: Issuance of/Repayments for Long Term Debt, Net | B63: -8704000000 | C63: -19528000000 | D63: -6454000000 | E63: -1983000000 | F63: -4407000000
A64: Proceeds from Issuance of Long Term Debt | B64: 17023000000 | C64: 1885000000 | D64: 2880000000 | E64: 2210000000 | F64: 2129000000
A65: Repayments for Long Term Debt | B65: -25727000000 | C65: -21413000000 | D65: -9334000000 | E65: -4193000000 | F65: -6536000000
A66: Issuance of/Repayments for Lease Financing | B66: -5880000000 | C66: -5827000000 | D66: -5430000000 | E66: -6286000000 | F66: -7895000000
A67: Repayments for Lease Financing | B67: -5880000000 | C67: -5827000000 | D67: -5430000000 | E67: -6286000000 | F67: -7895000000
A68: Net Movement in Non-Controlling/Minority Interest | B68: -67000000 | C68: -24000000 | D68: 63000000 | E68: 1000000 | F68: -84000000
A69: Cash Dividends and Interest Paid | B69: -4524000000 | C69: -15307000000 | D69: -39551000000 | E69: -21648000000 | F69: -20245000000
A70: Cash Dividends Paid | B70: -1367000000 | C70: -13078000000 | D70: -37701000000 | E70: -19670000000 | F70: -18327000000
A71: Interest Paid, CFF | B71: -3157000000 | C71: -2229000000 | D71: -1850000000 | E71: -1978000000 | F71: -1918000000
A72: Cash Dividends Paid to Non-Controlling/Minority Interests | B72: -84000000 | C72: -105000000 | D72: -81000000 | E72: -49000000 | F72: -77000000
A73: Other Financing Cash Flow
A74: Net Cash Flow from Discontinuing Financing Activities | C74: 0
A75: Cash and Cash Equivalents, End of Period | B75: 11725000000 | C75: 10480000000 | D75: 7996000000 | E75: 12727000000 | F75: 3271000000
A76: Change in Cash | B76: 5121000000 | C76: -843000000 | D76: -2168000000 | E76: 4557000000 | F76: -8473000000
A77: Effect of Exchange Rate Changes | B77: -773000000 | C77: -402000000 | D77: -316000000 | E77: 174000000 | F77: -983000000
A78: Cash and Cash Equivalents, Beginning of Period | B78: 7377000000 | C78: 11725000000 | D78: 10480000000 | E78: 7996000000 | F78: 12727000000
A79: Cash Flow Supplemental Section
A80: Change in Cash as Reported, Supplemental | B80: 4348000000 | C80: -1245000000 | D80: -2484000000 | E80: 4731000000 | F80: -9456000000
A81: Fiscal year ends in Dec 31 | USD
